Workbook

Sheet GRAFICO
A1: 🗺️ SERVICIO DE MOVILIDAD - CD TOTTUS HUACHIPA
A2: 📍 CD TOTTUS HUACHIPA | Lat: -11.997563 | Long: -76.900062
A4: 📊 ÁREA: | B4: TODOS | D4: STAFF | G4: =IF(B8=0,"⚠️ No hay empleados para: "&B4&" | "&D4,"ÁREA: "&B4&" | TIPO: "&D4&"") -> ÁREA: TODOS | TIPO: STAFF
A6: 📊 RESUMEN | D6: 🏢 DISTANCIA AL CENTRO DE DISTRIBUCIÓN | H6: 🚌 DISTANCIA A PARADEROS MÁS CERCANOS
A7: Métrica | B7: Valor | D7: Clasificación | E7: Empleados | F7: Porcentaje | H7: Clasificación | I7: Empleados | J7: Porcentaje
A8: Total Empleados Analizados | B8: =IF($D$4="TODOS", IF($B$4="TODOS",COUNTA('BD SECOS'!A:A)+COUNTA('BD PPA'!A:A)+COUNTA('BD FRESCOS'!A:A)-3, IF($B$4="SECOS",COUNTA('BD SECOS'!A:A)-1, IF($B$4="PPA",COUNTA('BD PPA'!A:A)-1,COUNTA('BD FRESCOS'!A:A)-1))), IF($B$4="TODOS", COUNTIF('BD SECOS'!AE:AE,$D$4)+COUNTIF('BD PPA'!AK:AK,$D$4)+COUNTIF('BD FRESCOS'!AK:AK,$D$4), IF($B$4="SECOS",COUNTIF('BD SECOS'!AE:AE,$D$4), IF($B$4="PPA",COUNTIF('BD PPA'!AK:AK,$D$4),COUNTIF('BD FRESCOS'!AK:AK,$D$4))))) -> 153 | D8: 🟢 Muy Cerca (0-5 km) | E8: =IF($D$4="TODOS", IF($B$4="TODOS",COUNTIF('BD SECOS'!V:V,"*Muy Cerca*")+COUNTIF('BD PPA'!AB:AB,"*Muy Cerca*")+COUNTIF('BD FRESCOS'!AB:AB,"*Muy Cerca*"), IF($B$4="SECOS",COUNTIF('BD SECOS'!V:V,"*Muy Cerca*"), IF($B$4="PPA",COUNTIF('BD PPA'!AB:AB,"*Muy Cerca*"),COUNTIF('BD FRESCOS'!AB:AB,"*Muy Cerca*")))), IF($B$4="TODOS", COUNTIFS('BD SECOS'!V:V,"*Muy Cerca*",'BD SECOS'!AE:AE,$D$4)+COUNTIFS('BD PPA'!AB:AB,"*Muy Cerca*",'BD PPA'!AK:AK,$D$4)+COUNTIFS('BD FRESCOS'!AB:AB,"*Muy Cerca*",'BD FRESCOS'!AK:AK,$D$4), IF($B$4="SECOS",COUNTIFS('BD SECOS'!V:V,"*Muy Cerca*",'BD SECOS'!AE:AE,$D$4), IF($B$4="PPA",COUNTIFS('BD PPA'!AB:AB,"*Muy Cerca*",'BD PPA'!AK:AK,$D$4),COUNTIFS('BD FRESCOS'!AB:AB,"*Muy Cerca*",'BD FRESCOS'!AK:AK,$D$4))))) -> 18 | F8: =IFERROR(IF($B$8=0,0,E8/$B$8),0) -> 0.11764706 | H8: 🟢 Muy Cerca (0-1 km) | I8: =IF($D$4="TODOS", IF($B$4="TODOS",COUNTIF('BD SECOS'!Z:Z,"*Muy Cerca*")+COUNTIF('BD PPA'!AF:AF,"*Muy Cerca*")+COUNTIF('BD FRESCOS'!AF:AF,"*Muy Cerca*"), IF($B$4="SECOS",COUNTIF('BD SECOS'!Z:Z,"*Muy Cerca*"), IF($B$4="PPA",COUNTIF('BD PPA'!AF:AF,"*Muy Cerca*"),COUNTIF('BD FRESCOS'!AF:AF,"*Muy Cerca*")))), IF($B$4="TODOS", COUNTIFS('BD SECOS'!Z:Z,"*Muy Cerca*",'BD SECOS'!AE:AE,$D$4)+COUNTIFS('BD PPA'!AF:AF,"*Muy Cerca*",'BD PPA'!AK:AK,$D$4)+COUNTIFS('BD FRESCOS'!AF:AF,"*Muy Cerca*",'BD FRESCOS'!AK:AK,$D$4), IF($B$4="SECOS",COUNTIFS('BD SECOS'!Z:Z,"*Muy Cerca*",'BD SECOS'!AE:AE,$D$4), IF($B$4="PPA",COUNTIFS('BD PPA'!AF:AF,"*Muy Cerca*",'BD PPA'!AK:AK,$D$4),COUNTIFS('BD FRESCOS'!AF:AF,"*Muy Cerca*",'BD FRESCOS'!AK:AK,$D$4))))) -> 57 | J8: =IFERROR(IF($B$8=0,0,I8/$B$8),0) -> 0.37254902
A9: Total Distritos | B9: {=IFERROR(IF($D$4="TODOS",IF($B$4="TODOS",ROWS(_xlfn.UNIQUE(_xlfn.VSTACK('BD SECOS'!Q2:Q455,'BD PPA'!U2:U386,'BD FRESCOS'!U2:U236))),IF($B$4="SECOS",SUMPRODUCT(1/COUNTIF('BD SECOS'!Q2:Q455,'BD SECOS'!Q2:Q455)),IF($B$4="PPA",SUMPRODUCT(1/COUNTIF('BD PPA'!U2:U386,'BD PPA'!U2:U386)),SUMPRODUCT(1/COUNTIF('BD FRESCOS'!U2:U236,'BD FRESCOS'!U2:U236))))),IF($B$4="TODOS",ROWS(_xlfn.UNIQUE(_xlfn._xlws.FILTER(_xlfn.VSTACK('BD SECOS'!Q2:Q455,'BD PPA'!U2:U386,'BD FRESCOS'!U2:U236),_xlfn.VSTACK('BD SECOS'!AE2:AE455,'BD PPA'!AK2:AK386,'BD FRESCOS'!AK2:AK236)=$D$4))),IF($B$4="SECOS",ROWS(_xlfn.UNIQUE(_xlfn._xlws.FILTER('BD SECOS'!Q2:Q455,'BD SECOS'!AE2:AE455=$D$4))),IF($B$4="PPA",ROWS(_xlfn.UNIQUE(_xlfn._xlws.FILTER('BD PPA'!U2:U386,'BD PPA'!AK2:AK386=$D$4))),ROWS(_xlfn.UNIQUE(_xlfn._xlws.FILTER('BD FRESCOS'!U2:U236,'BD FRESCOS'!AK2:AK236=$D$4))))))),0)} -> 33 | D9: 🟡 Cerca (5-10 km) | E9: =IF($D$4="TODOS", IF($B$4="TODOS",COUNTIF('BD SECOS'!V:V,"*Cerca (5*")+COUNTIF('BD PPA'!AB:AB,"*Cerca (5*")+COUNTIF('BD FRESCOS'!AB:AB,"*Cerca (5*"), IF($B$4="SECOS",COUNTIF('BD SECOS'!V:V,"*Cerca (5*"), IF($B$4="PPA",COUNTIF('BD PPA'!AB:AB,"*Cerca (5*"),COUNTIF('BD FRESCOS'!AB:AB,"*Cerca (5*")))), IF($B$4="TODOS", COUNTIFS('BD SECOS'!V:V,"*Cerca (5*",'BD SECOS'!AE:AE,$D$4)+COUNTIFS('BD PPA'!AB:AB,"*Cerca (5*",'BD PPA'!AK:AK,$D$4)+COUNTIFS('BD FRESCOS'!AB:AB,"*Cerca (5*",'BD FRESCOS'!AK:AK,$D$4), IF($B$4="SECOS",COUNTIFS('BD SECOS'!V:V,"*Cerca (5*",'BD SECOS'!AE:AE,$D$4), IF($B$4="PPA",COUNTIFS('BD PPA'!AB:AB,"*Cerca (5*",'BD PPA'!AK:AK,$D$4),COUNTIFS('BD FRESCOS'!AB:AB,"*Cerca (5*",'BD FRESCOS'!AK:AK,$D$4))))) -> 30 | F9: =IFERROR(IF($B$8=0,0,E9/$B$8),0) -> 0.19607843 | H9: 🟡 Cerca (1-3 km) | I9: =IF($D$4="TODOS", IF($B$4="TODOS",COUNTIF('BD SECOS'!Z:Z,"*Cerca (1*")+COUNTIF('BD PPA'!AF:AF,"*Cerca (1*")+COUNTIF('BD FRESCOS'!AF:AF,"*Cerca (1*"), IF($B$4="SECOS",COUNTIF('BD SECOS'!Z:Z,"*Cerca (1*"), IF($B$4="PPA",COUNTIF('BD PPA'!AF:AF,"*Cerca (1*"),COUNTIF('BD FRESCOS'!AF:AF,"*Cerca (1*")))), IF($B$4="TODOS", COUNTIFS('BD SECOS'!Z:Z,"*Cerca (1*",'BD SECOS'!AE:AE,$D$4)+COUNTIFS('BD PPA'!AF:AF,"*Cerca (1*",'BD PPA'!AK:AK,$D$4)+COUNTIFS('BD FRESCOS'!AF:AF,"*Cerca (1*",'BD FRESCOS'!AK:AK,$D$4), IF($B$4="SECOS",COUNTIFS('BD SECOS'!Z:Z,"*Cerca (1*",'BD SECOS'!AE:AE,$D$4), IF($B$4="PPA",COUNTIFS('BD PPA'!AF:AF,"*Cerca (1*",'BD PPA'!AK:AK,$D$4),COUNTIFS('BD FRESCOS'!AF:AF,"*Cerca (1*",'BD FRESCOS'!AK:AK,$D$4))))) -> 70 | J9: =IFERROR(IF($B$8=0,0,I9/$B$8),0) -> 0.45751634
A10: Distancia Promedio al CD | B10: {=IFERROR(IF($D$4="TODOS",IF($B$4="TODOS",AVERAGE('BD SECOS'!U2:U455,'BD PPA'!AA2:AA386,'BD FRESCOS'!AA2:AA236),IF($B$4="SECOS",AVERAGE('BD SECOS'!U2:U455),IF($B$4="PPA",AVERAGE('BD PPA'!AA2:AA386),AVERAGE('BD FRESCOS'!AA2:AA236)))),IF($B$4="TODOS",(SUMPRODUCT(('BD SECOS'!AE2:AE455=$D$4)*'BD SECOS'!U2:U455)+SUMPRODUCT(('BD PPA'!AK2:AK386=$D$4)*'BD PPA'!AA2:AA386)+SUMPRODUCT(('BD FRESCOS'!AK2:AK236=$D$4)*'BD FRESCOS'!AA2:AA236))/(COUNTIF('BD SECOS'!AE2:AE455,$D$4)+COUNTIF('BD PPA'!AK2:AK386,$D$4)+COUNTIF('BD FRESCOS'!AK2:AK236,$D$4)),IF($B$4="SECOS",AVERAGEIF('BD SECOS'!AE2:AE455,$D$4,'BD SECOS'!U2:U455),IF($B$4="PPA",AVERAGEIF('BD PPA'!AK2:AK386,$D$4,'BD PPA'!AA2:AA386),AVERAGEIF('BD FRESCOS'!AK2:AK236,$D$4,'BD FRESCOS'!AA2:AA236))))),"N/A")} -> 13.941503 | D10: 🟠 Moderada (10-20 km) | E10: =IF($D$4="TODOS", IF($B$4="TODOS",COUNTIF('BD SECOS'!V:V,"*Moderada*")+COUNTIF('BD PPA'!AB:AB,"*Moderada*")+COUNTIF('BD FRESCOS'!AB:AB,"*Moderada*"), IF($B$4="SECOS",COUNTIF('BD SECOS'!V:V,"*Moderada*"), IF($B$4="PPA",COUNTIF('BD PPA'!AB:AB,"*Moderada*"),COUNTIF('BD FRESCOS'!AB:AB,"*Moderada*")))), IF($B$4="TODOS", COUNTIFS('BD SECOS'!V:V,"*Moderada*",'BD SECOS'!AE:AE,$D$4)+COUNTIFS('BD PPA'!AB:AB,"*Moderada*",'BD PPA'!AK:AK,$D$4)+COUNTIFS('BD FRESCOS'!AB:AB,"*Moderada*",'BD FRESCOS'!AK:AK,$D$4), IF($B$4="SECOS",COUNTIFS('BD SECOS'!V:V,"*Moderada*",'BD SECOS'!AE:AE,$D$4), IF($B$4="PPA",COUNTIFS('BD PPA'!AB:AB,"*Moderada*",'BD PPA'!AK:AK,$D$4),COUNTIFS('BD FRESCOS'!AB:AB,"*Moderada*",'BD FRESCOS'!AK:AK,$D$4))))) -> 72 | F10: =IFERROR(IF($B$8=0,0,E10/$B$8),0) -> 0.47058824 | H10: 🟠 Moderada (3-5 km) | I10: =IF($D$4="TODOS", IF($B$4="TODOS",COUNTIF('BD SECOS'!Z:Z,"*Moderada*")+COUNTIF('BD PPA'!AF:AF,"*Moderada*")+COUNTIF('BD FRESCOS'!AF:AF,"*Moderada*"), IF($B$4="SECOS",COUNTIF('BD SECOS'!Z:Z,"*Moderada*"), IF($B$4="PPA",COUNTIF('BD PPA'!AF:AF,"*Moderada*"),COUNTIF('BD FRESCOS'!AF:AF,"*Moderada*")))), IF($B$4="TODOS", COUNTIFS('BD SECOS'!Z:Z,"*Moderada*",'BD SECOS'!AE:AE,$D$4)+COUNTIFS('BD PPA'!AF:AF,"*Moderada*",'BD PPA'!AK:AK,$D$4)+COUNTIFS('BD FRESCOS'!AF:AF,"*Moderada*",'BD FRESCOS'!AK:AK,$D$4), IF($B$4="SECOS",COUNTIFS('BD SECOS'!Z:Z,"*Moderada*",'BD SECOS'!AE:AE,$D$4), IF($B$4="PPA",COUNTIFS('BD PPA'!AF:AF,"*Moderada*",'BD PPA'!AK:AK,$D$4),COUNTIFS('BD FRESCOS'!AF:AF,"*Moderada*",'BD FRESCOS'!AK:AK,$D$4))))) -> 15 | J10: =IFERROR(IF($B$8=0,0,I10/$B$8),0) -> 0.098039216
A11: Distancia Promedio a Paradero | B11: {=IFERROR(IF($D$4="TODOS",IF($B$4="TODOS",AVERAGE('BD SECOS'!Y2:Y455,'BD PPA'!AE2:AE386,'BD FRESCOS'!AE2:AE236),IF($B$4="SECOS",AVERAGE('BD SECOS'!Y2:Y455),IF($B$4="PPA",AVERAGE('BD PPA'!AE2:AE386),AVERAGE('BD FRESCOS'!AE2:AE236)))),IF($B$4="TODOS",(SUMPRODUCT(('BD SECOS'!AE2:AE455=$D$4)*'BD SECOS'!Y2:Y455)+SUMPRODUCT(('BD PPA'!AK2:AK386=$D$4)*'BD PPA'!AE2:AE386)+SUMPRODUCT(('BD FRESCOS'!AK2:AK236=$D$4)*'BD FRESCOS'!AE2:AE236))/(COUNTIF('BD SECOS'!AE2:AE455,$D$4)+COUNTIF('BD PPA'!AK2:AK386,$D$4)+COUNTIF('BD FRESCOS'!AK2:AK236,$D$4)),IF($B$4="SECOS",AVERAGEIF('BD SECOS'!AE2:AE455,$D$4,'BD SECOS'!Y2:Y455),IF($B$4="PPA",AVERAGEIF('BD PPA'!AK2:AK386,$D$4,'BD PPA'!AE2:AE386),AVERAGEIF('BD FRESCOS'!AK2:AK236,$D$4,'BD FRESCOS'!AE2:AE236))))),"N/A")} -> 1.9980392 | D11: 🔴 Lejos (>20 km) | E11: =IF($D$4="TODOS", IF($B$4="TODOS",COUNTIF('BD SECOS'!V:V,"*Lejos*")+COUNTIF('BD PPA'!AB:AB,"*Lejos*")+COUNTIF('BD FRESCOS'!AB:AB,"*Lejos*"), IF($B$4="SECOS",COUNTIF('BD SECOS'!V:V,"*Lejos*"), IF($B$4="PPA",COUNTIF('BD PPA'!AB:AB,"*Lejos*"),COUNTIF('BD FRESCOS'!AB:AB,"*Lejos*")))), IF($B$4="TODOS", COUNTIFS('BD SECOS'!V:V,"*Lejos*",'BD SECOS'!AE:AE,$D$4)+COUNTIFS('BD PPA'!AB:AB,"*Lejos*",'BD PPA'!AK:AK,$D$4)+COUNTIFS('BD FRESCOS'!AB:AB,"*Lejos*",'BD FRESCOS'!AK:AK,$D$4), IF($B$4="SECOS",COUNTIFS('BD SECOS'!V:V,"*Lejos*",'BD SECOS'!AE:AE,$D$4), IF($B$4="PPA",COUNTIFS('BD PPA'!AB:AB,"*Lejos*",'BD PPA'!AK:AK,$D$4),COUNTIFS('BD FRESCOS'!AB:AB,"*Lejos*",'BD FRESCOS'!AK:AK,$D$4))))) -> 33 | F11: =IFERROR(IF($B$8=0,0,E11/$B$8),0) -> 0.21568627 | H11: 🔴 Lejos (>5 km) | I11: =IF($D$4="TODOS", IF($B$4="TODOS",COUNTIF('BD SECOS'!Z:Z,"*Lejos*")+COUNTIF('BD PPA'!AF:AF,"*Lejos*")+COUNTIF('BD FRESCOS'!AF:AF,"*Lejos*"), IF($B$4="SECOS",COUNTIF('BD SECOS'!Z:Z,"*Lejos*"), IF($B$4="PPA",COUNTIF('BD PPA'!AF:AF,"*Lejos*"),COUNTIF('BD FRESCOS'!AF:AF,"*Lejos*")))), IF($B$4="TODOS", COUNTIFS('BD SECOS'!Z:Z,"*Lejos*",'BD SECOS'!AE:AE,$D$4)+COUNTIFS('BD PPA'!AF:AF,"*Lejos*",'BD PPA'!AK:AK,$D$4)+COUNTIFS('BD FRESCOS'!AF:AF,"*Lejos*",'BD FRESCOS'!AK:AK,$D$4), IF($B$4="SECOS",COUNTIFS('BD SECOS'!Z:Z,"*Lejos*",'BD SECOS'!AE:AE,$D$4), IF($B$4="PPA",COUNTIFS('BD PPA'!AF:AF,"*Lejos*",'BD PPA'!AK:AK,$D$4),COUNTIFS('BD FRESCOS'!AF:AF,"*Lejos*",'BD FRESCOS'!AK:AK,$D$4))))) -> 11 | J11: =IFERROR(IF($B$8=0,0,I11/$B$8),0) -> 0.071895425
A12: Total Rutas Utilizadas (según filtros) | B12: =COUNTIF($W$98:$W$111,">0") -> 0
A17: 🏆 TOP 10 DISTRITOS CON MAYOR VOLUMEN DE EMPLEADOS | F17: 🚌 RUTAS DISPONIBLES | K17: 📍 TOP 10 PARADEROS MÁS CERCANOS A EMPLEADOS
A18: # | B18: Distrito | C18: Empleados | D18: Porcentaje | F18: # | G18: Ruta | H18: Empleados | I18: % Total | K18: # | L18: Paradero | M18: Ruta | N18: Empleados | O18: % Total
A19: 1 | B19: =IFERROR(INDEX(Distritos!$H$7:$H$51,MATCH(SMALL(Distritos!$J$7:$J$51,1),Distritos!$J$7:$J$51,0)),"") -> Ate | C19: =IFERROR(INDEX(Distritos!$I$7:$I$51,MATCH(SMALL(Distritos!$J$7:$J$51,1),Distritos!$J$7:$J$51,0)),0) -> 25 | D19: =IFERROR(IF(OR($B$8=0,C19="",C19=0),0,C19/$B$8),0) -> 0.16339869 | F19: 1 | G19: =IFERROR(INDEX(Distritos!$L$7:$L$20,MATCH(SMALL(Distritos!$N$7:$N$20,1),Distritos!$N$7:$N$20,0)),"") -> RUTA 7 | H19: =IFERROR(INDEX(Distritos!$M$7:$M$20,MATCH(SMALL(Distritos!$N$7:$N$20,1),Distritos!$N$7:$N$20,0)),0) -> 29 | I19: =IFERROR(IF(OR($B$8=0,H19="",H19=0),0,H19/$B$8),0) -> 0.18954248 | K19: 1 | L19: =IFERROR(INDEX(Distritos!$O$7:$O$46,MATCH(SMALL(Distritos!$R$7:$R$46,1),Distritos!$R$7:$R$46,0)),"") -> Paradero Arco San Antonio | M19: =IFERROR(INDEX(Distritos!$P$7:$P$46,MATCH(SMALL(Distritos!$R$7:$R$46,1),Distritos!$R$7:$R$46,0)),"") -> RUTA 2 | N19: =IFERROR(INDEX(Distritos!$Q$7:$Q$46,MATCH(SMALL(Distritos!$R$7:$R$46,1),Distritos!$R$7:$R$46,0)),0) -> 8 | O19: =IFERROR(IF(OR($B$8=0,N19="",N19=0),0,N19/$B$8),0) -> 0.052287582
A20: 2 | B20: =IFERROR(INDEX(Distritos!$H$7:$H$51,MATCH(SMALL(Distritos!$J$7:$J$51,2),Distritos!$J$7:$J$51,0)),"") -> San Juan De Lurigancho | C20: =IFERROR(INDEX(Distritos!$I$7:$I$51,MATCH(SMALL(Distritos!$J$7:$J$51,2),Distritos!$J$7:$J$51,0)),0) -> 22 | D20: =IFERROR(IF(OR($B$8=0,C20="",C20=0),0,C20/$B$8),0) -> 0.14379085 | F20: 2 | G20: =IFERROR(INDEX(Distritos!$L$7:$L$20,MATCH(SMALL(Distritos!$N$7:$N$20,2),Distritos!$N$7:$N$20,0)),"") -> RUTA 4A | H20: =IFERROR(INDEX(Distritos!$M$7:$M$20,MATCH(SMALL(Distritos!$N$7:$N$20,2),Distritos!$N$7:$N$20,0)),0) -> 18 | I20: =IFERROR(IF(OR($B$8=0,H20="",H20=0),0,H20/$B$8),0) -> 0.11764706 | K20: 2 | L20: =IFERROR(INDEX(Distritos!$O$7:$O$46,MATCH(SMALL(Distritos!$R$7:$R$46,2),Distritos!$R$7:$R$46,0)),"") -> Paradero Berlín con Javier prado (cruzando el semáforo) aplica solo al ingreso. | M20: =IFERROR(INDEX(Distritos!$P$7:$P$46,MATCH(SMALL(Distritos!$R$7:$R$46,2),Distritos!$R$7:$R$46,0)),"") -> RUTA 4A | N20: =IFERROR(INDEX(Distritos!$Q$7:$Q$46,MATCH(SMALL(Distritos!$R$7:$R$46,2),Distritos!$R$7:$R$46,0)),0) -> 7 | O20: =IFERROR(IF(OR($B$8=0,N20="",N20=0),0,N20/$B$8),0) -> 0.045751634
A21: 3 | B21: =IFERROR(INDEX(Distritos!$H$7:$H$51,MATCH(SMALL(Distritos!$J$7:$J$51,3),Distritos!$J$7:$J$51,0)),"") -> Lurigancho | C21: =IFERROR(INDEX(Distritos!$I$7:$I$51,MATCH(SMALL(Distritos!$J$7:$J$51,3),Distritos!$J$7:$J$51,0)),0) -> 21 | D21: =IFERROR(IF(OR($B$8=0,C21="",C21=0),0,C21/$B$8),0) -> 0.1372549 | F21: 3 | G21: =IFERROR(INDEX(Distritos!$L$7:$L$20,MATCH(SMALL(Distritos!$N$7:$N$20,3),Distritos!$N$7:$N$20,0)),"") -> RUTA 8 | H21: =IFERROR(INDEX(Distritos!$M$7:$M$20,MATCH(SMALL(Distritos!$N$7:$N$20,3),Distritos!$N$7:$N$20,0)),0) -> 17 | I21: =IFERROR(IF(OR($B$8=0,H21="",H21=0),0,H21/$B$8),0) -> 0.11111111 | K21: 3 | L21: =IFERROR(INDEX(Distritos!$O$7:$O$46,MATCH(SMALL(Distritos!$R$7:$R$46,3),Distritos!$R$7:$R$46,0)),"") -> Real Plaza Puruchuco (Grifo Primax) | M21: =IFERROR(INDEX(Distritos!$P$7:$P$46,MATCH(SMALL(Distritos!$R$7:$R$46,3),Distritos!$R$7:$R$46,0)),"") -> RUTA 4A | N21: =IFERROR(INDEX(Distritos!$Q$7:$Q$46,MATCH(SMALL(Distritos!$R$7:$R$46,3),Distritos!$R$7:$R$46,0)),0) -> 5 | O21: =IFERROR(IF(OR($B$8=0,N21="",N21=0),0,N21/$B$8),0) -> 0.032679739
A22: 4 | B22: =IFERROR(INDEX(Distritos!$H$7:$H$51,MATCH(SMALL(Distritos!$J$7:$J$51,4),Distritos!$J$7:$J$51,0)),"") -> Lima | C22: =IFERROR(INDEX(Distritos!$I$7:$I$51,MATCH(SMALL(Distritos!$J$7:$J$51,4),Distritos!$J$7:$J$51,0)),0) -> 10 | D22: =IFERROR(IF(OR($B$8=0,C22="",C22=0),0,C22/$B$8),0) -> 0.065359477 | F22: 4 | G22: =IFERROR(INDEX(Distritos!$L$7:$L$20,MATCH(SMALL(Distritos!$N$7:$N$20,4),Distritos!$N$7:$N$20,0)),"") -> RUTA 5B | H22: =IFERROR(INDEX(Distritos!$M$7:$M$20,MATCH(SMALL(Distritos!$N$7:$N$20,4),Distritos!$N$7:$N$20,0)),0) -> 12 | I22: =IFERROR(IF(OR($B$8=0,H22="",H22=0),0,H22/$B$8),0) -> 0.078431373 | K22: 4 | L22: =IFERROR(INDEX(Distritos!$O$7:$O$46,MATCH(SMALL(Distritos!$R$7:$R$46,4),Distritos!$R$7:$R$46,0)),"") -> Real Plaza Puruchuco (Grifo Primax) | M22: =IFERROR(INDEX(Distritos!$P$7:$P$46,MATCH(SMALL(Distritos!$R$7:$R$46,4),Distritos!$R$7:$R$46,0)),"") -> RUTA 4A | N22: =IFERROR(INDEX(Distritos!$Q$7:$Q$46,MATCH(SMALL(Distritos!$R$7:$R$46,4),Distritos!$R$7:$R$46,0)),0) -> 5 | O22: =IFERROR(IF(OR($B$8=0,N22="",N22=0),0,N22/$B$8),0) -> 0.032679739
A23: 5 | B23: =IFERROR(INDEX(Distritos!$H$7:$H$51,MATCH(SMALL(Distritos!$J$7:$J$51,5),Distritos!$J$7:$J$51,0)),"") -> Santiago De Surco | C23: =IFERROR(INDEX(Distritos!$I$7:$I$51,MATCH(SMALL(Distritos!$J$7:$J$51,5),Distritos!$J$7:$J$51,0)),0) -> 7 | D23: =IFERROR(IF(OR($B$8=0,C23="",C23=0),0,C23/$B$8),0) -> 0.045751634 | F23: 5 | G23: =IFERROR(INDEX(Distritos!$L$7:$L$20,MATCH(SMALL(Distritos!$N$7:$N$20,5),Distritos!$N$7:$N$20,0)),"") -> RUTA 3 | H23: =IFERROR(INDEX(Distritos!$M$7:$M$20,MATCH(SMALL(Distritos!$N$7:$N$20,5),Distritos!$N$7:$N$20,0)),0) -> 11 | I23: =IFERROR(IF(OR($B$8=0,H23="",H23=0),0,H23/$B$8),0) -> 0.071895425 | K23: 5 | L23: =IFERROR(INDEX(Distritos!$O$7:$O$46,MATCH(SMALL(Distritos!$R$7:$R$46,5),Distritos!$R$7:$R$46,0)),"") -> Real Plaza Puruchuco (Grifo Primax) | M23: =IFERROR(INDEX(Distritos!$P$7:$P$46,MATCH(SMALL(Distritos!$R$7:$R$46,5),Distritos!$R$7:$R$46,0)),"") -> RUTA 4A | N23: =IFERROR(INDEX(Distritos!$Q$7:$Q$46,MATCH(SMALL(Distritos!$R$7:$R$46,5),Distritos!$R$7:$R$46,0)),0) -> 5 | O23: =IFERROR(IF(OR($B$8=0,N23="",N23=0),0,N23/$B$8),0) -> 0.032679739
A24: 6 | B24: =IFERROR(INDEX(Distritos!$H$7:$H$51,MATCH(SMALL(Distritos!$J$7:$J$51,6),Distritos!$J$7:$J$51,0)),"") -> Callao | C24: =IFERROR(INDEX(Distritos!$I$7:$I$51,MATCH(SMALL(Distritos!$J$7:$J$51,6),Distritos!$J$7:$J$51,0)),0) -> 6 | D24: =IFERROR(IF(OR($B$8=0,C24="",C24=0),0,C24/$B$8),0) -> 0.039215686 | F24: 6 | G24: =IFERROR(INDEX(Distritos!$L$7:$L$20,MATCH(SMALL(Distritos!$N$7:$N$20,6),Distritos!$N$7:$N$20,0)),"") -> RUTA 3 | H24: =IFERROR(INDEX(Distritos!$M$7:$M$20,MATCH(SMALL(Distritos!$N$7:$N$20,6),Distritos!$N$7:$N$20,0)),0) -> 11 | I24: =IFERROR(IF(OR($B$8=0,H24="",H24=0),0,H24/$B$8),0) -> 0.071895425 | K24: 6 | L24: =IFERROR(INDEX(Distritos!$O$7:$O$46,MATCH(SMALL(Distritos!$R$7:$R$46,6),Distritos!$R$7:$R$46,0)),"") -> Paradero Rompemuelle | M24: =IFERROR(INDEX(Distritos!$P$7:$P$46,MATCH(SMALL(Distritos!$R$7:$R$46,6),Distritos!$R$7:$R$46,0)),"") -> RUTA 3 | N24: =IFERROR(INDEX(Distritos!$Q$7:$Q$46,MATCH(SMALL(Distritos!$R$7:$R$46,6),Distritos!$R$7:$R$46,0)),0) -> 4 | O24: =IFERROR(IF(OR($B$8=0,N24="",N24=0),0,N24/$B$8),0) -> 0.026143791
A25: 7 | B25: =IFERROR(INDEX(Distritos!$H$7:$H$51,MATCH(SMALL(Distritos!$J$7:$J$51,7),Distritos!$J$7:$J$51,0)),"") -> Los Olivos | C25: =IFERROR(INDEX(Distritos!$I$7:$I$51,MATCH(SMALL(Distritos!$J$7:$J$51,7),Distritos!$J$7:$J$51,0)),0) -> 6 | D25: =IFERROR(IF(OR($B$8=0,C25="",C25=0),0,C25/$B$8),0) -> 0.039215686 | F25: 7 | G25: =IFERROR(INDEX(Distritos!$L$7:$L$20,MATCH(SMALL(Distritos!$N$7:$N$20,7),Distritos!$N$7:$N$20,0)),"") -> RUTA 3 | H25: =IFERROR(INDEX(Distritos!$M$7:$M$20,MATCH(SMALL(Distritos!$N$7:$N$20,7),Distritos!$N$7:$N$20,0)),0) -> 11 | I25: =IFERROR(IF(OR($B$8=0,H25="",H25=0),0,H25/$B$8),0) -> 0.071895425 | K25: 7 | L25: =IFERROR(INDEX(Distritos!$O$7:$O$46,MATCH(SMALL(Distritos!$R$7:$R$46,7),Distritos!$R$7:$R$46,0)),"") -> Paradero Rompemuelle | M25: =IFERROR(INDEX(Distritos!$P$7:$P$46,MATCH(SMALL(Distritos!$R$7:$R$46,7),Distritos!$R$7:$R$46,0)),"") -> RUTA 3 | N25: =IFERROR(INDEX(Distritos!$Q$7:$Q$46,MATCH(SMALL(Distritos!$R$7:$R$46,7),Distritos!$R$7:$R$46,0)),0) -> 4 | O25: =IFERROR(IF(OR($B$8=0,N25="",N25=0),0,N25/$B$8),0) -> 0.026143791
A26: 8 | B26: =IFERROR(INDEX(Distritos!$H$7:$H$51,MATCH(SMALL(Distritos!$J$7:$J$51,8),Distritos!$J$7:$J$51,0)),"") -> Carabayllo | C26: =IFERROR(INDEX(Distritos!$I$7:$I$51,MATCH(SMALL(Distritos!$J$7:$J$51,8),Distritos!$J$7:$J$51,0)),0) -> 4 | D26: =IFERROR(IF(OR($B$8=0,C26="",C26=0),0,C26/$B$8),0) -> 0.026143791 | F26: 8 | G26: =IFERROR(INDEX(Distritos!$L$7:$L$20,MATCH(SMALL(Distritos!$N$7:$N$20,8),Distritos!$N$7:$N$20,0)),"") -> RUTA 4B | H26: =IFERROR(INDEX(Distritos!$M$7:$M$20,MATCH(SMALL(Distritos!$N$7:$N$20,8),Distritos!$N$7:$N$20,0)),0) -> 10 | I26: =IFERROR(IF(OR($B$8=0,H26="",H26=0),0,H26/$B$8),0) -> 0.065359477 | K26: 8 | L26: =IFERROR(INDEX(Distritos!$O$7:$O$46,MATCH(SMALL(Distritos!$R$7:$R$46,8),Distritos!$R$7:$R$46,0)),"") -> Paradero Rompemuelle | M26: =IFERROR(INDEX(Distritos!$P$7:$P$46,MATCH(SMALL(Distritos!$R$7:$R$46,8),Distritos!$R$7:$R$46,0)),"") -> RUTA 3 | N26: =IFERROR(INDEX(Distritos!$Q$7:$Q$46,MATCH(SMALL(Distritos!$R$7:$R$46,8),Distritos!$R$7:$R$46,0)),0) -> 4 | O26: =IFERROR(IF(OR($B$8=0,N26="",N26=0),0,N26/$B$8),0) -> 0.026143791
A27: 9 | B27: =IFERROR(INDEX(Distritos!$H$7:$H$51,MATCH(SMALL(Distritos!$J$7:$J$51,9),Distritos!$J$7:$J$51,0)),"") -> Chaclacayo | C27: =IFERROR(INDEX(Distritos!$I$7:$I$51,MATCH(SMALL(Distritos!$J$7:$J$51,9),Distritos!$J$7:$J$51,0)),0) -> 4 | D27: =IFERROR(IF(OR($B$8=0,C27="",C27=0),0,C27/$B$8),0) -> 0.026143791 | F27: 9 | G27: =IFERROR(INDEX(Distritos!$L$7:$L$20,MATCH(SMALL(Distritos!$N$7:$N$20,9),Distritos!$N$7:$N$20,0)),"") -> RUTA 2 | H27: =IFERROR(INDEX(Distritos!$M$7:$M$20,MATCH(SMALL(Distritos!$N$7:$N$20,9),Distritos!$N$7:$N$20,0)),0) -> 8 | I27: =IFERROR(IF(OR($B$8=0,H27="",H27=0),0,H27/$B$8),0) -> 0.052287582 | K27: 9 | L27: =IFERROR(INDEX(Distritos!$O$7:$O$46,MATCH(SMALL(Distritos!$R$7:$R$46,9),Distritos!$R$7:$R$46,0)),"") -> Paradero Rompemuelle | M27: =IFERROR(INDEX(Distritos!$P$7:$P$46,MATCH(SMALL(Distritos!$R$7:$R$46,9),Distritos!$R$7:$R$46,0)),"") -> RUTA 3 | N27: =IFERROR(INDEX(Distritos!$Q$7:$Q$46,MATCH(SMALL(Distritos!$R$7:$R$46,9),Distritos!$R$7:$R$46,0)),0) -> 4 | O27: =IFERROR(IF(OR($B$8=0,N27="",N27=0),0,N27/$B$8),0) -> 0.026143791
A28: 10 | B28: =IFERROR(INDEX(Distritos!$H$7:$H$51,MATCH(SMALL(Distritos!$J$7:$J$51,10),Distritos!$J$7:$J$51,0)),"") -> San Juan De Miraflores | C28: =IFERROR(INDEX(Distritos!$I$7:$I$51,MATCH(SMALL(Distritos!$J$7:$J$51,10),Distritos!$J$7:$J$51,0)),0) -> 4 | D28: =IFERROR(IF(OR($B$8=0,C28="",C28=0),0,C28/$B$8),0) -> 0.026143791 | F28: 10 | G28: =IFERROR(INDEX(Distritos!$L$7:$L$20,MATCH(SMALL(Distritos!$N$7:$N$20,10),Distritos!$N$7:$N$20,0)),"") -> RUTA 2 | H28: =IFERROR(INDEX(Distritos!$M$7:$M$20,MATCH(SMALL(Distritos!$N$7:$N$20,10),Distritos!$N$7:$N$20,0)),0) -> 8 | I28: =IFERROR(IF(OR($B$8=0,H28="",H28=0),0,H28/$B$8),0) -> 0.052287582 | K28: 10 | L28: =IFERROR(INDEX(Distritos!$O$7:$O$46,MATCH(SMALL(Distritos!$R$7:$R$46,10),Distritos!$R$7:$R$46,0)),"") -> Paradero Rompemuelle | M28: =IFERROR(INDEX(Distritos!$P$7:$P$46,MATCH(SMALL(Distritos!$R$7:$R$46,10),Distritos!$R$7:$R$46,0)),"") -> RUTA 3 | N28: =IFERROR(INDEX(Distritos!$Q$7:$Q$46,MATCH(SMALL(Distritos!$R$7:$R$46,10),Distritos!$R$7:$R$46,0)),0) -> 4 | O28: =IFERROR(IF(OR($B$8=0,N28="",N28=0),0,N28/$B$8),0) -> 0.026143791
F29: 11 | G29: =IFERROR(INDEX(Distritos!$L$7:$L$20,MATCH(SMALL(Distritos!$N$7:$N$20,11),Distritos!$N$7:$N$20,0)),"") -> RUTA 6A | H29: =IFERROR(INDEX(Distritos!$M$7:$M$20,MATCH(SMALL(Distritos!$N$7:$N$20,11),Distritos!$N$7:$N$20,0)),0) -> 7 | I29: =IFERROR(IF(OR($B$8=0,H29="",H29=0),0,H29/$B$8),0) -> 0.045751634
F30: 12 | G30: =IFERROR(INDEX(Distritos!$L$7:$L$20,MATCH(SMALL(Distritos!$N$7:$N$20,12),Distritos!$N$7:$N$20,0)),"") -> RUTA 6C | H30: =IFERROR(INDEX(Distritos!$M$7:$M$20,MATCH(SMALL(Distritos!$N$7:$N$20,12),Distritos!$N$7:$N$20,0)),0) -> 5 | I30: =IFERROR(IF(OR($B$8=0,H30="",H30=0),0,H30/$B$8),0) -> 0.032679739
F31: 13 | G31: =IFERROR(INDEX(Distritos!$L$7:$L$20,MATCH(SMALL(Distritos!$N$7:$N$20,13),Distritos!$N$7:$N$20,0)),"") -> RUTA 1 | H31: =IFERROR(INDEX(Distritos!$M$7:$M$20,MATCH(SMALL(Distritos!$N$7:$N$20,13),Distritos!$N$7:$N$20,0)),0) -> 4 | I31: =IFERROR(IF(OR($B$8=0,H31="",H31=0),0,H31/$B$8),0) -> 0.026143791
F32: 14 | G32: =IFERROR(INDEX(Distritos!$L$7:$L$20,MATCH(SMALL(Distritos!$N$7:$N$20,14),Distritos!$N$7:$N$20,0)),"") -> RUTA 5C | H32: =IFERROR(INDEX(Distritos!$M$7:$M$20,MATCH(SMALL(Distritos!$N$7:$N$20,14),Distritos!$N$7:$N$20,0)),0) -> 2 | I32: =IFERROR(IF(OR($B$8=0,H32="",H32=0),0,H32/$B$8),0) -> 0.013071895
A37: 🏘️ ANÁLISIS DETALLADO POR DISTRITO
A38: # | B38: Distrito | C38: Empleados | D38: % Total | E38: Dist. Prom. CD (km) | F38: Clasif. CD | G38: Dist. Prom. Paradero (km) | H38: Clasif. Paradero | I38: Ruta Principal | J38: Observación
A39: =IF(OR($B$8=0,C39="",C39=0),"",1) -> 1 | B39: =IF($B$8=0,"",IFERROR(IF(INDEX(Distritos!$I$7:$I$66,MATCH(SMALL(Distritos!$J$7:$J$66,1),Distritos!$J$7:$J$66,0))=0,"",INDEX(Distritos!$H$7:$H$66,MATCH(SMALL(Distritos!$J$7:$J$66,1),Distritos!$J$7:$J$66,0))),"")) -> Ate | C39: =IF($B$8=0,"",IFERROR(IF(INDEX(Distritos!$I$7:$I$66,MATCH(SMALL(Distritos!$J$7:$J$66,1),Distritos!$J$7:$J$66,0))=0,"",INDEX(Distritos!$I$7:$I$66,MATCH(SMALL(Distritos!$J$7:$J$66,1),Distritos!$J$7:$J$66,0))),"")) -> 25 | D39: =IF(OR($B$8=0,C39="",C39=0),"",C39/$B$8) -> 0.16339869 | E39: =IF(OR($B$8=0,B39=""),"",IFERROR(ROUND(IF($D$4="TODOS",IF($B$4="TODOS",(SUMIF('BD SECOS'!Q:Q,B39,'BD SECOS'!U:U)+SUMIF('BD PPA'!U:U,B39,'BD PPA'!AA:AA)+SUMIF('BD FRESCOS'!U:U,B39,'BD FRESCOS'!AA:AA))/(COUNTIF('BD SECOS'!Q:Q,B39)+COUNTIF('BD PPA'!U:U,B39)+COUNTIF('BD FRESCOS'!U:U,B39)),IF($B$4="SECOS",AVERAGEIF('BD SECOS'!Q:Q,B39,'BD SECOS'!U:U),IF($B$4="PPA",AVERAGEIF('BD PPA'!U:U,B39,'BD PPA'!AA:AA),AVERAGEIF('BD FRESCOS'!U:U,B39,'BD FRESCOS'!AA:AA)))),IF($B$4="TODOS",(SUMIFS('BD SECOS'!U:U,'BD SECOS'!Q:Q,B39,'BD SECOS'!AE:AE,$D$4)+SUMIFS('BD PPA'!AA:AA,'BD PPA'!U:U,B39,'BD PPA'!AK:AK,$D$4)+SUMIFS('BD FRESCOS'!AA:AA,'BD FRESCOS'!U:U,B39,'BD FRESCOS'!AK:AK,$D$4))/(COUNTIFS('BD SECOS'!Q:Q,B39,'BD SECOS'!AE:AE,$D$4)+COUNTIFS('BD PPA'!U:U,B39,'BD PPA'!AK:AK,$D$4)+COUNTIFS('BD FRESCOS'!U:U,B39,'BD FRESCOS'!AK:AK,$D$4)),IF($B$4="SECOS",AVERAGEIFS('BD SECOS'!U:U,'BD SECOS'!Q:Q,B39,'BD SECOS'!AE:AE,$D$4),IF($B$4="PPA",AVERAGEIFS('BD PPA'!AA:AA,'BD PPA'!U:U,B39,'BD PPA'!AK:AK,$D$4),AVERAGEIFS('BD FRESCOS'!AA:AA,'BD FRESCOS'!U:U,B39,'BD FRESCOS'!AK:AK,$D$4))))),2),"")) -> 7.82 | F39: =IF(OR($B$8=0,E39=""),"",IF(E39<=5,"🟢 Muy Cerca",IF(E39<=10,"🟡 Cerca",IF(E39<=20,"🟠 Moderada","🔴 Lejos")))) -> 🟡 Cerca | G39: =IF(OR($B$8=0,B39=""),"",IFERROR(ROUND(IF($D$4="TODOS",IF($B$4="TODOS",(SUMIF('BD SECOS'!Q:Q,B39,'BD SECOS'!Y:Y)+SUMIF('BD PPA'!U:U,B39,'BD PPA'!AE:AE)+SUMIF('BD FRESCOS'!U:U,B39,'BD FRESCOS'!AE:AE))/(COUNTIF('BD SECOS'!Q:Q,B39)+COUNTIF('BD PPA'!U:U,B39)+COUNTIF('BD FRESCOS'!U:U,B39)),IF($B$4="SECOS",AVERAGEIF('BD SECOS'!Q:Q,B39,'BD SECOS'!Y:Y),IF($B$4="PPA",AVERAGEIF('BD PPA'!U:U,B39,'BD PPA'!AE:AE),AVERAGEIF('BD FRESCOS'!U:U,B39,'BD FRESCOS'!AE:AE)))),IF($B$4="TODOS",(SUMIFS('BD SECOS'!Y:Y,'BD SECOS'!Q:Q,B39,'BD SECOS'!AE:AE,$D$4)+SUMIFS('BD PPA'!AE:AE,'BD PPA'!U:U,B39,'BD PPA'!AK:AK,$D$4)+SUMIFS('BD FRESCOS'!AE:AE,'BD FRESCOS'!U:U,B39,'BD FRESCOS'!AK:AK,$D$4))/(COUNTIFS('BD SECOS'!Q:Q,B39,'BD SECOS'!AE:AE,$D$4)+COUNTIFS('BD PPA'!U:U,B39,'BD PPA'!AK:AK,$D$4)+COUNTIFS('BD FRESCOS'!U:U,B39,'BD FRESCOS'!AK:AK,$D$4)),IF($B$4="SECOS",AVERAGEIFS('BD SECOS'!Y:Y,'BD SECOS'!Q:Q,B39,'BD SECOS'!AE:AE,$D$4),IF($B$4="PPA",AVERAGEIFS('BD PPA'!AE:AE,'BD PPA'!U:U,B39,'BD PPA'!AK:AK,$D$4),AVERAGEIFS('BD FRESCOS'!AE:AE,'BD FRESCOS'!U:U,B39,'BD FRESCOS'!AK:AK,$D$4))))),2),"")) -> 1.29 | H39: =IF(OR($B$8=0,G39=""),"",IF(G39<=1,"🟢 Muy Cerca",IF(G39<=3,"🟡 Cerca",IF(G39<=5,"🟠 Moderada","🔴 Lejos")))) -> 🟡 Cerca | I39: {=IF(OR($B$8=0,B39=""),"",IFERROR(IF($D$4="TODOS",IF($B$4="TODOS",INDEX('BD SECOS'!X:X,MATCH(B39,'BD SECOS'!Q:Q,0)),IF($B$4="SECOS",INDEX('BD SECOS'!X:X,MATCH(B39,'BD SECOS'!Q:Q,0)),IF($B$4="PPA",INDEX('BD PPA'!AD:AD,MATCH(B39,'BD PPA'!U:U,0)),INDEX('BD FRESCOS'!AD:AD,MATCH(B39,'BD FRESCOS'!U:U,0))))),IF($B$4="TODOS",IFERROR(INDEX('BD SECOS'!X:X,MATCH(1,('BD SECOS'!Q:Q=B39)*('BD SECOS'!AE:AE=$D$4),0)),IFERROR(INDEX('BD PPA'!AD:AD,MATCH(1,('BD PPA'!U:U=B39)*('BD PPA'!AK:AK=$D$4),0)),INDEX('BD FRESCOS'!AD:AD,MATCH(1,('BD FRESCOS'!U:U=B39)*('BD FRESCOS'!AK:AK=$D$4),0)))),IF($B$4="SECOS",INDEX('BD SECOS'!X:X,MATCH(1,('BD SECOS'!Q:Q=B39)*('BD SECOS'!AE:AE=$D$4),0)),IF($B$4="PPA",INDEX('BD PPA'!AD:AD,MATCH(1,('BD PPA'!U:U=B39)*('BD PPA'!AK:AK=$D$4),0)),INDEX('BD FRESCOS'!AD:AD,MATCH(1,('BD FRESCOS'!U:U=B39)*('BD FRESCOS'!AK:AK=$D$4),0)))))),""))} -> RUTA 7 | J39: =IF(OR($B$8=0,B39=""),"",IF(AND(E39>20,G39>5),"⚠️ Muy lejos del CD y paraderos",IF(E39>20,"⚠️ Muy lejos del CD",IF(G39>5,"⚠️ Lejos de paraderos","📍 Normal")))) -> 📍 Normal
A40: =IF(OR($B$8=0,C40="",C40=0),"",2) -> 2 | B40: =IF($B$8=0,"",IFERROR(IF(INDEX(Distritos!$I$7:$I$66,MATCH(SMALL(Distritos!$J$7:$J$66,2),Distritos!$J$7:$J$66,0))=0,"",INDEX(Distritos!$H$7:$H$66,MATCH(SMALL(Distritos!$J$7:$J$66,2),Distritos!$J$7:$J$66,0))),"")) -> San Juan De Lurigancho | C40: =IF($B$8=0,"",IFERROR(IF(INDEX(Distritos!$I$7:$I$66,MATCH(SMALL(Distritos!$J$7:$J$66,2),Distritos!$J$7:$J$66,0))=0,"",INDEX(Distritos!$I$7:$I$66,MATCH(SMALL(Distritos!$J$7:$J$66,2),Distritos!$J$7:$J$66,0))),"")) -> 22 | D40: =IF(OR($B$8=0,C40="",C40=0),"",C40/$B$8) -> 0.14379085 | E40: =IF(OR($B$8=0,B40=""),"",IFERROR(ROUND(IF($D$4="TODOS",IF($B$4="TODOS",(SUMIF('BD SECOS'!Q:Q,B40,'BD SECOS'!U:U)+SUMIF('BD PPA'!U:U,B40,'BD PPA'!AA:AA)+SUMIF('BD FRESCOS'!U:U,B40,'BD FRESCOS'!AA:AA))/(COUNTIF('BD SECOS'!Q:Q,B40)+COUNTIF('BD PPA'!U:U,B40)+COUNTIF('BD FRESCOS'!U:U,B40)),IF($B$4="SECOS",AVERAGEIF('BD SECOS'!Q:Q,B40,'BD SECOS'!U:U),IF($B$4="PPA",AVERAGEIF('BD PPA'!U:U,B40,'BD PPA'!AA:AA),AVERAGEIF('BD FRESCOS'!U:U,B40,'BD FRESCOS'!AA:AA)))),IF($B$4="TODOS",(SUMIFS('BD SECOS'!U:U,'BD SECOS'!Q:Q,B40,'BD SECOS'!AE:AE,$D$4)+SUMIFS('BD PPA'!AA:AA,'BD PPA'!U:U,B40,'BD PPA'!AK:AK,$D$4)+SUMIFS('BD FRESCOS'!AA:AA,'BD FRESCOS'!U:U,B40,'BD FRESCOS'!AK:AK,$D$4))/(COUNTIFS('BD SECOS'!Q:Q,B40,'BD SECOS'!AE:AE,$D$4)+COUNTIFS('BD PPA'!U:U,B40,'BD PPA'!AK:AK,$D$4)+COUNTIFS('BD FRESCOS'!U:U,B40,'BD FRESCOS'!AK:AK,$D$4)),IF($B$4="SECOS",AVERAGEIFS('BD SECOS'!U:U,'BD SECOS'!Q:Q,B40,'BD SECOS'!AE:AE,$D$4),IF($B$4="PPA",AVERAGEIFS('BD PPA'!AA:AA,'BD PPA'!U:U,B40,'BD PPA'!AK:AK,$D$4),AVERAGEIFS('BD FRESCOS'!AA:AA,'BD FRESCOS'!U:U,B40,'BD FRESCOS'!AK:AK,$D$4))))),2),"")) -> 11.75 | F40: =IF(OR($B$8=0,E40=""),"",IF(E40<=5,"🟢 Muy Cerca",IF(E40<=10,"🟡 Cerca",IF(E40<=20,"🟠 Moderada","🔴 Lejos")))) -> 🟠 Moderada | G40: =IF(OR($B$8=0,B40=""),"",IFERROR(ROUND(IF($D$4="TODOS",IF($B$4="TODOS",(SUMIF('BD SECOS'!Q:Q,B40,'BD SECOS'!Y:Y)+SUMIF('BD PPA'!U:U,B40,'BD PPA'!AE:AE)+SUMIF('BD FRESCOS'!U:U,B40,'BD FRESCOS'!AE:AE))/(COUNTIF('BD SECOS'!Q:Q,B40)+COUNTIF('BD PPA'!U:U,B40)+COUNTIF('BD FRESCOS'!U:U,B40)),IF($B$4="SECOS",AVERAGEIF('BD SECOS'!Q:Q,B40,'BD SECOS'!Y:Y),IF($B$4="PPA",AVERAGEIF('BD PPA'!U:U,B40,'BD PPA'!AE:AE),AVERAGEIF('BD FRESCOS'!U:U,B40,'BD FRESCOS'!AE:AE)))),IF($B$4="TODOS",(SUMIFS('BD SECOS'!Y:Y,'BD SECOS'!Q:Q,B40,'BD SECOS'!AE:AE,$D$4)+SUMIFS('BD PPA'!AE:AE,'BD PPA'!U:U,B40,'BD PPA'!AK:AK,$D$4)+SUMIFS('BD FRESCOS'!AE:AE,'BD FRESCOS'!U:U,B40,'BD FRESCOS'!AK:AK,$D$4))/(COUNTIFS('BD SECOS'!Q:Q,B40,'BD SECOS'!AE:AE,$D$4)+COUNTIFS('BD PPA'!U:U,B40,'BD PPA'!AK:AK,$D$4)+COUNTIFS('BD FRESCOS'!U:U,B40,'BD FRESCOS'!AK:AK,$D$4)),IF($B$4="SECOS",AVERAGEIFS('BD SECOS'!Y:Y,'BD SECOS'!Q:Q,B40,'BD SECOS'!AE:AE,$D$4),IF($B$4="PPA",AVERAGEIFS('BD PPA'!AE:AE,'BD PPA'!U:U,B40,'BD PPA'!AK:AK,$D$4),AVERAGEIFS('BD FRESCOS'!AE:AE,'BD FRESCOS'!U:U,B40,'BD FRESCOS'!AK:AK,$D$4))))),2),"")) -> 1.78 | H40: =IF(OR($B$8=0,G40=""),"",IF(G40<=1,"🟢 Muy Cerca",IF(G40<=3,"🟡 Cerca",IF(G40<=5,"🟠 Moderada","🔴 Lejos")))) -> 🟡 Cerca | I40: {=IF(OR($B$8=0,B40=""),"",IFERROR(IF($D$4="TODOS",IF($B$4="TODOS",INDEX('BD SECOS'!X:X,MATCH(B40,'BD SECOS'!Q:Q,0)),IF($B$4="SECOS",INDEX('BD SECOS'!X:X,MATCH(B40,'BD SECOS'!Q:Q,0)),IF($B$4="PPA",INDEX('BD PPA'!AD:AD,MATCH(B40,'BD PPA'!U:U,0)),INDEX('BD FRESCOS'!AD:AD,MATCH(B40,'BD FRESCOS'!U:U,0))))),IF($B$4="TODOS",IFERROR(INDEX('BD SECOS'!X:X,MATCH(1,('BD SECOS'!Q:Q=B40)*('BD SECOS'!AE:AE=$D$4),0)),IFERROR(INDEX('BD PPA'!AD:AD,MATCH(1,('BD PPA'!U:U=B40)*('BD PPA'!AK:AK=$D$4),0)),INDEX('BD FRESCOS'!AD:AD,MATCH(1,('BD FRESCOS'!U:U=B40)*('BD FRESCOS'!AK:AK=$D$4),0)))),IF($B$4="SECOS",INDEX('BD SECOS'!X:X,MATCH(1,('BD SECOS'!Q:Q=B40)*('BD SECOS'!AE:AE=$D$4),0)),IF($B$4="PPA",INDEX('BD PPA'!AD:AD,MATCH(1,('BD PPA'!U:U=B40)*('BD PPA'!AK:AK=$D$4),0)),INDEX('BD FRESCOS'!AD:AD,MATCH(1,('BD FRESCOS'!U:U=B40)*('BD FRESCOS'!AK:AK=$D$4),0)))))),""))} -> RUTA 8 | J40: =IF(OR($B$8=0,B40=""),"",IF(AND(E40>20,G40>5),"⚠️ Muy lejos del CD y paraderos",IF(E40>20,"⚠️ Muy lejos del CD",IF(G40>5,"⚠️ Lejos de paraderos","📍 Normal")))) -> 📍 Normal
A41: =IF(OR($B$8=0,C41="",C41=0),"",3) -> 3 | B41: =IF($B$8=0,"",IFERROR(IF(INDEX(Distritos!$I$7:$I$66,MATCH(SMALL(Distritos!$J$7:$J$66,3),Distritos!$J$7:$J$66,0))=0,"",INDEX(Distritos!$H$7:$H$66,MATCH(SMALL(Distritos!$J$7:$J$66,3),Distritos!$J$7:$J$66,0))),"")) -> Lurigancho | C41: =IF($B$8=0,"",IFERROR(IF(INDEX(Distritos!$I$7:$I$66,MATCH(SMALL(Distritos!$J$7:$J$66,3),Distritos!$J$7:$J$66,0))=0,"",INDEX(Distritos!$I$7:$I$66,MATCH(SMALL(Distritos!$J$7:$J$66,3),Distritos!$J$7:$J$66,0))),"")) -> 21 | D41: =IF(OR($B$8=0,C41="",C41=0),"",C41/$B$8) -> 0.1372549 | E41: =IF(OR($B$8=0,B41=""),"",IFERROR(ROUND(IF($D$4="TODOS",IF($B$4="TODOS",(SUMIF('BD SECOS'!Q:Q,B41,'BD SECOS'!U:U)+SUMIF('BD PPA'!U:U,B41,'BD PPA'!AA:AA)+SUMIF('BD FRESCOS'!U:U,B41,'BD FRESCOS'!AA:AA))/(COUNTIF('BD SECOS'!Q:Q,B41)+COUNTIF('BD PPA'!U:U,B41)+COUNTIF('BD FRESCOS'!U:U,B41)),IF($B$4="SECOS",AVERAGEIF('BD SECOS'!Q:Q,B41,'BD SECOS'!U:U),IF($B$4="PPA",AVERAGEIF('BD PPA'!U:U,B41,'BD PPA'!AA:AA),AVERAGEIF('BD FRESCOS'!U:U,B41,'BD FRESCOS'!AA:AA)))),IF($B$4="TODOS",(SUMIFS('BD SECOS'!U:U,'BD SECOS'!Q:Q,B41,'BD SECOS'!AE:AE,$D$4)+SUMIFS('BD PPA'!AA:AA,'BD PPA'!U:U,B41,'BD PPA'!AK:AK,$D$4)+SUMIFS('BD FRESCOS'!AA:AA,'BD FRESCOS'!U:U,B41,'BD FRESCOS'!AK:AK,$D$4))/(COUNTIFS('BD SECOS'!Q:Q,B41,'BD SECOS'!AE:AE,$D$4)+COUNTIFS('BD PPA'!U:U,B41,'BD PPA'!AK:AK,$D$4)+COUNTIFS('BD FRESCOS'!U:U,B41,'BD FRESCOS'!AK:AK,$D$4)),IF($B$4="SECOS",AVERAGEIFS('BD SECOS'!U:U,'BD SECOS'!Q:Q,B41,'BD SECOS'!AE:AE,$D$4),IF($B$4="PPA",AVERAGEIFS('BD PPA'!AA:AA,'BD PPA'!U:U,B41,'BD PPA'!AK:AK,$D$4),AVERAGEIFS('BD FRESCOS'!AA:AA,'BD FRESCOS'!U:U,B41,'BD FRESCOS'!AK:AK,$D$4))))),2),"")) -> 9.71 | F41: =IF(OR($B$8=0,E41=""),"",IF(E41<=5,"🟢 Muy Cerca",IF(E41<=10,"🟡 Cerca",IF(E41<=20,"🟠 Moderada","🔴 Lejos")))) -> 🟡 Cerca | G41: =IF(OR($B$8=0,B41=""),"",IFERROR(ROUND(IF($D$4="TODOS",IF($B$4="TODOS",(SUMIF('BD SECOS'!Q:Q,B41,'BD SECOS'!Y:Y)+SUMIF('BD PPA'!U:U,B41,'BD PPA'!AE:AE)+SUMIF('BD FRESCOS'!U:U,B41,'BD FRESCOS'!AE:AE))/(COUNTIF('BD SECOS'!Q:Q,B41)+COUNTIF('BD PPA'!U:U,B41)+COUNTIF('BD FRESCOS'!U:U,B41)),IF($B$4="SECOS",AVERAGEIF('BD SECOS'!Q:Q,B41,'BD SECOS'!Y:Y),IF($B$4="PPA",AVERAGEIF('BD PPA'!U:U,B41,'BD PPA'!AE:AE),AVERAGEIF('BD FRESCOS'!U:U,B41,'BD FRESCOS'!AE:AE)))),IF($B$4="TODOS",(SUMIFS('BD SECOS'!Y:Y,'BD SECOS'!Q:Q,B41,'BD SECOS'!AE:AE,$D$4)+SUMIFS('BD PPA'!AE:AE,'BD PPA'!U:U,B41,'BD PPA'!AK:AK,$D$4)+SUMIFS('BD FRESCOS'!AE:AE,'BD FRESCOS'!U:U,B41,'BD FRESCOS'!AK:AK,$D$4))/(COUNTIFS('BD SECOS'!Q:Q,B41,'BD SECOS'!AE:AE,$D$4)+COUNTIFS('BD PPA'!U:U,B41,'BD PPA'!AK:AK,$D$4)+COUNTIFS('BD FRESCOS'!U:U,B41,'BD FRESCOS'!AK:AK,$D$4)),IF($B$4="SECOS",AVERAGEIFS('BD SECOS'!Y:Y,'BD SECOS'!Q:Q,B41,'BD SECOS'!AE:AE,$D$4),IF($B$4="PPA",AVERAGEIFS('BD PPA'!AE:AE,'BD PPA'!U:U,B41,'BD PPA'!AK:AK,$D$4),AVERAGEIFS('BD FRESCOS'!AE:AE,'BD FRESCOS'!U:U,B41,'BD FRESCOS'!AK:AK,$D$4))))),2),"")) -> 3.41 | H41: =IF(OR($B$8=0,G41=""),"",IF(G41<=1,"🟢 Muy Cerca",IF(G41<=3,"🟡 Cerca",IF(G41<=5,"🟠 Moderada","🔴 Lejos")))) -> 🟠 Moderada | I41: {=IF(OR($B$8=0,B41=""),"",IFERROR(IF($D$4="TODOS",IF($B$4="TODOS",INDEX('BD SECOS'!X:X,MATCH(B41,'BD SECOS'!Q:Q,0)),IF($B$4="SECOS",INDEX('BD SECOS'!X:X,MATCH(B41,'BD SECOS'!Q:Q,0)),IF($B$4="PPA",INDEX('BD PPA'!AD:AD,MATCH(B41,'BD PPA'!U:U,0)),INDEX('BD FRESCOS'!AD:AD,MATCH(B41,'BD FRESCOS'!U:U,0))))),IF($B$4="TODOS",IFERROR(INDEX('BD SECOS'!X:X,MATCH(1,('BD SECOS'!Q:Q=B41)*('BD SECOS'!AE:AE=$D$4),0)),IFERROR(INDEX('BD PPA'!AD:AD,MATCH(1,('BD PPA'!U:U=B41)*('BD PPA'!AK:AK=$D$4),0)),INDEX('BD FRESCOS'!AD:AD,MATCH(1,('BD FRESCOS'!U:U=B41)*('BD FRESCOS'!AK:AK=$D$4),0)))),IF($B$4="SECOS",INDEX('BD SECOS'!X:X,MATCH(1,('BD SECOS'!Q:Q=B41)*('BD SECOS'!AE:AE=$D$4),0)),IF($B$4="PPA",INDEX('BD PPA'!AD:AD,MATCH(1,('BD PPA'!U:U=B41)*('BD PPA'!AK:AK=$D$4),0)),INDEX('BD FRESCOS'!AD:AD,MATCH(1,('BD FRESCOS'!U:U=B41)*('BD FRESCOS'!AK:AK=$D$4),0)))))),""))} -> RUTA 2 | J41: =IF(OR($B$8=0,B41=""),"",IF(AND(E41>20,G41>5),"⚠️ Muy lejos del CD y paraderos",IF(E41>20,"⚠️ Muy lejos del CD",IF(G41>5,"⚠️ Lejos de paraderos","📍 Normal")))) -> 📍 Normal
A42: =IF(OR($B$8=0,C42="",C42=0),"",4) -> 4 | B42: =IF($B$8=0,"",IFERROR(IF(INDEX(Distritos!$I$7:$I$66,MATCH(SMALL(Distritos!$J$7:$J$66,4),Distritos!$J$7:$J$66,0))=0,"",INDEX(Distritos!$H$7:$H$66,MATCH(SMALL(Distritos!$J$7:$J$66,4),Distritos!$J$7:$J$66,0))),"")) -> Lima | C42: =IF($B$8=0,"",IFERROR(IF(INDEX(Distritos!$I$7:$I$66,MATCH(SMALL(Distritos!$J$7:$J$66,4),Distritos!$J$7:$J$66,0))=0,"",INDEX(Distritos!$I$7:$I$66,MATCH(SMALL(Distritos!$J$7:$J$66,4),Distritos!$J$7:$J$66,0))),"")) -> 10 | D42: =IF(OR($B$8=0,C42="",C42=0),"",C42/$B$8) -> 0.065359477 | E42: =IF(OR($B$8=0,B42=""),"",IFERROR(ROUND(IF($D$4="TODOS",IF($B$4="TODOS",(SUMIF('BD SECOS'!Q:Q,B42,'BD SECOS'!U:U)+SUMIF('BD PPA'!U:U,B42,'BD PPA'!AA:AA)+SUMIF('BD FRESCOS'!U:U,B42,'BD FRESCOS'!AA:AA))/(COUNTIF('BD SECOS'!Q:Q,B42)+COUNTIF('BD PPA'!U:U,B42)+COUNTIF('BD FRESCOS'!U:U,B42)),IF($B$4="SECOS",AVERAGEIF('BD SECOS'!Q:Q,B42,'BD SECOS'!U:U),IF($B$4="PPA",AVERAGEIF('BD PPA'!U:U,B42,'BD PPA'!AA:AA),AVERAGEIF('BD FRESCOS'!U:U,B42,'BD FRESCOS'!AA:AA)))),IF($B$4="TODOS",(SUMIFS('BD SECOS'!U:U,'BD SECOS'!Q:Q,B42,'BD SECOS'!AE:AE,$D$4)+SUMIFS('BD PPA'!AA:AA,'BD PPA'!U:U,B42,'BD PPA'!AK:AK,$D$4)+SUMIFS('BD FRESCOS'!AA:AA,'BD FRESCOS'!U:U,B42,'BD FRESCOS'!AK:AK,$D$4))/(COUNTIFS('BD SECOS'!Q:Q,B42,'BD SECOS'!AE:AE,$D$4)+COUNTIFS('BD PPA'!U:U,B42,'BD PPA'!AK:AK,$D$4)+COUNTIFS('BD FRESCOS'!U:U,B42,'BD FRESCOS'!AK:AK,$D$4)),IF($B$4="SECOS",AVERAGEIFS('BD SECOS'!U:U,'BD SECOS'!Q:Q,B42,'BD SECOS'!AE:AE,$D$4),IF($B$4="PPA",AVERAGEIFS('BD PPA'!AA:AA,'BD PPA'!U:U,B42,'BD PPA'!AK:AK,$D$4),AVERAGEIFS('BD FRESCOS'!AA:AA,'BD FRESCOS'!U:U,B42,'BD FRESCOS'!AK:AK,$D$4))))),2),"")) -> 16.92 | F42: =IF(OR($B$8=0,E42=""),"",IF(E42<=5,"🟢 Muy Cerca",IF(E42<=10,"🟡 Cerca",IF(E42<=20,"🟠 Moderada","🔴 Lejos")))) -> 🟠 Moderada | G42: =IF(OR($B$8=0,B42=""),"",IFERROR(ROUND(IF($D$4="TODOS",IF($B$4="TODOS",(SUMIF('BD SECOS'!Q:Q,B42,'BD SECOS'!Y:Y)+SUMIF('BD PPA'!U:U,B42,'BD PPA'!AE:AE)+SUMIF('BD FRESCOS'!U:U,B42,'BD FRESCOS'!AE:AE))/(COUNTIF('BD SECOS'!Q:Q,B42)+COUNTIF('BD PPA'!U:U,B42)+COUNTIF('BD FRESCOS'!U:U,B42)),IF($B$4="SECOS",AVERAGEIF('BD SECOS'!Q:Q,B42,'BD SECOS'!Y:Y),IF($B$4="PPA",AVERAGEIF('BD PPA'!U:U,B42,'BD PPA'!AE:AE),AVERAGEIF('BD FRESCOS'!U:U,B42,'BD FRESCOS'!AE:AE)))),IF($B$4="TODOS",(SUMIFS('BD SECOS'!Y:Y,'BD SECOS'!Q:Q,B42,'BD SECOS'!AE:AE,$D$4)+SUMIFS('BD PPA'!AE:AE,'BD PPA'!U:U,B42,'BD PPA'!AK:AK,$D$4)+SUMIFS('BD FRESCOS'!AE:AE,'BD FRESCOS'!U:U,B42,'BD FRESCOS'!AK:AK,$D$4))/(COUNTIFS('BD SECOS'!Q:Q,B42,'BD SECOS'!AE:AE,$D$4)+COUNTIFS('BD PPA'!U:U,B42,'BD PPA'!AK:AK,$D$4)+COUNTIFS('BD FRESCOS'!U:U,B42,'BD FRESCOS'!AK:AK,$D$4)),IF($B$4="SECOS",AVERAGEIFS('BD SECOS'!Y:Y,'BD SECOS'!Q:Q,B42,'BD SECOS'!AE:AE,$D$4),IF($B$4="PPA",AVERAGEIFS('BD PPA'!AE:AE,'BD PPA'!U:U,B42,'BD PPA'!AK:AK,$D$4),AVERAGEIFS('BD FRESCOS'!AE:AE,'BD FRESCOS'!U:U,B42,'BD FRESCOS'!AK:AK,$D$4))))),2),"")) -> 1.37 | H42: =IF(OR($B$8=0,G42=""),"",IF(G42<=1,"🟢 Muy Cerca",IF(G42<=3,"🟡 Cerca",IF(G42<=5,"🟠 Moderada","🔴 Lejos")))) -> 🟡 Cerca | I42: {=IF(OR($B$8=0,B42=""),"",IFERROR(IF($D$4="TODOS",IF($B$4="TODOS",INDEX('BD SECOS'!X:X,MATCH(B42,'BD SECOS'!Q:Q,0)),IF($B$4="SECOS",INDEX('BD SECOS'!X:X,MATCH(B42,'BD SECOS'!Q:Q,0)),IF($B$4="PPA",INDEX('BD PPA'!AD:AD,MATCH(B42,'BD PPA'!U:U,0)),INDEX('BD FRESCOS'!AD:AD,MATCH(B42,'BD FRESCOS'!U:U,0))))),IF($B$4="TODOS",IFERROR(INDEX('BD SECOS'!X:X,MATCH(1,('BD SECOS'!Q:Q=B42)*('BD SECOS'!AE:AE=$D$4),0)),IFERROR(INDEX('BD PPA'!AD:AD,MATCH(1,('BD PPA'!U:U=B42)*('BD PPA'!AK:AK=$D$4),0)),INDEX('BD FRESCOS'!AD:AD,MATCH(1,('BD FRESCOS'!U:U=B42)*('BD FRESCOS'!AK:AK=$D$4),0)))),IF($B$4="SECOS",INDEX('BD SECOS'!X:X,MATCH(1,('BD SECOS'!Q:Q=B42)*('BD SECOS'!AE:AE=$D$4),0)),IF($B$4="PPA",INDEX('BD PPA'!AD:AD,MATCH(1,('BD PPA'!U:U=B42)*('BD PPA'!AK:AK=$D$4),0)),INDEX('BD FRESCOS'!AD:AD,MATCH(1,('BD FRESCOS'!U:U=B42)*('BD FRESCOS'!AK:AK=$D$4),0)))))),""))} -> RUTA 9 | J42: =IF(OR($B$8=0,B42=""),"",IF(AND(E42>20,G42>5),"⚠️ Muy lejos del CD y paraderos",IF(E42>20,"⚠️ Muy lejos del CD",IF(G42>5,"⚠️ Lejos de paraderos","📍 Normal")))) -> 📍 Normal
A43: =IF(OR($B$8=0,C43="",C43=0),"",5) -> 5 | B43: =IF($B$8=0,"",IFERROR(IF(INDEX(Distritos!$I$7:$I$66,MATCH(SMALL(Distritos!$J$7:$J$66,5),Distritos!$J$7:$J$66,0))=0,"",INDEX(Distritos!$H$7:$H$66,MATCH(SMALL(Distritos!$J$7:$J$66,5),Distritos!$J$7:$J$66,0))),"")) -> Santiago De Surco | C43: =IF($B$8=0,"",IFERROR(IF(INDEX(Distritos!$I$7:$I$66,MATCH(SMALL(Distritos!$J$7:$J$66,5),Distritos!$J$7:$J$66,0))=0,"",INDEX(Distritos!$I$7:$I$66,MATCH(SMALL(Distritos!$J$7:$J$66,5),Distritos!$J$7:$J$66,0))),"")) -> 7 | D43: =IF(OR($B$8=0,C43="",C43=0),"",C43/$B$8) -> 0.045751634 | E43: =IF(OR($B$8=0,B43=""),"",IFERROR(ROUND(IF($D$4="TODOS",IF($B$4="TODOS",(SUMIF('BD SECOS'!Q:Q,B43,'BD SECOS'!U:U)+SUMIF('BD PPA'!U:U,B43,'BD PPA'!AA:AA)+SUMIF('BD FRESCOS'!U:U,B43,'BD FRESCOS'!AA:AA))/(COUNTIF('BD SECOS'!Q:Q,B43)+COUNTIF('BD PPA'!U:U,B43)+COUNTIF('BD FRESCOS'!U:U,B43)),IF($B$4="SECOS",AVERAGEIF('BD SECOS'!Q:Q,B43,'BD SECOS'!U:U),IF($B$4="PPA",AVERAGEIF('BD PPA'!U:U,B43,'BD PPA'!AA:AA),AVERAGEIF('BD FRESCOS'!U:U,B43,'BD FRESCOS'!AA:AA)))),IF($B$4="TODOS",(SUMIFS('BD SECOS'!U:U,'BD SECOS'!Q:Q,B43,'BD SECOS'!AE:AE,$D$4)+SUMIFS('BD PPA'!AA:AA,'BD PPA'!U:U,B43,'BD PPA'!AK:AK,$D$4)+SUMIFS('BD FRESCOS'!AA:AA,'BD FRESCOS'!U:U,B43,'BD FRESCOS'!AK:AK,$D$4))/(COUNTIFS('BD SECOS'!Q:Q,B43,'BD SECOS'!AE:AE,$D$4)+COUNTIFS('BD PPA'!U:U,B43,'BD PPA'!AK:AK,$D$4)+COUNTIFS('BD FRESCOS'!U:U,B43,'BD FRESCOS'!AK:AK,$D$4)),IF($B$4="SECOS",AVERAGEIFS('BD SECOS'!U:U,'BD SECOS'!Q:Q,B43,'BD SECOS'!AE:AE,$D$4),IF($B$4="PPA",AVERAGEIFS('BD PPA'!AA:AA,'BD PPA'!U:U,B43,'BD PPA'!AK:AK,$D$4),AVERAGEIFS('BD FRESCOS'!AA:AA,'BD FRESCOS'!U:U,B43,'BD FRESCOS'!AK:AK,$D$4))))),2),"")) -> 18.72 | F43: =IF(OR($B$8=0,E43=""),"",IF(E43<=5,"🟢 Muy Cerca",IF(E43<=10,"🟡 Cerca",IF(E43<=20,"🟠 Moderada","🔴 Lejos")))) -> 🟠 Moderada | G43: =IF(OR($B$8=0,B43=""),"",IFERROR(ROUND(IF($D$4="TODOS",IF($B$4="TODOS",(SUMIF('BD SECOS'!Q:Q,B43,'BD SECOS'!Y:Y)+SUMIF('BD PPA'!U:U,B43,'BD PPA'!AE:AE)+SUMIF('BD FRESCOS'!U:U,B43,'BD FRESCOS'!AE:AE))/(COUNTIF('BD SECOS'!Q:Q,B43)+COUNTIF('BD PPA'!U:U,B43)+COUNTIF('BD FRESCOS'!U:U,B43)),IF($B$4="SECOS",AVERAGEIF('BD SECOS'!Q:Q,B43,'BD SECOS'!Y:Y),IF($B$4="PPA",AVERAGEIF('BD PPA'!U:U,B43,'BD PPA'!AE:AE),AVERAGEIF('BD FRESCOS'!U:U,B43,'BD FRESCOS'!AE:AE)))),IF($B$4="TODOS",(SUMIFS('BD SECOS'!Y:Y,'BD SECOS'!Q:Q,B43,'BD SECOS'!AE:AE,$D$4)+SUMIFS('BD PPA'!AE:AE,'BD PPA'!U:U,B43,'BD PPA'!AK:AK,$D$4)+SUMIFS('BD FRESCOS'!AE:AE,'BD FRESCOS'!U:U,B43,'BD FRESCOS'!AK:AK,$D$4))/(COUNTIFS('BD SECOS'!Q:Q,B43,'BD SECOS'!AE:AE,$D$4)+COUNTIFS('BD PPA'!U:U,B43,'BD PPA'!AK:AK,$D$4)+COUNTIFS('BD FRESCOS'!U:U,B43,'BD FRESCOS'!AK:AK,$D$4)),IF($B$4="SECOS",AVERAGEIFS('BD SECOS'!Y:Y,'BD SECOS'!Q:Q,B43,'BD SECOS'!AE:AE,$D$4),IF($B$4="PPA",AVERAGEIFS('BD PPA'!AE:AE,'BD PPA'!U:U,B43,'BD PPA'!AK:AK,$D$4),AVERAGEIFS('BD FRESCOS'!AE:AE,'BD FRESCOS'!U:U,B43,'BD FRESCOS'!AK:AK,$D$4))))),2),"")) -> 1.29 | H43: =IF(OR($B$8=0,G43=""),"",IF(G43<=1,"🟢 Muy Cerca",IF(G43<=3,"🟡 Cerca",IF(G43<=5,"🟠 Moderada","🔴 Lejos")))) -> 🟡 Cerca | I43: {=IF(OR($B$8=0,B43=""),"",IFERROR(IF($D$4="TODOS",IF($B$4="TODOS",INDEX('BD SECOS'!X:X,MATCH(B43,'BD SECOS'!Q:Q,0)),IF($B$4="SECOS",INDEX('BD SECOS'!X:X,MATCH(B43,'BD SECOS'!Q:Q,0)),IF($B$4="PPA",INDEX('BD PPA'!AD:AD,MATCH(B43,'BD PPA'!U:U,0)),INDEX('BD FRESCOS'!AD:AD,MATCH(B43,'BD FRESCOS'!U:U,0))))),IF($B$4="TODOS",IFERROR(INDEX('BD SECOS'!X:X,MATCH(1,('BD SECOS'!Q:Q=B43)*('BD SECOS'!AE:AE=$D$4),0)),IFERROR(INDEX('BD PPA'!AD:AD,MATCH(1,('BD PPA'!U:U=B43)*('BD PPA'!AK:AK=$D$4),0)),INDEX('BD FRESCOS'!AD:AD,MATCH(1,('BD FRESCOS'!U:U=B43)*('BD FRESCOS'!AK:AK=$D$4),0)))),IF($B$4="SECOS",INDEX('BD SECOS'!X:X,MATCH(1,('BD SECOS'!Q:Q=B43)*('BD SECOS'!AE:AE=$D$4),0)),IF($B$4="PPA",INDEX('BD PPA'!AD:AD,MATCH(1,('BD PPA'!U:U=B43)*('BD PPA'!AK:AK=$D$4),0)),INDEX('BD FRESCOS'!AD:AD,MATCH(1,('BD FRESCOS'!U:U=B43)*('BD FRESCOS'!AK:AK=$D$4),0)))))),""))} -> RUTA 7 | J43: =IF(OR($B$8=0,B43=""),"",IF(AND(E43>20,G43>5),"⚠️ Muy lejos del CD y paraderos",IF(E43>20,"⚠️ Muy lejos del CD",IF(G43>5,"⚠️ Lejos de paraderos","📍 Normal")))) -> 📍 Normal
A44: =IF(OR($B$8=0,C44="",C44=0),"",6) -> 6 | B44: =IF($B$8=0,"",IFERROR(IF(INDEX(Distritos!$I$7:$I$66,MATCH(SMALL(Distritos!$J$7:$J$66,6),Distritos!$J$7:$J$66,0))=0,"",INDEX(Distritos!$H$7:$H$66,MATCH(SMALL(Distritos!$J$7:$J$66,6),Distritos!$J$7:$J$66,0))),"")) -> Callao | C44: =IF($B$8=0,"",IFERROR(IF(INDEX(Distritos!$I$7:$I$66,MATCH(SMALL(Distritos!$J$7:$J$66,6),Distritos!$J$7:$J$66,0))=0,"",INDEX(Distritos!$I$7:$I$66,MATCH(SMALL(Distritos!$J$7:$J$66,6),Distritos!$J$7:$J$66,0))),"")) -> 6 | D44: =IF(OR($B$8=0,C44="",C44=0),"",C44/$B$8) -> 0.039215686 | E44: =IF(OR($B$8=0,B44=""),"",IFERROR(ROUND(IF($D$4="TODOS",IF($B$4="TODOS",(SUMIF('BD SECOS'!Q:Q,B44,'BD SECOS'!U:U)+SUMIF('BD PPA'!U:U,B44,'BD PPA'!AA:AA)+SUMIF('BD FRESCOS'!U:U,B44,'BD FRESCOS'!AA:AA))/(COUNTIF('BD SECOS'!Q:Q,B44)+COUNTIF('BD PPA'!U:U,B44)+COUNTIF('BD FRESCOS'!U:U,B44)),IF($B$4="SECOS",AVERAGEIF('BD SECOS'!Q:Q,B44,'BD SECOS'!U:U),IF($B$4="PPA",AVERAGEIF('BD PPA'!U:U,B44,'BD PPA'!AA:AA),AVERAGEIF('BD FRESCOS'!U:U,B44,'BD FRESCOS'!AA:AA)))),IF($B$4="TODOS",(SUMIFS('BD SECOS'!U:U,'BD SECOS'!Q:Q,B44,'BD SECOS'!AE:AE,$D$4)+SUMIFS('BD PPA'!AA:AA,'BD PPA'!U:U,B44,'BD PPA'!AK:AK,$D$4)+SUMIFS('BD FRESCOS'!AA:AA,'BD FRESCOS'!U:U,B44,'BD FRESCOS'!AK:AK,$D$4))/(COUNTIFS('BD SECOS'!Q:Q,B44,'BD SECOS'!AE:AE,$D$4)+COUNTIFS('BD PPA'!U:U,B44,'BD PPA'!AK:AK,$D$4)+COUNTIFS('BD FRESCOS'!U:U,B44,'BD FRESCOS'!AK:AK,$D$4)),IF($B$4="SECOS",AVERAGEIFS('BD SECOS'!U:U,'BD SECOS'!Q:Q,B44,'BD SECOS'!AE:AE,$D$4),IF($B$4="PPA",AVERAGEIFS('BD PPA'!AA:AA,'BD PPA'!U:U,B44,'BD PPA'!AK:AK,$D$4),AVERAGEIFS('BD FRESCOS'!AA:AA,'BD FRESCOS'!U:U,B44,'BD FRESCOS'!AK:AK,$D$4))))),2),"")) -> 23.02 | F44: =IF(OR($B$8=0,E44=""),"",IF(E44<=5,"🟢 Muy Cerca",IF(E44<=10,"🟡 Cerca",IF(E44<=20,"🟠 Moderada","🔴 Lejos")))) -> 🔴 Lejos | G44: =IF(OR($B$8=0,B44=""),"",IFERROR(ROUND(IF($D$4="TODOS",IF($B$4="TODOS",(SUMIF('BD SECOS'!Q:Q,B44,'BD SECOS'!Y:Y)+SUMIF('BD PPA'!U:U,B44,'BD PPA'!AE:AE)+SUMIF('BD FRESCOS'!U:U,B44,'BD FRESCOS'!AE:AE))/(COUNTIF('BD SECOS'!Q:Q,B44)+COUNTIF('BD PPA'!U:U,B44)+COUNTIF('BD FRESCOS'!U:U,B44)),IF($B$4="SECOS",AVERAGEIF('BD SECOS'!Q:Q,B44,'BD SECOS'!Y:Y),IF($B$4="PPA",AVERAGEIF('BD PPA'!U:U,B44,'BD PPA'!AE:AE),AVERAGEIF('BD FRESCOS'!U:U,B44,'BD FRESCOS'!AE:AE)))),IF($B$4="TODOS",(SUMIFS('BD SECOS'!Y:Y,'BD SECOS'!Q:Q,B44,'BD SECOS'!AE:AE,$D$4)+SUMIFS('BD PPA'!AE:AE,'BD PPA'!U:U,B44,'BD PPA'!AK:AK,$D$4)+SUMIFS('BD FRESCOS'!AE:AE,'BD FRESCOS'!U:U,B44,'BD FRESCOS'!AK:AK,$D$4))/(COUNTIFS('BD SECOS'!Q:Q,B44,'BD SECOS'!AE:AE,$D$4)+COUNTIFS('BD PPA'!U:U,B44,'BD PPA'!AK:AK,$D$4)+COUNTIFS('BD FRESCOS'!U:U,B44,'BD FRESCOS'!AK:AK,$D$4)),IF($B$4="SECOS",AVERAGEIFS('BD SECOS'!Y:Y,'BD SECOS'!Q:Q,B44,'BD SECOS'!AE:AE,$D$4),IF($B$4="PPA",AVERAGEIFS('BD PPA'!AE:AE,'BD PPA'!U:U,B44,'BD PPA'!AK:AK,$D$4),AVERAGEIFS('BD FRESCOS'!AE:AE,'BD FRESCOS'!U:U,B44,'BD FRESCOS'!AK:AK,$D$4))))),2),"")) -> 1.53 | H44: =IF(OR($B$8=0,G44=""),"",IF(G44<=1,"🟢 Muy Cerca",IF(G44<=3,"🟡 Cerca",IF(G44<=5,"🟠 Moderada","🔴 Lejos")))) -> 🟡 Cerca | I44: {=IF(OR($B$8=0,B44=""),"",IFERROR(IF($D$4="TODOS",IF($B$4="TODOS",INDEX('BD SECOS'!X:X,MATCH(B44,'BD SECOS'!Q:Q,0)),IF($B$4="SECOS",INDEX('BD SECOS'!X:X,MATCH(B44,'BD SECOS'!Q:Q,0)),IF($B$4="PPA",INDEX('BD PPA'!AD:AD,MATCH(B44,'BD PPA'!U:U,0)),INDEX('BD FRESCOS'!AD:AD,MATCH(B44,'BD FRESCOS'!U:U,0))))),IF($B$4="TODOS",IFERROR(INDEX('BD SECOS'!X:X,MATCH(1,('BD SECOS'!Q:Q=B44)*('BD SECOS'!AE:AE=$D$4),0)),IFERROR(INDEX('BD PPA'!AD:AD,MATCH(1,('BD PPA'!U:U=B44)*('BD PPA'!AK:AK=$D$4),0)),INDEX('BD FRESCOS'!AD:AD,MATCH(1,('BD FRESCOS'!U:U=B44)*('BD FRESCOS'!AK:AK=$D$4),0)))),IF($B$4="SECOS",INDEX('BD SECOS'!X:X,MATCH(1,('BD SECOS'!Q:Q=B44)*('BD SECOS'!AE:AE=$D$4),0)),IF($B$4="PPA",INDEX('BD PPA'!AD:AD,MATCH(1,('BD PPA'!U:U=B44)*('BD PPA'!AK:AK=$D$4),0)),INDEX('BD FRESCOS'!AD:AD,MATCH(1,('BD FRESCOS'!U:U=B44)*('BD FRESCOS'!AK:AK=$D$4),0)))))),""))} -> RUTA 3 | J44: =IF(OR($B$8=0,B44=""),"",IF(AND(E44>20,G44>5),"⚠️ Muy lejos del CD y paraderos",IF(E44>20,"⚠️ Muy lejos del CD",IF(G44>5,"⚠️ Lejos de paraderos","📍 Normal")))) -> ⚠️ Muy lejos del CD
A45: =IF(OR($B$8=0,C45="",C45=0),"",7) -> 7 | B45: =IF($B$8=0,"",IFERROR(IF(INDEX(Distritos!$I$7:$I$66,MATCH(SMALL(Distritos!$J$7:$J$66,7),Distritos!$J$7:$J$66,0))=0,"",INDEX(Distritos!$H$7:$H$66,MATCH(SMALL(Distritos!$J$7:$J$66,7),Distritos!$J$7:$J$66,0))),"")) -> Los Olivos | C45: =IF($B$8=0,"",IFERROR(IF(INDEX(Distritos!$I$7:$I$66,MATCH(SMALL(Distritos!$J$7:$J$66,7),Distritos!$J$7:$J$66,0))=0,"",INDEX(Distritos!$I$7:$I$66,MATCH(SMALL(Distritos!$J$7:$J$66,7),Distritos!$J$7:$J$66,0))),"")) -> 6 | D45: =IF(OR($B$8=0,C45="",C45=0),"",C45/$B$8) -> 0.039215686 | E45: =IF(OR($B$8=0,B45=""),"",IFERROR(ROUND(IF($D$4="TODOS",IF($B$4="TODOS",(SUMIF('BD SECOS'!Q:Q,B45,'BD SECOS'!U:U)+SUMIF('BD PPA'!U:U,B45,'BD PPA'!AA:AA)+SUMIF('BD FRESCOS'!U:U,B45,'BD FRESCOS'!AA:AA))/(COUNTIF('BD SECOS'!Q:Q,B45)+COUNTIF('BD PPA'!U:U,B45)+COUNTIF('BD FRESCOS'!U:U,B45)),IF($B$4="SECOS",AVERAGEIF('BD SECOS'!Q:Q,B45,'BD SECOS'!U:U),IF($B$4="PPA",AVERAGEIF('BD PPA'!U:U,B45,'BD PPA'!AA:AA),AVERAGEIF('BD FRESCOS'!U:U,B45,'BD FRESCOS'!AA:AA)))),IF($B$4="TODOS",(SUMIFS('BD SECOS'!U:U,'BD SECOS'!Q:Q,B45,'BD SECOS'!AE:AE,$D$4)+SUMIFS('BD PPA'!AA:AA,'BD PPA'!U:U,B45,'BD PPA'!AK:AK,$D$4)+SUMIFS('BD FRESCOS'!AA:AA,'BD FRESCOS'!U:U,B45,'BD FRESCOS'!AK:AK,$D$4))/(COUNTIFS('BD SECOS'!Q:Q,B45,'BD SECOS'!AE:AE,$D$4)+COUNTIFS('BD PPA'!U:U,B45,'BD PPA'!AK:AK,$D$4)+COUNTIFS('BD FRESCOS'!U:U,B45,'BD FRESCOS'!AK:AK,$D$4)),IF($B$4="SECOS",AVERAGEIFS('BD SECOS'!U:U,'BD SECOS'!Q:Q,B45,'BD SECOS'!AE:AE,$D$4),IF($B$4="PPA",AVERAGEIFS('BD PPA'!AA:AA,'BD PPA'!U:U,B45,'BD PPA'!AK:AK,$D$4),AVERAGEIFS('BD FRESCOS'!AA:AA,'BD FRESCOS'!U:U,B45,'BD FRESCOS'!AK:AK,$D$4))))),2),"")) -> 18.88 | F45: =IF(OR($B$8=0,E45=""),"",IF(E45<=5,"🟢 Muy Cerca",IF(E45<=10,"🟡 Cerca",IF(E45<=20,"🟠 Moderada","🔴 Lejos")))) -> 🟠 Moderada | G45: =IF(OR($B$8=0,B45=""),"",IFERROR(ROUND(IF($D$4="TODOS",IF($B$4="TODOS",(SUMIF('BD SECOS'!Q:Q,B45,'BD SECOS'!Y:Y)+SUMIF('BD PPA'!U:U,B45,'BD PPA'!AE:AE)+SUMIF('BD FRESCOS'!U:U,B45,'BD FRESCOS'!AE:AE))/(COUNTIF('BD SECOS'!Q:Q,B45)+COUNTIF('BD PPA'!U:U,B45)+COUNTIF('BD FRESCOS'!U:U,B45)),IF($B$4="SECOS",AVERAGEIF('BD SECOS'!Q:Q,B45,'BD SECOS'!Y:Y),IF($B$4="PPA",AVERAGEIF('BD PPA'!U:U,B45,'BD PPA'!AE:AE),AVERAGEIF('BD FRESCOS'!U:U,B45,'BD FRESCOS'!AE:AE)))),IF($B$4="TODOS",(SUMIFS('BD SECOS'!Y:Y,'BD SECOS'!Q:Q,B45,'BD SECOS'!AE:AE,$D$4)+SUMIFS('BD PPA'!AE:AE,'BD PPA'!U:U,B45,'BD PPA'!AK:AK,$D$4)+SUMIFS('BD FRESCOS'!AE:AE,'BD FRESCOS'!U:U,B45,'BD FRESCOS'!AK:AK,$D$4))/(COUNTIFS('BD SECOS'!Q:Q,B45,'BD SECOS'!AE:AE,$D$4)+COUNTIFS('BD PPA'!U:U,B45,'BD PPA'!AK:AK,$D$4)+COUNTIFS('BD FRESCOS'!U:U,B45,'BD FRESCOS'!AK:AK,$D$4)),IF($B$4="SECOS",AVERAGEIFS('BD SECOS'!Y:Y,'BD SECOS'!Q:Q,B45,'BD SECOS'!AE:AE,$D$4),IF($B$4="PPA",AVERAGEIFS('BD PPA'!AE:AE,'BD PPA'!U:U,B45,'BD PPA'!AK:AK,$D$4),AVERAGEIFS('BD FRESCOS'!AE:AE,'BD FRESCOS'!U:U,B45,'BD FRESCOS'!AK:AK,$D$4))))),2),"")) -> 0.83 | H45: =IF(OR($B$8=0,G45=""),"",IF(G45<=1,"🟢 Muy Cerca",IF(G45<=3,"🟡 Cerca",IF(G45<=5,"🟠 Moderada","🔴 Lejos")))) -> 🟢 Muy Cerca | I45: {=IF(OR($B$8=0,B45=""),"",IFERROR(IF($D$4="TODOS",IF($B$4="TODOS",INDEX('BD SECOS'!X:X,MATCH(B45,'BD SECOS'!Q:Q,0)),IF($B$4="SECOS",INDEX('BD SECOS'!X:X,MATCH(B45,'BD SECOS'!Q:Q,0)),IF($B$4="PPA",INDEX('BD PPA'!AD:AD,MATCH(B45,'BD PPA'!U:U,0)),INDEX('BD FRESCOS'!AD:AD,MATCH(B45,'BD FRESCOS'!U:U,0))))),IF($B$4="TODOS",IFERROR(INDEX('BD SECOS'!X:X,MATCH(1,('BD SECOS'!Q:Q=B45)*('BD SECOS'!AE:AE=$D$4),0)),IFERROR(INDEX('BD PPA'!AD:AD,MATCH(1,('BD PPA'!U:U=B45)*('BD PPA'!AK:AK=$D$4),0)),INDEX('BD FRESCOS'!AD:AD,MATCH(1,('BD FRESCOS'!U:U=B45)*('BD FRESCOS'!AK:AK=$D$4),0)))),IF($B$4="SECOS",INDEX('BD SECOS'!X:X,MATCH(1,('BD SECOS'!Q:Q=B45)*('BD SECOS'!AE:AE=$D$4),0)),IF($B$4="PPA",INDEX('BD PPA'!AD:AD,MATCH(1,('BD PPA'!U:U=B45)*('BD PPA'!AK:AK=$D$4),0)),INDEX('BD FRESCOS'!AD:AD,MATCH(1,('BD FRESCOS'!U:U=B45)*('BD FRESCOS'!AK:AK=$D$4),0)))))),""))} -> RUTA 7 | J45: =IF(OR($B$8=0,B45=""),"",IF(AND(E45>20,G45>5),"⚠️ Muy lejos del CD y paraderos",IF(E45>20,"⚠️ Muy lejos del CD",IF(G45>5,"⚠️ Lejos de paraderos","📍 Normal")))) -> 📍 Normal
A46: =IF(OR($B$8=0,C46="",C46=0),"",8) -> 8 | B46: =IF($B$8=0,"",IFERROR(IF(INDEX(Distritos!$I$7:$I$66,MATCH(SMALL(Distritos!$J$7:$J$66,8),Distritos!$J$7:$J$66,0))=0,"",INDEX(Distritos!$H$7:$H$66,MATCH(SMALL(Distritos!$J$7:$J$66,8),Distritos!$J$7:$J$66,0))),"")) -> Carabayllo | C46: =IF($B$8=0,"",IFERROR(IF(INDEX(Distritos!$I$7:$I$66,MATCH(SMALL(Distritos!$J$7:$J$66,8),Distritos!$J$7:$J$66,0))=0,"",INDEX(Distritos!$I$7:$I$66,MATCH(SMALL(Distritos!$J$7:$J$66,8),Distritos!$J$7:$J$66,0))),"")) -> 4 | D46: =IF(OR($B$8=0,C46="",C46=0),"",C46/$B$8) -> 0.026143791 | E46: =IF(OR($B$8=0,B46=""),"",IFERROR(ROUND(IF($D$4="TODOS",IF($B$4="TODOS",(SUMIF('BD SECOS'!Q:Q,B46,'BD SECOS'!U:U)+SUMIF('BD PPA'!U:U,B46,'BD PPA'!AA:AA)+SUMIF('BD FRESCOS'!U:U,B46,'BD FRESCOS'!AA:AA))/(COUNTIF('BD SECOS'!Q:Q,B46)+COUNTIF('BD PPA'!U:U,B46)+COUNTIF('BD FRESCOS'!U:U,B46)),IF($B$4="SECOS",AVERAGEIF('BD SECOS'!Q:Q,B46,'BD SECOS'!U:U),IF($B$4="PPA",AVERAGEIF('BD PPA'!U:U,B46,'BD PPA'!AA:AA),AVERAGEIF('BD FRESCOS'!U:U,B46,'BD FRESCOS'!AA:AA)))),IF($B$4="TODOS",(SUMIFS('BD SECOS'!U:U,'BD SECOS'!Q:Q,B46,'BD SECOS'!AE:AE,$D$4)+SUMIFS('BD PPA'!AA:AA,'BD PPA'!U:U,B46,'BD PPA'!AK:AK,$D$4)+SUMIFS('BD FRESCOS'!AA:AA,'BD FRESCOS'!U:U,B46,'BD FRESCOS'!AK:AK,$D$4))/(COUNTIFS('BD SECOS'!Q:Q,B46,'BD SECOS'!AE:AE,$D$4)+COUNTIFS('BD PPA'!U:U,B46,'BD PPA'!AK:AK,$D$4)+COUNTIFS('BD FRESCOS'!U:U,B46,'BD FRESCOS'!AK:AK,$D$4)),IF($B$4="SECOS",AVERAGEIFS('BD SECOS'!U:U,'BD SECOS'!Q:Q,B46,'BD SECOS'!AE:AE,$D$4),IF($B$4="PPA",AVERAGEIFS('BD PPA'!AA:AA,'BD PPA'!U:U,B46,'BD PPA'!AK:AK,$D$4),AVERAGEIFS('BD FRESCOS'!AA:AA,'BD FRESCOS'!U:U,B46,'BD FRESCOS'!AK:AK,$D$4))))),2),"")) -> 20.41 | F46: =IF(OR($B$8=0,E46=""),"",IF(E46<=5,"🟢 Muy Cerca",IF(E46<=10,"🟡 Cerca",IF(E46<=20,"🟠 Moderada","🔴 Lejos")))) -> 🔴 Lejos | G46: =IF(OR($B$8=0,B46=""),"",IFERROR(ROUND(IF($D$4="TODOS",IF($B$4="TODOS",(SUMIF('BD SECOS'!Q:Q,B46,'BD SECOS'!Y:Y)+SUMIF('BD PPA'!U:U,B46,'BD PPA'!AE:AE)+SUMIF('BD FRESCOS'!U:U,B46,'BD FRESCOS'!AE:AE))/(COUNTIF('BD SECOS'!Q:Q,B46)+COUNTIF('BD PPA'!U:U,B46)+COUNTIF('BD FRESCOS'!U:U,B46)),IF($B$4="SECOS",AVERAGEIF('BD SECOS'!Q:Q,B46,'BD SECOS'!Y:Y),IF($B$4="PPA",AVERAGEIF('BD PPA'!U:U,B46,'BD PPA'!AE:AE),AVERAGEIF('BD FRESCOS'!U:U,B46,'BD FRESCOS'!AE:AE)))),IF($B$4="TODOS",(SUMIFS('BD SECOS'!Y:Y,'BD SECOS'!Q:Q,B46,'BD SECOS'!AE:AE,$D$4)+SUMIFS('BD PPA'!AE:AE,'BD PPA'!U:U,B46,'BD PPA'!AK:AK,$D$4)+SUMIFS('BD FRESCOS'!AE:AE,'BD FRESCOS'!U:U,B46,'BD FRESCOS'!AK:AK,$D$4))/(COUNTIFS('BD SECOS'!Q:Q,B46,'BD SECOS'!AE:AE,$D$4)+COUNTIFS('BD PPA'!U:U,B46,'BD PPA'!AK:AK,$D$4)+COUNTIFS('BD FRESCOS'!U:U,B46,'BD FRESCOS'!AK:AK,$D$4)),IF($B$4="SECOS",AVERAGEIFS('BD SECOS'!Y:Y,'BD SECOS'!Q:Q,B46,'BD SECOS'!AE:AE,$D$4),IF($B$4="PPA",AVERAGEIFS('BD PPA'!AE:AE,'BD PPA'!U:U,B46,'BD PPA'!AK:AK,$D$4),AVERAGEIFS('BD FRESCOS'!AE:AE,'BD FRESCOS'!U:U,B46,'BD FRESCOS'!AK:AK,$D$4))))),2),"")) -> 5.62 | H46: =IF(OR($B$8=0,G46=""),"",IF(G46<=1,"🟢 Muy Cerca",IF(G46<=3,"🟡 Cerca",IF(G46<=5,"🟠 Moderada","🔴 Lejos")))) -> 🔴 Lejos | I46: {=IF(OR($B$8=0,B46=""),"",IFERROR(IF($D$4="TODOS",IF($B$4="TODOS",INDEX('BD SECOS'!X:X,MATCH(B46,'BD SECOS'!Q:Q,0)),IF($B$4="SECOS",INDEX('BD SECOS'!X:X,MATCH(B46,'BD SECOS'!Q:Q,0)),IF($B$4="PPA",INDEX('BD PPA'!AD:AD,MATCH(B46,'BD PPA'!U:U,0)),INDEX('BD FRESCOS'!AD:AD,MATCH(B46,'BD FRESCOS'!U:U,0))))),IF($B$4="TODOS",IFERROR(INDEX('BD SECOS'!X:X,MATCH(1,('BD SECOS'!Q:Q=B46)*('BD SECOS'!AE:AE=$D$4),0)),IFERROR(INDEX('BD PPA'!AD:AD,MATCH(1,('BD PPA'!U:U=B46)*('BD PPA'!AK:AK=$D$4),0)),INDEX('BD FRESCOS'!AD:AD,MATCH(1,('BD FRESCOS'!U:U=B46)*('BD FRESCOS'!AK:AK=$D$4),0)))),IF($B$4="SECOS",INDEX('BD SECOS'!X:X,MATCH(1,('BD SECOS'!Q:Q=B46)*('BD SECOS'!AE:AE=$D$4),0)),IF($B$4="PPA",INDEX('BD PPA'!AD:AD,MATCH(1,('BD PPA'!U:U=B46)*('BD PPA'!AK:AK=$D$4),0)),INDEX('BD FRESCOS'!AD:AD,MATCH(1,('BD FRESCOS'!U:U=B46)*('BD FRESCOS'!AK:AK=$D$4),0)))))),""))} -> RUTA 4B | J46: =IF(OR($B$8=0,B46=""),"",IF(AND(E46>20,G46>5),"⚠️ Muy lejos del CD y paraderos",IF(E46>20,"⚠️ Muy lejos del CD",IF(G46>5,"⚠️ Lejos de paraderos","📍 Normal")))) -> ⚠️ Muy lejos del CD y paraderos
A47: =IF(OR($B$8=0,C47="",C47=0),"",9) -> 9 | B47: =IF($B$8=0,"",IFERROR(IF(INDEX(Distritos!$I$7:$I$66,MATCH(SMALL(Distritos!$J$7:$J$66,9),Distritos!$J$7:$J$66,0))=0,"",INDEX(Distritos!$H$7:$H$66,MATCH(SMALL(Distritos!$J$7:$J$66,9),Distritos!$J$7:$J$66,0))),"")) -> Chaclacayo | C47: =IF($B$8=0,"",IFERROR(IF(INDEX(Distritos!$I$7:$I$66,MATCH(SMALL(Distritos!$J$7:$J$66,9),Distritos!$J$7:$J$66,0))=0,"",INDEX(Distritos!$I$7:$I$66,MATCH(SMALL(Distritos!$J$7:$J$66,9),Distritos!$J$7:$J$66,0))),"")) -> 4 | D47: =IF(OR($B$8=0,C47="",C47=0),"",C47/$B$8) -> 0.026143791 | E47: =IF(OR($B$8=0,B47=""),"",IFERROR(ROUND(IF($D$4="TODOS",IF($B$4="TODOS",(SUMIF('BD SECOS'!Q:Q,B47,'BD SECOS'!U:U)+SUMIF('BD PPA'!U:U,B47,'BD PPA'!AA:AA)+SUMIF('BD FRESCOS'!U:U,B47,'BD FRESCOS'!AA:AA))/(COUNTIF('BD SECOS'!Q:Q,B47)+COUNTIF('BD PPA'!U:U,B47)+COUNTIF('BD FRESCOS'!U:U,B47)),IF($B$4="SECOS",AVERAGEIF('BD SECOS'!Q:Q,B47,'BD SECOS'!U:U),IF($B$4="PPA",AVERAGEIF('BD PPA'!U:U,B47,'BD PPA'!AA:AA),AVERAGEIF('BD FRESCOS'!U:U,B47,'BD FRESCOS'!AA:AA)))),IF($B$4="TODOS",(SUMIFS('BD SECOS'!U:U,'BD SECOS'!Q:Q,B47,'BD SECOS'!AE:AE,$D$4)+SUMIFS('BD PPA'!AA:AA,'BD PPA'!U:U,B47,'BD PPA'!AK:AK,$D$4)+SUMIFS('BD FRESCOS'!AA:AA,'BD FRESCOS'!U:U,B47,'BD FRESCOS'!AK:AK,$D$4))/(COUNTIFS('BD SECOS'!Q:Q,B47,'BD SECOS'!AE:AE,$D$4)+COUNTIFS('BD PPA'!U:U,B47,'BD PPA'!AK:AK,$D$4)+COUNTIFS('BD FRESCOS'!U:U,B47,'BD FRESCOS'!AK:AK,$D$4)),IF($B$4="SECOS",AVERAGEIFS('BD SECOS'!U:U,'BD SECOS'!Q:Q,B47,'BD SECOS'!AE:AE,$D$4),IF($B$4="PPA",AVERAGEIFS('BD PPA'!AA:AA,'BD PPA'!U:U,B47,'BD PPA'!AK:AK,$D$4),AVERAGEIFS('BD FRESCOS'!AA:AA,'BD FRESCOS'!U:U,B47,'BD FRESCOS'!AK:AK,$D$4))))),2),"")) -> 10.41 | F47: =IF(OR($B$8=0,E47=""),"",IF(E47<=5,"🟢 Muy Cerca",IF(E47<=10,"🟡 Cerca",IF(E47<=20,"🟠 Moderada","🔴 Lejos")))) -> 🟠 Moderada | G47: =IF(OR($B$8=0,B47=""),"",IFERROR(ROUND(IF($D$4="TODOS",IF($B$4="TODOS",(SUMIF('BD SECOS'!Q:Q,B47,'BD SECOS'!Y:Y)+SUMIF('BD PPA'!U:U,B47,'BD PPA'!AE:AE)+SUMIF('BD FRESCOS'!U:U,B47,'BD FRESCOS'!AE:AE))/(COUNTIF('BD SECOS'!Q:Q,B47)+COUNTIF('BD PPA'!U:U,B47)+COUNTIF('BD FRESCOS'!U:U,B47)),IF($B$4="SECOS",AVERAGEIF('BD SECOS'!Q:Q,B47,'BD SECOS'!Y:Y),IF($B$4="PPA",AVERAGEIF('BD PPA'!U:U,B47,'BD PPA'!AE:AE),AVERAGEIF('BD FRESCOS'!U:U,B47,'BD FRESCOS'!AE:AE)))),IF($B$4="TODOS",(SUMIFS('BD SECOS'!Y:Y,'BD SECOS'!Q:Q,B47,'BD SECOS'!AE:AE,$D$4)+SUMIFS('BD PPA'!AE:AE,'BD PPA'!U:U,B47,'BD PPA'!AK:AK,$D$4)+SUMIFS('BD FRESCOS'!AE:AE,'BD FRESCOS'!U:U,B47,'BD FRESCOS'!AK:AK,$D$4))/(COUNTIFS('BD SECOS'!Q:Q,B47,'BD SECOS'!AE:AE,$D$4)+COUNTIFS('BD PPA'!U:U,B47,'BD PPA'!AK:AK,$D$4)+COUNTIFS('BD FRESCOS'!U:U,B47,'BD FRESCOS'!AK:AK,$D$4)),IF($B$4="SECOS",AVERAGEIFS('BD SECOS'!Y:Y,'BD SECOS'!Q:Q,B47,'BD SECOS'!AE:AE,$D$4),IF($B$4="PPA",AVERAGEIFS('BD PPA'!AE:AE,'BD PPA'!U:U,B47,'BD PPA'!AK:AK,$D$4),AVERAGEIFS('BD FRESCOS'!AE:AE,'BD FRESCOS'!U:U,B47,'BD FRESCOS'!AK:AK,$D$4))))),2),"")) -> 0.84 | H47: =IF(OR($B$8=0,G47=""),"",IF(G47<=1,"🟢 Muy Cerca",IF(G47<=3,"🟡 Cerca",IF(G47<=5,"🟠 Moderada","🔴 Lejos")))) -> 🟢 Muy Cerca | I47: {=IF(OR($B$8=0,B47=""),"",IFERROR(IF($D$4="TODOS",IF($B$4="TODOS",INDEX('BD SECOS'!X:X,MATCH(B47,'BD SECOS'!Q:Q,0)),IF($B$4="SECOS",INDEX('BD SECOS'!X:X,MATCH(B47,'BD SECOS'!Q:Q,0)),IF($B$4="PPA",INDEX('BD PPA'!AD:AD,MATCH(B47,'BD PPA'!U:U,0)),INDEX('BD FRESCOS'!AD:AD,MATCH(B47,'BD FRESCOS'!U:U,0))))),IF($B$4="TODOS",IFERROR(INDEX('BD SECOS'!X:X,MATCH(1,('BD SECOS'!Q:Q=B47)*('BD SECOS'!AE:AE=$D$4),0)),IFERROR(INDEX('BD PPA'!AD:AD,MATCH(1,('BD PPA'!U:U=B47)*('BD PPA'!AK:AK=$D$4),0)),INDEX('BD FRESCOS'!AD:AD,MATCH(1,('BD FRESCOS'!U:U=B47)*('BD FRESCOS'!AK:AK=$D$4),0)))),IF($B$4="SECOS",INDEX('BD SECOS'!X:X,MATCH(1,('BD SECOS'!Q:Q=B47)*('BD SECOS'!AE:AE=$D$4),0)),IF($B$4="PPA",INDEX('BD PPA'!AD:AD,MATCH(1,('BD PPA'!U:U=B47)*('BD PPA'!AK:AK=$D$4),0)),INDEX('BD FRESCOS'!AD:AD,MATCH(1,('BD FRESCOS'!U:U=B47)*('BD FRESCOS'!AK:AK=$D$4),0)))))),""))} -> RUTA 5A | J47: =IF(OR($B$8=0,B47=""),"",IF(AND(E47>20,G47>5),"⚠️ Muy lejos del CD y paraderos",IF(E47>20,"⚠️ Muy lejos del CD",IF(G47>5,"⚠️ Lejos de paraderos","📍 Normal")))) -> 📍 Normal
A48: =IF(OR($B$8=0,C48="",C48=0),"",10) -> 10 | B48: =IF($B$8=0,"",IFERROR(IF(INDEX(Distritos!$I$7:$I$66,MATCH(SMALL(Distritos!$J$7:$J$66,10),Distritos!$J$7:$J$66,0))=0,"",INDEX(Distritos!$H$7:$H$66,MATCH(SMALL(Distritos!$J$7:$J$66,10),Distritos!$J$7:$J$66,0))),"")) -> San Juan De Miraflores | C48: =IF($B$8=0,"",IFERROR(IF(INDEX(Distritos!$I$7:$I$66,MATCH(SMALL(Distritos!$J$7:$J$66,10),Distritos!$J$7:$J$66,0))=0,"",INDEX(Distritos!$I$7:$I$66,MATCH(SMALL(Distritos!$J$7:$J$66,10),Distritos!$J$7:$J$66,0))),"")) -> 4 | D48: =IF(OR($B$8=0,C48="",C48=0),"",C48/$B$8) -> 0.026143791 | E48: =IF(OR($B$8=0,B48=""),"",IFERROR(ROUND(IF($D$4="TODOS",IF($B$4="TODOS",(SUMIF('BD SECOS'!Q:Q,B48,'BD SECOS'!U:U)+SUMIF('BD PPA'!U:U,B48,'BD PPA'!AA:AA)+SUMIF('BD FRESCOS'!U:U,B48,'BD FRESCOS'!AA:AA))/(COUNTIF('BD SECOS'!Q:Q,B48)+COUNTIF('BD PPA'!U:U,B48)+COUNTIF('BD FRESCOS'!U:U,B48)),IF($B$4="SECOS",AVERAGEIF('BD SECOS'!Q:Q,B48,'BD SECOS'!U:U),IF($B$4="PPA",AVERAGEIF('BD PPA'!U:U,B48,'BD PPA'!AA:AA),AVERAGEIF('BD FRESCOS'!U:U,B48,'BD FRESCOS'!AA:AA)))),IF($B$4="TODOS",(SUMIFS('BD SECOS'!U:U,'BD SECOS'!Q:Q,B48,'BD SECOS'!AE:AE,$D$4)+SUMIFS('BD PPA'!AA:AA,'BD PPA'!U:U,B48,'BD PPA'!AK:AK,$D$4)+SUMIFS('BD FRESCOS'!AA:AA,'BD FRESCOS'!U:U,B48,'BD FRESCOS'!AK:AK,$D$4))/(COUNTIFS('BD SECOS'!Q:Q,B48,'BD SECOS'!AE:AE,$D$4)+COUNTIFS('BD PPA'!U:U,B48,'BD PPA'!AK:AK,$D$4)+COUNTIFS('BD FRESCOS'!U:U,B48,'BD FRESCOS'!AK:AK,$D$4)),IF($B$4="SECOS",AVERAGEIFS('BD SECOS'!U:U,'BD SECOS'!Q:Q,B48,'BD SECOS'!AE:AE,$D$4),IF($B$4="PPA",AVERAGEIFS('BD PPA'!AA:AA,'BD PPA'!U:U,B48,'BD PPA'!AK:AK,$D$4),AVERAGEIFS('BD FRESCOS'!AA:AA,'BD FRESCOS'!U:U,B48,'BD FRESCOS'!AK:AK,$D$4))))),2),"")) -> 18.94 | F48: =IF(OR($B$8=0,E48=""),"",IF(E48<=5,"🟢 Muy Cerca",IF(E48<=10,"🟡 Cerca",IF(E48<=20,"🟠 Moderada","🔴 Lejos")))) -> 🟠 Moderada | G48: =IF(OR($B$8=0,B48=""),"",IFERROR(ROUND(IF($D$4="TODOS",IF($B$4="TODOS",(SUMIF('BD SECOS'!Q:Q,B48,'BD SECOS'!Y:Y)+SUMIF('BD PPA'!U:U,B48,'BD PPA'!AE:AE)+SUMIF('BD FRESCOS'!U:U,B48,'BD FRESCOS'!AE:AE))/(COUNTIF('BD SECOS'!Q:Q,B48)+COUNTIF('BD PPA'!U:U,B48)+COUNTIF('BD FRESCOS'!U:U,B48)),IF($B$4="SECOS",AVERAGEIF('BD SECOS'!Q:Q,B48,'BD SECOS'!Y:Y),IF($B$4="PPA",AVERAGEIF('BD PPA'!U:U,B48,'BD PPA'!AE:AE),AVERAGEIF('BD FRESCOS'!U:U,B48,'BD FRESCOS'!AE:AE)))),IF($B$4="TODOS",(SUMIFS('BD SECOS'!Y:Y,'BD SECOS'!Q:Q,B48,'BD SECOS'!AE:AE,$D$4)+SUMIFS('BD PPA'!AE:AE,'BD PPA'!U:U,B48,'BD PPA'!AK:AK,$D$4)+SUMIFS('BD FRESCOS'!AE:AE,'BD FRESCOS'!U:U,B48,'BD FRESCOS'!AK:AK,$D$4))/(COUNTIFS('BD SECOS'!Q:Q,B48,'BD SECOS'!AE:AE,$D$4)+COUNTIFS('BD PPA'!U:U,B48,'BD PPA'!AK:AK,$D$4)+COUNTIFS('BD FRESCOS'!U:U,B48,'BD FRESCOS'!AK:AK,$D$4)),IF($B$4="SECOS",AVERAGEIFS('BD SECOS'!Y:Y,'BD SECOS'!Q:Q,B48,'BD SECOS'!AE:AE,$D$4),IF($B$4="PPA",AVERAGEIFS('BD PPA'!AE:AE,'BD PPA'!U:U,B48,'BD PPA'!AK:AK,$D$4),AVERAGEIFS('BD FRESCOS'!AE:AE,'BD FRESCOS'!U:U,B48,'BD FRESCOS'!AK:AK,$D$4))))),2),"")) -> 1.63 | H48: =IF(OR($B$8=0,G48=""),"",IF(G48<=1,"🟢 Muy Cerca",IF(G48<=3,"🟡 Cerca",IF(G48<=5,"🟠 Moderada","🔴 Lejos")))) -> 🟡 Cerca | I48: {=IF(OR($B$8=0,B48=""),"",IFERROR(IF($D$4="TODOS",IF($B$4="TODOS",INDEX('BD SECOS'!X:X,MATCH(B48,'BD SECOS'!Q:Q,0)),IF($B$4="SECOS",INDEX('BD SECOS'!X:X,MATCH(B48,'BD SECOS'!Q:Q,0)),IF($B$4="PPA",INDEX('BD PPA'!AD:AD,MATCH(B48,'BD PPA'!U:U,0)),INDEX('BD FRESCOS'!AD:AD,MATCH(B48,'BD FRESCOS'!U:U,0))))),IF($B$4="TODOS",IFERROR(INDEX('BD SECOS'!X:X,MATCH(1,('BD SECOS'!Q:Q=B48)*('BD SECOS'!AE:AE=$D$4),0)),IFERROR(INDEX('BD PPA'!AD:AD,MATCH(1,('BD PPA'!U:U=B48)*('BD PPA'!AK:AK=$D$4),0)),INDEX('BD FRESCOS'!AD:AD,MATCH(1,('BD FRESCOS'!U:U=B48)*('BD FRESCOS'!AK:AK=$D$4),0)))),IF($B$4="SECOS",INDEX('BD SECOS'!X:X,MATCH(1,('BD SECOS'!Q:Q=B48)*('BD SECOS'!AE:AE=$D$4),0)),IF($B$4="PPA",INDEX('BD PPA'!AD:AD,MATCH(1,('BD PPA'!U:U=B48)*('BD PPA'!AK:AK=$D$4),0)),INDEX('BD FRESCOS'!AD:AD,MATCH(1,('BD FRESCOS'!U:U=B48)*('BD FRESCOS'!AK:AK=$D$4),0)))))),""))} -> RUTA 7 | J48: =IF(OR($B$8=0,B48=""),"",IF(AND(E48>20,G48>5),"⚠️ Muy lejos del CD y paraderos",IF(E48>20,"⚠️ Muy lejos del CD",IF(G48>5,"⚠️ Lejos de paraderos","📍 Normal")))) -> 📍 Normal
A49: =IF(OR($B$8=0,C49="",C49=0),"",11) -> 11 | B49: =IF($B$8=0,"",IFERROR(IF(INDEX(Distritos!$I$7:$I$66,MATCH(SMALL(Distritos!$J$7:$J$66,11),Distritos!$J$7:$J$66,0))=0,"",INDEX(Distritos!$H$7:$H$66,MATCH(SMALL(Distritos!$J$7:$J$66,11),Distritos!$J$7:$J$66,0))),"")) -> San Martin De Porres | C49: =IF($B$8=0,"",IFERROR(IF(INDEX(Distritos!$I$7:$I$66,MATCH(SMALL(Distritos!$J$7:$J$66,11),Distritos!$J$7:$J$66,0))=0,"",INDEX(Distritos!$I$7:$I$66,MATCH(SMALL(Distritos!$J$7:$J$66,11),Distritos!$J$7:$J$66,0))),"")) -> 4 | D49: =IF(OR($B$8=0,C49="",C49=0),"",C49/$B$8) -> 0.026143791 | E49: =IF(OR($B$8=0,B49=""),"",IFERROR(ROUND(IF($D$4="TODOS",IF($B$4="TODOS",(SUMIF('BD SECOS'!Q:Q,B49,'BD SECOS'!U:U)+SUMIF('BD PPA'!U:U,B49,'BD PPA'!AA:AA)+SUMIF('BD FRESCOS'!U:U,B49,'BD FRESCOS'!AA:AA))/(COUNTIF('BD SECOS'!Q:Q,B49)+COUNTIF('BD PPA'!U:U,B49)+COUNTIF('BD FRESCOS'!U:U,B49)),IF($B$4="SECOS",AVERAGEIF('BD SECOS'!Q:Q,B49,'BD SECOS'!U:U),IF($B$4="PPA",AVERAGEIF('BD PPA'!U:U,B49,'BD PPA'!AA:AA),AVERAGEIF('BD FRESCOS'!U:U,B49,'BD FRESCOS'!AA:AA)))),IF($B$4="TODOS",(SUMIFS('BD SECOS'!U:U,'BD SECOS'!Q:Q,B49,'BD SECOS'!AE:AE,$D$4)+SUMIFS('BD PPA'!AA:AA,'BD PPA'!U:U,B49,'BD PPA'!AK:AK,$D$4)+SUMIFS('BD FRESCOS'!AA:AA,'BD FRESCOS'!U:U,B49,'BD FRESCOS'!AK:AK,$D$4))/(COUNTIFS('BD SECOS'!Q:Q,B49,'BD SECOS'!AE:AE,$D$4)+COUNTIFS('BD PPA'!U:U,B49,'BD PPA'!AK:AK,$D$4)+COUNTIFS('BD FRESCOS'!U:U,B49,'BD FRESCOS'!AK:AK,$D$4)),IF($B$4="SECOS",AVERAGEIFS('BD SECOS'!U:U,'BD SECOS'!Q:Q,B49,'BD SECOS'!AE:AE,$D$4),IF($B$4="PPA",AVERAGEIFS('BD PPA'!AA:AA,'BD PPA'!U:U,B49,'BD PPA'!AK:AK,$D$4),AVERAGEIFS('BD FRESCOS'!AA:AA,'BD FRESCOS'!U:U,B49,'BD FRESCOS'!AK:AK,$D$4))))),2),"")) -> 19.42 | F49: =IF(OR($B$8=0,E49=""),"",IF(E49<=5,"🟢 Muy Cerca",IF(E49<=10,"🟡 Cerca",IF(E49<=20,"🟠 Moderada","🔴 Lejos")))) -> 🟠 Moderada | G49: =IF(OR($B$8=0,B49=""),"",IFERROR(ROUND(IF($D$4="TODOS",IF($B$4="TODOS",(SUMIF('BD SECOS'!Q:Q,B49,'BD SECOS'!Y:Y)+SUMIF('BD PPA'!U:U,B49,'BD PPA'!AE:AE)+SUMIF('BD FRESCOS'!U:U,B49,'BD FRESCOS'!AE:AE))/(COUNTIF('BD SECOS'!Q:Q,B49)+COUNTIF('BD PPA'!U:U,B49)+COUNTIF('BD FRESCOS'!U:U,B49)),IF($B$4="SECOS",AVERAGEIF('BD SECOS'!Q:Q,B49,'BD SECOS'!Y:Y),IF($B$4="PPA",AVERAGEIF('BD PPA'!U:U,B49,'BD PPA'!AE:AE),AVERAGEIF('BD FRESCOS'!U:U,B49,'BD FRESCOS'!AE:AE)))),IF($B$4="TODOS",(SUMIFS('BD SECOS'!Y:Y,'BD SECOS'!Q:Q,B49,'BD SECOS'!AE:AE,$D$4)+SUMIFS('BD PPA'!AE:AE,'BD PPA'!U:U,B49,'BD PPA'!AK:AK,$D$4)+SUMIFS('BD FRESCOS'!AE:AE,'BD FRESCOS'!U:U,B49,'BD FRESCOS'!AK:AK,$D$4))/(COUNTIFS('BD SECOS'!Q:Q,B49,'BD SECOS'!AE:AE,$D$4)+COUNTIFS('BD PPA'!U:U,B49,'BD PPA'!AK:AK,$D$4)+COUNTIFS('BD FRESCOS'!U:U,B49,'BD FRESCOS'!AK:AK,$D$4)),IF($B$4="SECOS",AVERAGEIFS('BD SECOS'!Y:Y,'BD SECOS'!Q:Q,B49,'BD SECOS'!AE:AE,$D$4),IF($B$4="PPA",AVERAGEIFS('BD PPA'!AE:AE,'BD PPA'!U:U,B49,'BD PPA'!AK:AK,$D$4),AVERAGEIFS('BD FRESCOS'!AE:AE,'BD FRESCOS'!U:U,B49,'BD FRESCOS'!AK:AK,$D$4))))),2),"")) -> 1.09 | H49: =IF(OR($B$8=0,G49=""),"",IF(G49<=1,"🟢 Muy Cerca",IF(G49<=3,"🟡 Cerca",IF(G49<=5,"🟠 Moderada","🔴 Lejos")))) -> 🟡 Cerca | I49: {=IF(OR($B$8=0,B49=""),"",IFERROR(IF($D$4="TODOS",IF($B$4="TODOS",INDEX('BD SECOS'!X:X,MATCH(B49,'BD SECOS'!Q:Q,0)),IF($B$4="SECOS",INDEX('BD SECOS'!X:X,MATCH(B49,'BD SECOS'!Q:Q,0)),IF($B$4="PPA",INDEX('BD PPA'!AD:AD,MATCH(B49,'BD PPA'!U:U,0)),INDEX('BD FRESCOS'!AD:AD,MATCH(B49,'BD FRESCOS'!U:U,0))))),IF($B$4="TODOS",IFERROR(INDEX('BD SECOS'!X:X,MATCH(1,('BD SECOS'!Q:Q=B49)*('BD SECOS'!AE:AE=$D$4),0)),IFERROR(INDEX('BD PPA'!AD:AD,MATCH(1,('BD PPA'!U:U=B49)*('BD PPA'!AK:AK=$D$4),0)),INDEX('BD FRESCOS'!AD:AD,MATCH(1,('BD FRESCOS'!U:U=B49)*('BD FRESCOS'!AK:AK=$D$4),0)))),IF($B$4="SECOS",INDEX('BD SECOS'!X:X,MATCH(1,('BD SECOS'!Q:Q=B49)*('BD SECOS'!AE:AE=$D$4),0)),IF($B$4="PPA",INDEX('BD PPA'!AD:AD,MATCH(1,('BD PPA'!U:U=B49)*('BD PPA'!AK:AK=$D$4),0)),INDEX('BD FRESCOS'!AD:AD,MATCH(1,('BD FRESCOS'!U:U=B49)*('BD FRESCOS'!AK:AK=$D$4),0)))))),""))} -> RUTA 5A | J49: =IF(OR($B$8=0,B49=""),"",IF(AND(E49>20,G49>5),"⚠️ Muy lejos del CD y paraderos",IF(E49>20,"⚠️ Muy lejos del CD",IF(G49>5,"⚠️ Lejos de paraderos","📍 Normal")))) -> 📍 Normal
A50: =IF(OR($B$8=0,C50="",C50=0),"",12) -> 12 | B50: =IF($B$8=0,"",IFERROR(IF(INDEX(Distritos!$I$7:$I$66,MATCH(SMALL(Distritos!$J$7:$J$66,12),Distritos!$J$7:$J$66,0))=0,"",INDEX(Distritos!$H$7:$H$66,MATCH(SMALL(Distritos!$J$7:$J$66,12),Distritos!$J$7:$J$66,0))),"")) -> Santa Anita | C50: =IF($B$8=0,"",IFERROR(IF(INDEX(Distritos!$I$7:$I$66,MATCH(SMALL(Distritos!$J$7:$J$66,12),Distritos!$J$7:$J$66,0))=0,"",INDEX(Distritos!$I$7:$I$66,MATCH(SMALL(Distritos!$J$7:$J$66,12),Distritos!$J$7:$J$66,0))),"")) -> 4 | D50: =IF(OR($B$8=0,C50="",C50=0),"",C50/$B$8) -> 0.026143791 | E50: =IF(OR($B$8=0,B50=""),"",IFERROR(ROUND(IF($D$4="TODOS",IF($B$4="TODOS",(SUMIF('BD SECOS'!Q:Q,B50,'BD SECOS'!U:U)+SUMIF('BD PPA'!U:U,B50,'BD PPA'!AA:AA)+SUMIF('BD FRESCOS'!U:U,B50,'BD FRESCOS'!AA:AA))/(COUNTIF('BD SECOS'!Q:Q,B50)+COUNTIF('BD PPA'!U:U,B50)+COUNTIF('BD FRESCOS'!U:U,B50)),IF($B$4="SECOS",AVERAGEIF('BD SECOS'!Q:Q,B50,'BD SECOS'!U:U),IF($B$4="PPA",AVERAGEIF('BD PPA'!U:U,B50,'BD PPA'!AA:AA),AVERAGEIF('BD FRESCOS'!U:U,B50,'BD FRESCOS'!AA:AA)))),IF($B$4="TODOS",(SUMIFS('BD SECOS'!U:U,'BD SECOS'!Q:Q,B50,'BD SECOS'!AE:AE,$D$4)+SUMIFS('BD PPA'!AA:AA,'BD PPA'!U:U,B50,'BD PPA'!AK:AK,$D$4)+SUMIFS('BD FRESCOS'!AA:AA,'BD FRESCOS'!U:U,B50,'BD FRESCOS'!AK:AK,$D$4))/(COUNTIFS('BD SECOS'!Q:Q,B50,'BD SECOS'!AE:AE,$D$4)+COUNTIFS('BD PPA'!U:U,B50,'BD PPA'!AK:AK,$D$4)+COUNTIFS('BD FRESCOS'!U:U,B50,'BD FRESCOS'!AK:AK,$D$4)),IF($B$4="SECOS",AVERAGEIFS('BD SECOS'!U:U,'BD SECOS'!Q:Q,B50,'BD SECOS'!AE:AE,$D$4),IF($B$4="PPA",AVERAGEIFS('BD PPA'!AA:AA,'BD PPA'!U:U,B50,'BD PPA'!AK:AK,$D$4),AVERAGEIFS('BD FRESCOS'!AA:AA,'BD FRESCOS'!U:U,B50,'BD FRESCOS'!AK:AK,$D$4))))),2),"")) -> 7.93 | F50: =IF(OR($B$8=0,E50=""),"",IF(E50<=5,"🟢 Muy Cerca",IF(E50<=10,"🟡 Cerca",IF(E50<=20,"🟠 Moderada","🔴 Lejos")))) -> 🟡 Cerca | G50: =IF(OR($B$8=0,B50=""),"",IFERROR(ROUND(IF($D$4="TODOS",IF($B$4="TODOS",(SUMIF('BD SECOS'!Q:Q,B50,'BD SECOS'!Y:Y)+SUMIF('BD PPA'!U:U,B50,'BD PPA'!AE:AE)+SUMIF('BD FRESCOS'!U:U,B50,'BD FRESCOS'!AE:AE))/(COUNTIF('BD SECOS'!Q:Q,B50)+COUNTIF('BD PPA'!U:U,B50)+COUNTIF('BD FRESCOS'!U:U,B50)),IF($B$4="SECOS",AVERAGEIF('BD SECOS'!Q:Q,B50,'BD SECOS'!Y:Y),IF($B$4="PPA",AVERAGEIF('BD PPA'!U:U,B50,'BD PPA'!AE:AE),AVERAGEIF('BD FRESCOS'!U:U,B50,'BD FRESCOS'!AE:AE)))),IF($B$4="TODOS",(SUMIFS('BD SECOS'!Y:Y,'BD SECOS'!Q:Q,B50,'BD SECOS'!AE:AE,$D$4)+SUMIFS('BD PPA'!AE:AE,'BD PPA'!U:U,B50,'BD PPA'!AK:AK,$D$4)+SUMIFS('BD FRESCOS'!AE:AE,'BD FRESCOS'!U:U,B50,'BD FRESCOS'!AK:AK,$D$4))/(COUNTIFS('BD SECOS'!Q:Q,B50,'BD SECOS'!AE:AE,$D$4)+COUNTIFS('BD PPA'!U:U,B50,'BD PPA'!AK:AK,$D$4)+COUNTIFS('BD FRESCOS'!U:U,B50,'BD FRESCOS'!AK:AK,$D$4)),IF($B$4="SECOS",AVERAGEIFS('BD SECOS'!Y:Y,'BD SECOS'!Q:Q,B50,'BD SECOS'!AE:AE,$D$4),IF($B$4="PPA",AVERAGEIFS('BD PPA'!AE:AE,'BD PPA'!U:U,B50,'BD PPA'!AK:AK,$D$4),AVERAGEIFS('BD FRESCOS'!AE:AE,'BD FRESCOS'!U:U,B50,'BD FRESCOS'!AK:AK,$D$4))))),2),"")) -> 0.52 | H50: =IF(OR($B$8=0,G50=""),"",IF(G50<=1,"🟢 Muy Cerca",IF(G50<=3,"🟡 Cerca",IF(G50<=5,"🟠 Moderada","🔴 Lejos")))) -> 🟢 Muy Cerca | I50: {=IF(OR($B$8=0,B50=""),"",IFERROR(IF($D$4="TODOS",IF($B$4="TODOS",INDEX('BD SECOS'!X:X,MATCH(B50,'BD SECOS'!Q:Q,0)),IF($B$4="SECOS",INDEX('BD SECOS'!X:X,MATCH(B50,'BD SECOS'!Q:Q,0)),IF($B$4="PPA",INDEX('BD PPA'!AD:AD,MATCH(B50,'BD PPA'!U:U,0)),INDEX('BD FRESCOS'!AD:AD,MATCH(B50,'BD FRESCOS'!U:U,0))))),IF($B$4="TODOS",IFERROR(INDEX('BD SECOS'!X:X,MATCH(1,('BD SECOS'!Q:Q=B50)*('BD SECOS'!AE:AE=$D$4),0)),IFERROR(INDEX('BD PPA'!AD:AD,MATCH(1,('BD PPA'!U:U=B50)*('BD PPA'!AK:AK=$D$4),0)),INDEX('BD FRESCOS'!AD:AD,MATCH(1,('BD FRESCOS'!U:U=B50)*('BD FRESCOS'!AK:AK=$D$4),0)))),IF($B$4="SECOS",INDEX('BD SECOS'!X:X,MATCH(1,('BD SECOS'!Q:Q=B50)*('BD SECOS'!AE:AE=$D$4),0)),IF($B$4="PPA",INDEX('BD PPA'!AD:AD,MATCH(1,('BD PPA'!U:U=B50)*('BD PPA'!AK:AK=$D$4),0)),INDEX('BD FRESCOS'!AD:AD,MATCH(1,('BD FRESCOS'!U:U=B50)*('BD FRESCOS'!AK:AK=$D$4),0)))))),""))} -> RUTA 4A | J50: =IF(OR($B$8=0,B50=""),"",IF(AND(E50>20,G50>5),"⚠️ Muy lejos del CD y paraderos",IF(E50>20,"⚠️ Muy lejos del CD",IF(G50>5,"⚠️ Lejos de paraderos","📍 Normal")))) -> 📍 Normal
A51: =IF(OR($B$8=0,C51="",C51=0),"",13) -> 13 | B51: =IF($B$8=0,"",IFERROR(IF(INDEX(Distritos!$I$7:$I$66,MATCH(SMALL(Distritos!$J$7:$J$66,13),Distritos!$J$7:$J$66,0))=0,"",INDEX(Distritos!$H$7:$H$66,MATCH(SMALL(Distritos!$J$7:$J$66,13),Distritos!$J$7:$J$66,0))),"")) -> El Agustino | C51: =IF($B$8=0,"",IFERROR(IF(INDEX(Distritos!$I$7:$I$66,MATCH(SMALL(Distritos!$J$7:$J$66,13),Distritos!$J$7:$J$66,0))=0,"",INDEX(Distritos!$I$7:$I$66,MATCH(SMALL(Distritos!$J$7:$J$66,13),Distritos!$J$7:$J$66,0))),"")) -> 3 | D51: =IF(OR($B$8=0,C51="",C51=0),"",C51/$B$8) -> 0.019607843 | E51: =IF(OR($B$8=0,B51=""),"",IFERROR(ROUND(IF($D$4="TODOS",IF($B$4="TODOS",(SUMIF('BD SECOS'!Q:Q,B51,'BD SECOS'!U:U)+SUMIF('BD PPA'!U:U,B51,'BD PPA'!AA:AA)+SUMIF('BD FRESCOS'!U:U,B51,'BD FRESCOS'!AA:AA))/(COUNTIF('BD SECOS'!Q:Q,B51)+COUNTIF('BD PPA'!U:U,B51)+COUNTIF('BD FRESCOS'!U:U,B51)),IF($B$4="SECOS",AVERAGEIF('BD SECOS'!Q:Q,B51,'BD SECOS'!U:U),IF($B$4="PPA",AVERAGEIF('BD PPA'!U:U,B51,'BD PPA'!AA:AA),AVERAGEIF('BD FRESCOS'!U:U,B51,'BD FRESCOS'!AA:AA)))),IF($B$4="TODOS",(SUMIFS('BD SECOS'!U:U,'BD SECOS'!Q:Q,B51,'BD SECOS'!AE:AE,$D$4)+SUMIFS('BD PPA'!AA:AA,'BD PPA'!U:U,B51,'BD PPA'!AK:AK,$D$4)+SUMIFS('BD FRESCOS'!AA:AA,'BD FRESCOS'!U:U,B51,'BD FRESCOS'!AK:AK,$D$4))/(COUNTIFS('BD SECOS'!Q:Q,B51,'BD SECOS'!AE:AE,$D$4)+COUNTIFS('BD PPA'!U:U,B51,'BD PPA'!AK:AK,$D$4)+COUNTIFS('BD FRESCOS'!U:U,B51,'BD FRESCOS'!AK:AK,$D$4)),IF($B$4="SECOS",AVERAGEIFS('BD SECOS'!U:U,'BD SECOS'!Q:Q,B51,'BD SECOS'!AE:AE,$D$4),IF($B$4="PPA",AVERAGEIFS('BD PPA'!AA:AA,'BD PPA'!U:U,B51,'BD PPA'!AK:AK,$D$4),AVERAGEIFS('BD FRESCOS'!AA:AA,'BD FRESCOS'!U:U,B51,'BD FRESCOS'!AK:AK,$D$4))))),2),"")) -> 10.72 | F51: =IF(OR($B$8=0,E51=""),"",IF(E51<=5,"🟢 Muy Cerca",IF(E51<=10,"🟡 Cerca",IF(E51<=20,"🟠 Moderada","🔴 Lejos")))) -> 🟠 Moderada | G51: =IF(OR($B$8=0,B51=""),"",IFERROR(ROUND(IF($D$4="TODOS",IF($B$4="TODOS",(SUMIF('BD SECOS'!Q:Q,B51,'BD SECOS'!Y:Y)+SUMIF('BD PPA'!U:U,B51,'BD PPA'!AE:AE)+SUMIF('BD FRESCOS'!U:U,B51,'BD FRESCOS'!AE:AE))/(COUNTIF('BD SECOS'!Q:Q,B51)+COUNTIF('BD PPA'!U:U,B51)+COUNTIF('BD FRESCOS'!U:U,B51)),IF($B$4="SECOS",AVERAGEIF('BD SECOS'!Q:Q,B51,'BD SECOS'!Y:Y),IF($B$4="PPA",AVERAGEIF('BD PPA'!U:U,B51,'BD PPA'!AE:AE),AVERAGEIF('BD FRESCOS'!U:U,B51,'BD FRESCOS'!AE:AE)))),IF($B$4="TODOS",(SUMIFS('BD SECOS'!Y:Y,'BD SECOS'!Q:Q,B51,'BD SECOS'!AE:AE,$D$4)+SUMIFS('BD PPA'!AE:AE,'BD PPA'!U:U,B51,'BD PPA'!AK:AK,$D$4)+SUMIFS('BD FRESCOS'!AE:AE,'BD FRESCOS'!U:U,B51,'BD FRESCOS'!AK:AK,$D$4))/(COUNTIFS('BD SECOS'!Q:Q,B51,'BD SECOS'!AE:AE,$D$4)+COUNTIFS('BD PPA'!U:U,B51,'BD PPA'!AK:AK,$D$4)+COUNTIFS('BD FRESCOS'!U:U,B51,'BD FRESCOS'!AK:AK,$D$4)),IF($B$4="SECOS",AVERAGEIFS('BD SECOS'!Y:Y,'BD SECOS'!Q:Q,B51,'BD SECOS'!AE:AE,$D$4),IF($B$4="PPA",AVERAGEIFS('BD PPA'!AE:AE,'BD PPA'!U:U,B51,'BD PPA'!AK:AK,$D$4),AVERAGEIFS('BD FRESCOS'!AE:AE,'BD FRESCOS'!U:U,B51,'BD FRESCOS'!AK:AK,$D$4))))),2),"")) -> 1.16 | H51: =IF(OR($B$8=0,G51=""),"",IF(G51<=1,"🟢 Muy Cerca",IF(G51<=3,"🟡 Cerca",IF(G51<=5,"🟠 Moderada","🔴 Lejos")))) -> 🟡 Cerca | I51: {=IF(OR($B$8=0,B51=""),"",IFERROR(IF($D$4="TODOS",IF($B$4="TODOS",INDEX('BD SECOS'!X:X,MATCH(B51,'BD SECOS'!Q:Q,0)),IF($B$4="SECOS",INDEX('BD SECOS'!X:X,MATCH(B51,'BD SECOS'!Q:Q,0)),IF($B$4="PPA",INDEX('BD PPA'!AD:AD,MATCH(B51,'BD PPA'!U:U,0)),INDEX('BD FRESCOS'!AD:AD,MATCH(B51,'BD FRESCOS'!U:U,0))))),IF($B$4="TODOS",IFERROR(INDEX('BD SECOS'!X:X,MATCH(1,('BD SECOS'!Q:Q=B51)*('BD SECOS'!AE:AE=$D$4),0)),IFERROR(INDEX('BD PPA'!AD:AD,MATCH(1,('BD PPA'!U:U=B51)*('BD PPA'!AK:AK=$D$4),0)),INDEX('BD FRESCOS'!AD:AD,MATCH(1,('BD FRESCOS'!U:U=B51)*('BD FRESCOS'!AK:AK=$D$4),0)))),IF($B$4="SECOS",INDEX('BD SECOS'!X:X,MATCH(1,('BD SECOS'!Q:Q=B51)*('BD SECOS'!AE:AE=$D$4),0)),IF($B$4="PPA",INDEX('BD PPA'!AD:AD,MATCH(1,('BD PPA'!U:U=B51)*('BD PPA'!AK:AK=$D$4),0)),INDEX('BD FRESCOS'!AD:AD,MATCH(1,('BD FRESCOS'!U:U=B51)*('BD FRESCOS'!AK:AK=$D$4),0)))))),""))} -> RUTA 6C | J51: =IF(OR($B$8=0,B51=""),"",IF(AND(E51>20,G51>5),"⚠️ Muy lejos del CD y paraderos",IF(E51>20,"⚠️ Muy lejos del CD",IF(G51>5,"⚠️ Lejos de paraderos","📍 Normal")))) -> 📍 Normal
A52: =IF(OR($B$8=0,C52="",C52=0),"",14) -> 14 | B52: =IF($B$8=0,"",IFERROR(IF(INDEX(Distritos!$I$7:$I$66,MATCH(SMALL(Distritos!$J$7:$J$66,14),Distritos!$J$7:$J$66,0))=0,"",INDEX(Distritos!$H$7:$H$66,MATCH(SMALL(Distritos!$J$7:$J$66,14),Distritos!$J$7:$J$66,0))),"")) -> La Molina | C52: =IF($B$8=0,"",IFERROR(IF(INDEX(Distritos!$I$7:$I$66,MATCH(SMALL(Distritos!$J$7:$J$66,14),Distritos!$J$7:$J$66,0))=0,"",INDEX(Distritos!$I$7:$I$66,MATCH(SMALL(Distritos!$J$7:$J$66,14),Distritos!$J$7:$J$66,0))),"")) -> 3 | D52: =IF(OR($B$8=0,C52="",C52=0),"",C52/$B$8) -> 0.019607843 | E52: =IF(OR($B$8=0,B52=""),"",IFERROR(ROUND(IF($D$4="TODOS",IF($B$4="TODOS",(SUMIF('BD SECOS'!Q:Q,B52,'BD SECOS'!U:U)+SUMIF('BD PPA'!U:U,B52,'BD PPA'!AA:AA)+SUMIF('BD FRESCOS'!U:U,B52,'BD FRESCOS'!AA:AA))/(COUNTIF('BD SECOS'!Q:Q,B52)+COUNTIF('BD PPA'!U:U,B52)+COUNTIF('BD FRESCOS'!U:U,B52)),IF($B$4="SECOS",AVERAGEIF('BD SECOS'!Q:Q,B52,'BD SECOS'!U:U),IF($B$4="PPA",AVERAGEIF('BD PPA'!U:U,B52,'BD PPA'!AA:AA),AVERAGEIF('BD FRESCOS'!U:U,B52,'BD FRESCOS'!AA:AA)))),IF($B$4="TODOS",(SUMIFS('BD SECOS'!U:U,'BD SECOS'!Q:Q,B52,'BD SECOS'!AE:AE,$D$4)+SUMIFS('BD PPA'!AA:AA,'BD PPA'!U:U,B52,'BD PPA'!AK:AK,$D$4)+SUMIFS('BD FRESCOS'!AA:AA,'BD FRESCOS'!U:U,B52,'BD FRESCOS'!AK:AK,$D$4))/(COUNTIFS('BD SECOS'!Q:Q,B52,'BD SECOS'!AE:AE,$D$4)+COUNTIFS('BD PPA'!U:U,B52,'BD PPA'!AK:AK,$D$4)+COUNTIFS('BD FRESCOS'!U:U,B52,'BD FRESCOS'!AK:AK,$D$4)),IF($B$4="SECOS",AVERAGEIFS('BD SECOS'!U:U,'BD SECOS'!Q:Q,B52,'BD SECOS'!AE:AE,$D$4),IF($B$4="PPA",AVERAGEIFS('BD PPA'!AA:AA,'BD PPA'!U:U,B52,'BD PPA'!AK:AK,$D$4),AVERAGEIFS('BD FRESCOS'!AA:AA,'BD FRESCOS'!U:U,B52,'BD FRESCOS'!AK:AK,$D$4))))),2),"")) -> 12.23 | F52: =IF(OR($B$8=0,E52=""),"",IF(E52<=5,"🟢 Muy Cerca",IF(E52<=10,"🟡 Cerca",IF(E52<=20,"🟠 Moderada","🔴 Lejos")))) -> 🟠 Moderada | G52: =IF(OR($B$8=0,B52=""),"",IFERROR(ROUND(IF($D$4="TODOS",IF($B$4="TODOS",(SUMIF('BD SECOS'!Q:Q,B52,'BD SECOS'!Y:Y)+SUMIF('BD PPA'!U:U,B52,'BD PPA'!AE:AE)+SUMIF('BD FRESCOS'!U:U,B52,'BD FRESCOS'!AE:AE))/(COUNTIF('BD SECOS'!Q:Q,B52)+COUNTIF('BD PPA'!U:U,B52)+COUNTIF('BD FRESCOS'!U:U,B52)),IF($B$4="SECOS",AVERAGEIF('BD SECOS'!Q:Q,B52,'BD SECOS'!Y:Y),IF($B$4="PPA",AVERAGEIF('BD PPA'!U:U,B52,'BD PPA'!AE:AE),AVERAGEIF('BD FRESCOS'!U:U,B52,'BD FRESCOS'!AE:AE)))),IF($B$4="TODOS",(SUMIFS('BD SECOS'!Y:Y,'BD SECOS'!Q:Q,B52,'BD SECOS'!AE:AE,$D$4)+SUMIFS('BD PPA'!AE:AE,'BD PPA'!U:U,B52,'BD PPA'!AK:AK,$D$4)+SUMIFS('BD FRESCOS'!AE:AE,'BD FRESCOS'!U:U,B52,'BD FRESCOS'!AK:AK,$D$4))/(COUNTIFS('BD SECOS'!Q:Q,B52,'BD SECOS'!AE:AE,$D$4)+COUNTIFS('BD PPA'!U:U,B52,'BD PPA'!AK:AK,$D$4)+COUNTIFS('BD FRESCOS'!U:U,B52,'BD FRESCOS'!AK:AK,$D$4)),IF($B$4="SECOS",AVERAGEIFS('BD SECOS'!Y:Y,'BD SECOS'!Q:Q,B52,'BD SECOS'!AE:AE,$D$4),IF($B$4="PPA",AVERAGEIFS('BD PPA'!AE:AE,'BD PPA'!U:U,B52,'BD PPA'!AK:AK,$D$4),AVERAGEIFS('BD FRESCOS'!AE:AE,'BD FRESCOS'!U:U,B52,'BD FRESCOS'!AK:AK,$D$4))))),2),"")) -> 2.25 | H52: =IF(OR($B$8=0,G52=""),"",IF(G52<=1,"🟢 Muy Cerca",IF(G52<=3,"🟡 Cerca",IF(G52<=5,"🟠 Moderada","🔴 Lejos")))) -> 🟡 Cerca | I52: {=IF(OR($B$8=0,B52=""),"",IFERROR(IF($D$4="TODOS",IF($B$4="TODOS",INDEX('BD SECOS'!X:X,MATCH(B52,'BD SECOS'!Q:Q,0)),IF($B$4="SECOS",INDEX('BD SECOS'!X:X,MATCH(B52,'BD SECOS'!Q:Q,0)),IF($B$4="PPA",INDEX('BD PPA'!AD:AD,MATCH(B52,'BD PPA'!U:U,0)),INDEX('BD FRESCOS'!AD:AD,MATCH(B52,'BD FRESCOS'!U:U,0))))),IF($B$4="TODOS",IFERROR(INDEX('BD SECOS'!X:X,MATCH(1,('BD SECOS'!Q:Q=B52)*('BD SECOS'!AE:AE=$D$4),0)),IFERROR(INDEX('BD PPA'!AD:AD,MATCH(1,('BD PPA'!U:U=B52)*('BD PPA'!AK:AK=$D$4),0)),INDEX('BD FRESCOS'!AD:AD,MATCH(1,('BD FRESCOS'!U:U=B52)*('BD FRESCOS'!AK:AK=$D$4),0)))),IF($B$4="SECOS",INDEX('BD SECOS'!X:X,MATCH(1,('BD SECOS'!Q:Q=B52)*('BD SECOS'!AE:AE=$D$4),0)),IF($B$4="PPA",INDEX('BD PPA'!AD:AD,MATCH(1,('BD PPA'!U:U=B52)*('BD PPA'!AK:AK=$D$4),0)),INDEX('BD FRESCOS'!AD:AD,MATCH(1,('BD FRESCOS'!U:U=B52)*('BD FRESCOS'!AK:AK=$D$4),0)))))),""))} -> RUTA 7 | J52: =IF(OR($B$8=0,B52=""),"",IF(AND(E52>20,G52>5),"⚠️ Muy lejos del CD y paraderos",IF(E52>20,"⚠️ Muy lejos del CD",IF(G52>5,"⚠️ Lejos de paraderos","📍 Normal")))) -> 📍 Normal
A53: =IF(OR($B$8=0,C53="",C53=0),"",15) -> 15 | B53: =IF($B$8=0,"",IFERROR(IF(INDEX(Distritos!$I$7:$I$66,MATCH(SMALL(Distritos!$J$7:$J$66,15),Distritos!$J$7:$J$66,0))=0,"",INDEX(Distritos!$H$7:$H$66,MATCH(SMALL(Distritos!$J$7:$J$66,15),Distritos!$J$7:$J$66,0))),"")) -> Pueblo Libre | C53: =IF($B$8=0,"",IFERROR(IF(INDEX(Distritos!$I$7:$I$66,MATCH(SMALL(Distritos!$J$7:$J$66,15),Distritos!$J$7:$J$66,0))=0,"",INDEX(Distritos!$I$7:$I$66,MATCH(SMALL(Distritos!$J$7:$J$66,15),Distritos!$J$7:$J$66,0))),"")) -> 3 | D53: =IF(OR($B$8=0,C53="",C53=0),"",C53/$B$8) -> 0.019607843 | E53: =IF(OR($B$8=0,B53=""),"",IFERROR(ROUND(IF($D$4="TODOS",IF($B$4="TODOS",(SUMIF('BD SECOS'!Q:Q,B53,'BD SECOS'!U:U)+SUMIF('BD PPA'!U:U,B53,'BD PPA'!AA:AA)+SUMIF('BD FRESCOS'!U:U,B53,'BD FRESCOS'!AA:AA))/(COUNTIF('BD SECOS'!Q:Q,B53)+COUNTIF('BD PPA'!U:U,B53)+COUNTIF('BD FRESCOS'!U:U,B53)),IF($B$4="SECOS",AVERAGEIF('BD SECOS'!Q:Q,B53,'BD SECOS'!U:U),IF($B$4="PPA",AVERAGEIF('BD PPA'!U:U,B53,'BD PPA'!AA:AA),AVERAGEIF('BD FRESCOS'!U:U,B53,'BD FRESCOS'!AA:AA)))),IF($B$4="TODOS",(SUMIFS('BD SECOS'!U:U,'BD SECOS'!Q:Q,B53,'BD SECOS'!AE:AE,$D$4)+SUMIFS('BD PPA'!AA:AA,'BD PPA'!U:U,B53,'BD PPA'!AK:AK,$D$4)+SUMIFS('BD FRESCOS'!AA:AA,'BD FRESCOS'!U:U,B53,'BD FRESCOS'!AK:AK,$D$4))/(COUNTIFS('BD SECOS'!Q:Q,B53,'BD SECOS'!AE:AE,$D$4)+COUNTIFS('BD PPA'!U:U,B53,'BD PPA'!AK:AK,$D$4)+COUNTIFS('BD FRESCOS'!U:U,B53,'BD FRESCOS'!AK:AK,$D$4)),IF($B$4="SECOS",AVERAGEIFS('BD SECOS'!U:U,'BD SECOS'!Q:Q,B53,'BD SECOS'!AE:AE,$D$4),IF($B$4="PPA",AVERAGEIFS('BD PPA'!AA:AA,'BD PPA'!U:U,B53,'BD PPA'!AK:AK,$D$4),AVERAGEIFS('BD FRESCOS'!AA:AA,'BD FRESCOS'!U:U,B53,'BD FRESCOS'!AK:AK,$D$4))))),2),"")) -> 20.07 | F53: =IF(OR($B$8=0,E53=""),"",IF(E53<=5,"🟢 Muy Cerca",IF(E53<=10,"🟡 Cerca",IF(E53<=20,"🟠 Moderada","🔴 Lejos")))) -> 🔴 Lejos | G53: =IF(OR($B$8=0,B53=""),"",IFERROR(ROUND(IF($D$4="TODOS",IF($B$4="TODOS",(SUMIF('BD SECOS'!Q:Q,B53,'BD SECOS'!Y:Y)+SUMIF('BD PPA'!U:U,B53,'BD PPA'!AE:AE)+SUMIF('BD FRESCOS'!U:U,B53,'BD FRESCOS'!AE:AE))/(COUNTIF('BD SECOS'!Q:Q,B53)+COUNTIF('BD PPA'!U:U,B53)+COUNTIF('BD FRESCOS'!U:U,B53)),IF($B$4="SECOS",AVERAGEIF('BD SECOS'!Q:Q,B53,'BD SECOS'!Y:Y),IF($B$4="PPA",AVERAGEIF('BD PPA'!U:U,B53,'BD PPA'!AE:AE),AVERAGEIF('BD FRESCOS'!U:U,B53,'BD FRESCOS'!AE:AE)))),IF($B$4="TODOS",(SUMIFS('BD SECOS'!Y:Y,'BD SECOS'!Q:Q,B53,'BD SECOS'!AE:AE,$D$4)+SUMIFS('BD PPA'!AE:AE,'BD PPA'!U:U,B53,'BD PPA'!AK:AK,$D$4)+SUMIFS('BD FRESCOS'!AE:AE,'BD FRESCOS'!U:U,B53,'BD FRESCOS'!AK:AK,$D$4))/(COUNTIFS('BD SECOS'!Q:Q,B53,'BD SECOS'!AE:AE,$D$4)+COUNTIFS('BD PPA'!U:U,B53,'BD PPA'!AK:AK,$D$4)+COUNTIFS('BD FRESCOS'!U:U,B53,'BD FRESCOS'!AK:AK,$D$4)),IF($B$4="SECOS",AVERAGEIFS('BD SECOS'!Y:Y,'BD SECOS'!Q:Q,B53,'BD SECOS'!AE:AE,$D$4),IF($B$4="PPA",AVERAGEIFS('BD PPA'!AE:AE,'BD PPA'!U:U,B53,'BD PPA'!AK:AK,$D$4),AVERAGEIFS('BD FRESCOS'!AE:AE,'BD FRESCOS'!U:U,B53,'BD FRESCOS'!AK:AK,$D$4))))),2),"")) -> 1.85 | H53: =IF(OR($B$8=0,G53=""),"",IF(G53<=1,"🟢 Muy Cerca",IF(G53<=3,"🟡 Cerca",IF(G53<=5,"🟠 Moderada","🔴 Lejos")))) -> 🟡 Cerca | I53: {=IF(OR($B$8=0,B53=""),"",IFERROR(IF($D$4="TODOS",IF($B$4="TODOS",INDEX('BD SECOS'!X:X,MATCH(B53,'BD SECOS'!Q:Q,0)),IF($B$4="SECOS",INDEX('BD SECOS'!X:X,MATCH(B53,'BD SECOS'!Q:Q,0)),IF($B$4="PPA",INDEX('BD PPA'!AD:AD,MATCH(B53,'BD PPA'!U:U,0)),INDEX('BD FRESCOS'!AD:AD,MATCH(B53,'BD FRESCOS'!U:U,0))))),IF($B$4="TODOS",IFERROR(INDEX('BD SECOS'!X:X,MATCH(1,('BD SECOS'!Q:Q=B53)*('BD SECOS'!AE:AE=$D$4),0)),IFERROR(INDEX('BD PPA'!AD:AD,MATCH(1,('BD PPA'!U:U=B53)*('BD PPA'!AK:AK=$D$4),0)),INDEX('BD FRESCOS'!AD:AD,MATCH(1,('BD FRESCOS'!U:U=B53)*('BD FRESCOS'!AK:AK=$D$4),0)))),IF($B$4="SECOS",INDEX('BD SECOS'!X:X,MATCH(1,('BD SECOS'!Q:Q=B53)*('BD SECOS'!AE:AE=$D$4),0)),IF($B$4="PPA",INDEX('BD PPA'!AD:AD,MATCH(1,('BD PPA'!U:U=B53)*('BD PPA'!AK:AK=$D$4),0)),INDEX('BD FRESCOS'!AD:AD,MATCH(1,('BD FRESCOS'!U:U=B53)*('BD FRESCOS'!AK:AK=$D$4),0)))))),""))} -> RUTA 9 | J53: =IF(OR($B$8=0,B53=""),"",IF(AND(E53>20,G53>5),"⚠️ Muy lejos del CD y paraderos",IF(E53>20,"⚠️ Muy lejos del CD",IF(G53>5,"⚠️ Lejos de paraderos","📍 Normal")))) -> ⚠️ Muy lejos del CD
A54: =IF(OR($B$8=0,C54="",C54=0),"",16) -> 16 | B54: =IF($B$8=0,"",IFERROR(IF(INDEX(Distritos!$I$7:$I$66,MATCH(SMALL(Distritos!$J$7:$J$66,16),Distritos!$J$7:$J$66,0))=0,"",INDEX(Distritos!$H$7:$H$66,MATCH(SMALL(Distritos!$J$7:$J$66,16),Distritos!$J$7:$J$66,0))),"")) -> Brena | C54: =IF($B$8=0,"",IFERROR(IF(INDEX(Distritos!$I$7:$I$66,MATCH(SMALL(Distritos!$J$7:$J$66,16),Distritos!$J$7:$J$66,0))=0,"",INDEX(Distritos!$I$7:$I$66,MATCH(SMALL(Distritos!$J$7:$J$66,16),Distritos!$J$7:$J$66,0))),"")) -> 2 | D54: =IF(OR($B$8=0,C54="",C54=0),"",C54/$B$8) -> 0.013071895 | E54: =IF(OR($B$8=0,B54=""),"",IFERROR(ROUND(IF($D$4="TODOS",IF($B$4="TODOS",(SUMIF('BD SECOS'!Q:Q,B54,'BD SECOS'!U:U)+SUMIF('BD PPA'!U:U,B54,'BD PPA'!AA:AA)+SUMIF('BD FRESCOS'!U:U,B54,'BD FRESCOS'!AA:AA))/(COUNTIF('BD SECOS'!Q:Q,B54)+COUNTIF('BD PPA'!U:U,B54)+COUNTIF('BD FRESCOS'!U:U,B54)),IF($B$4="SECOS",AVERAGEIF('BD SECOS'!Q:Q,B54,'BD SECOS'!U:U),IF($B$4="PPA",AVERAGEIF('BD PPA'!U:U,B54,'BD PPA'!AA:AA),AVERAGEIF('BD FRESCOS'!U:U,B54,'BD FRESCOS'!AA:AA)))),IF($B$4="TODOS",(SUMIFS('BD SECOS'!U:U,'BD SECOS'!Q:Q,B54,'BD SECOS'!AE:AE,$D$4)+SUMIFS('BD PPA'!AA:AA,'BD PPA'!U:U,B54,'BD PPA'!AK:AK,$D$4)+SUMIFS('BD FRESCOS'!AA:AA,'BD FRESCOS'!U:U,B54,'BD FRESCOS'!AK:AK,$D$4))/(COUNTIFS('BD SECOS'!Q:Q,B54,'BD SECOS'!AE:AE,$D$4)+COUNTIFS('BD PPA'!U:U,B54,'BD PPA'!AK:AK,$D$4)+COUNTIFS('BD FRESCOS'!U:U,B54,'BD FRESCOS'!AK:AK,$D$4)),IF($B$4="SECOS",AVERAGEIFS('BD SECOS'!U:U,'BD SECOS'!Q:Q,B54,'BD SECOS'!AE:AE,$D$4),IF($B$4="PPA",AVERAGEIFS('BD PPA'!AA:AA,'BD PPA'!U:U,B54,'BD PPA'!AK:AK,$D$4),AVERAGEIFS('BD FRESCOS'!AA:AA,'BD FRESCOS'!U:U,B54,'BD FRESCOS'!AK:AK,$D$4))))),2),"")) -> 18.02 | F54: =IF(OR($B$8=0,E54=""),"",IF(E54<=5,"🟢 Muy Cerca",IF(E54<=10,"🟡 Cerca",IF(E54<=20,"🟠 Moderada","🔴 Lejos")))) -> 🟠 Moderada | G54: =IF(OR($B$8=0,B54=""),"",IFERROR(ROUND(IF($D$4="TODOS",IF($B$4="TODOS",(SUMIF('BD SECOS'!Q:Q,B54,'BD SECOS'!Y:Y)+SUMIF('BD PPA'!U:U,B54,'BD PPA'!AE:AE)+SUMIF('BD FRESCOS'!U:U,B54,'BD FRESCOS'!AE:AE))/(COUNTIF('BD SECOS'!Q:Q,B54)+COUNTIF('BD PPA'!U:U,B54)+COUNTIF('BD FRESCOS'!U:U,B54)),IF($B$4="SECOS",AVERAGEIF('BD SECOS'!Q:Q,B54,'BD SECOS'!Y:Y),IF($B$4="PPA",AVERAGEIF('BD PPA'!U:U,B54,'BD PPA'!AE:AE),AVERAGEIF('BD FRESCOS'!U:U,B54,'BD FRESCOS'!AE:AE)))),IF($B$4="TODOS",(SUMIFS('BD SECOS'!Y:Y,'BD SECOS'!Q:Q,B54,'BD SECOS'!AE:AE,$D$4)+SUMIFS('BD PPA'!AE:AE,'BD PPA'!U:U,B54,'BD PPA'!AK:AK,$D$4)+SUMIFS('BD FRESCOS'!AE:AE,'BD FRESCOS'!U:U,B54,'BD FRESCOS'!AK:AK,$D$4))/(COUNTIFS('BD SECOS'!Q:Q,B54,'BD SECOS'!AE:AE,$D$4)+COUNTIFS('BD PPA'!U:U,B54,'BD PPA'!AK:AK,$D$4)+COUNTIFS('BD FRESCOS'!U:U,B54,'BD FRESCOS'!AK:AK,$D$4)),IF($B$4="SECOS",AVERAGEIFS('BD SECOS'!Y:Y,'BD SECOS'!Q:Q,B54,'BD SECOS'!AE:AE,$D$4),IF($B$4="PPA",AVERAGEIFS('BD PPA'!AE:AE,'BD PPA'!U:U,B54,'BD PPA'!AK:AK,$D$4),AVERAGEIFS('BD FRESCOS'!AE:AE,'BD FRESCOS'!U:U,B54,'BD FRESCOS'!AK:AK,$D$4))))),2),"")) -> 1.79 | H54: =IF(OR($B$8=0,G54=""),"",IF(G54<=1,"🟢 Muy Cerca",IF(G54<=3,"🟡 Cerca",IF(G54<=5,"🟠 Moderada","🔴 Lejos")))) -> 🟡 Cerca | I54: {=IF(OR($B$8=0,B54=""),"",IFERROR(IF($D$4="TODOS",IF($B$4="TODOS",INDEX('BD SECOS'!X:X,MATCH(B54,'BD SECOS'!Q:Q,0)),IF($B$4="SECOS",INDEX('BD SECOS'!X:X,MATCH(B54,'BD SECOS'!Q:Q,0)),IF($B$4="PPA",INDEX('BD PPA'!AD:AD,MATCH(B54,'BD PPA'!U:U,0)),INDEX('BD FRESCOS'!AD:AD,MATCH(B54,'BD FRESCOS'!U:U,0))))),IF($B$4="TODOS",IFERROR(INDEX('BD SECOS'!X:X,MATCH(1,('BD SECOS'!Q:Q=B54)*('BD SECOS'!AE:AE=$D$4),0)),IFERROR(INDEX('BD PPA'!AD:AD,MATCH(1,('BD PPA'!U:U=B54)*('BD PPA'!AK:AK=$D$4),0)),INDEX('BD FRESCOS'!AD:AD,MATCH(1,('BD FRESCOS'!U:U=B54)*('BD FRESCOS'!AK:AK=$D$4),0)))),IF($B$4="SECOS",INDEX('BD SECOS'!X:X,MATCH(1,('BD SECOS'!Q:Q=B54)*('BD SECOS'!AE:AE=$D$4),0)),IF($B$4="PPA",INDEX('BD PPA'!AD:AD,MATCH(1,('BD PPA'!U:U=B54)*('BD PPA'!AK:AK=$D$4),0)),INDEX('BD FRESCOS'!AD:AD,MATCH(1,('BD FRESCOS'!U:U=B54)*('BD FRESCOS'!AK:AK=$D$4),0)))))),""))} -> RUTA 3 | J54: =IF(OR($B$8=0,B54=""),"",IF(AND(E54>20,G54>5),"⚠️ Muy lejos del CD y paraderos",IF(E54>20,"⚠️ Muy lejos del CD",IF(G54>5,"⚠️ Lejos de paraderos","📍 Normal")))) -> 📍 Normal
A55: =IF(OR($B$8=0,C55="",C55=0),"",17) -> 17 | B55: =IF($B$8=0,"",IFERROR(IF(INDEX(Distritos!$I$7:$I$66,MATCH(SMALL(Distritos!$J$7:$J$66,17),Distritos!$J$7:$J$66,0))=0,"",INDEX(Distritos!$H$7:$H$66,MATCH(SMALL(Distritos!$J$7:$J$66,17),Distritos!$J$7:$J$66,0))),"")) -> Chorrillos | C55: =IF($B$8=0,"",IFERROR(IF(INDEX(Distritos!$I$7:$I$66,MATCH(SMALL(Distritos!$J$7:$J$66,17),Distritos!$J$7:$J$66,0))=0,"",INDEX(Distritos!$I$7:$I$66,MATCH(SMALL(Distritos!$J$7:$J$66,17),Distritos!$J$7:$J$66,0))),"")) -> 2 | D55: =IF(OR($B$8=0,C55="",C55=0),"",C55/$B$8) -> 0.013071895 | E55: =IF(OR($B$8=0,B55=""),"",IFERROR(ROUND(IF($D$4="TODOS",IF($B$4="TODOS",(SUMIF('BD SECOS'!Q:Q,B55,'BD SECOS'!U:U)+SUMIF('BD PPA'!U:U,B55,'BD PPA'!AA:AA)+SUMIF('BD FRESCOS'!U:U,B55,'BD FRESCOS'!AA:AA))/(COUNTIF('BD SECOS'!Q:Q,B55)+COUNTIF('BD PPA'!U:U,B55)+COUNTIF('BD FRESCOS'!U:U,B55)),IF($B$4="SECOS",AVERAGEIF('BD SECOS'!Q:Q,B55,'BD SECOS'!U:U),IF($B$4="PPA",AVERAGEIF('BD PPA'!U:U,B55,'BD PPA'!AA:AA),AVERAGEIF('BD FRESCOS'!U:U,B55,'BD FRESCOS'!AA:AA)))),IF($B$4="TODOS",(SUMIFS('BD SECOS'!U:U,'BD SECOS'!Q:Q,B55,'BD SECOS'!AE:AE,$D$4)+SUMIFS('BD PPA'!AA:AA,'BD PPA'!U:U,B55,'BD PPA'!AK:AK,$D$4)+SUMIFS('BD FRESCOS'!AA:AA,'BD FRESCOS'!U:U,B55,'BD FRESCOS'!AK:AK,$D$4))/(COUNTIFS('BD SECOS'!Q:Q,B55,'BD SECOS'!AE:AE,$D$4)+COUNTIFS('BD PPA'!U:U,B55,'BD PPA'!AK:AK,$D$4)+COUNTIFS('BD FRESCOS'!U:U,B55,'BD FRESCOS'!AK:AK,$D$4)),IF($B$4="SECOS",AVERAGEIFS('BD SECOS'!U:U,'BD SECOS'!Q:Q,B55,'BD SECOS'!AE:AE,$D$4),IF($B$4="PPA",AVERAGEIFS('BD PPA'!AA:AA,'BD PPA'!U:U,B55,'BD PPA'!AK:AK,$D$4),AVERAGEIFS('BD FRESCOS'!AA:AA,'BD FRESCOS'!U:U,B55,'BD FRESCOS'!AK:AK,$D$4))))),2),"")) -> 24.03 | F55: =IF(OR($B$8=0,E55=""),"",IF(E55<=5,"🟢 Muy Cerca",IF(E55<=10,"🟡 Cerca",IF(E55<=20,"🟠 Moderada","🔴 Lejos")))) -> 🔴 Lejos | G55: =IF(OR($B$8=0,B55=""),"",IFERROR(ROUND(IF($D$4="TODOS",IF($B$4="TODOS",(SUMIF('BD SECOS'!Q:Q,B55,'BD SECOS'!Y:Y)+SUMIF('BD PPA'!U:U,B55,'BD PPA'!AE:AE)+SUMIF('BD FRESCOS'!U:U,B55,'BD FRESCOS'!AE:AE))/(COUNTIF('BD SECOS'!Q:Q,B55)+COUNTIF('BD PPA'!U:U,B55)+COUNTIF('BD FRESCOS'!U:U,B55)),IF($B$4="SECOS",AVERAGEIF('BD SECOS'!Q:Q,B55,'BD SECOS'!Y:Y),IF($B$4="PPA",AVERAGEIF('BD PPA'!U:U,B55,'BD PPA'!AE:AE),AVERAGEIF('BD FRESCOS'!U:U,B55,'BD FRESCOS'!AE:AE)))),IF($B$4="TODOS",(SUMIFS('BD SECOS'!Y:Y,'BD SECOS'!Q:Q,B55,'BD SECOS'!AE:AE,$D$4)+SUMIFS('BD PPA'!AE:AE,'BD PPA'!U:U,B55,'BD PPA'!AK:AK,$D$4)+SUMIFS('BD FRESCOS'!AE:AE,'BD FRESCOS'!U:U,B55,'BD FRESCOS'!AK:AK,$D$4))/(COUNTIFS('BD SECOS'!Q:Q,B55,'BD SECOS'!AE:AE,$D$4)+COUNTIFS('BD PPA'!U:U,B55,'BD PPA'!AK:AK,$D$4)+COUNTIFS('BD FRESCOS'!U:U,B55,'BD FRESCOS'!AK:AK,$D$4)),IF($B$4="SECOS",AVERAGEIFS('BD SECOS'!Y:Y,'BD SECOS'!Q:Q,B55,'BD SECOS'!AE:AE,$D$4),IF($B$4="PPA",AVERAGEIFS('BD PPA'!AE:AE,'BD PPA'!U:U,B55,'BD PPA'!AK:AK,$D$4),AVERAGEIFS('BD FRESCOS'!AE:AE,'BD FRESCOS'!U:U,B55,'BD FRESCOS'!AK:AK,$D$4))))),2),"")) -> 3.54 | H55: =IF(OR($B$8=0,G55=""),"",IF(G55<=1,"🟢 Muy Cerca",IF(G55<=3,"🟡 Cerca",IF(G55<=5,"🟠 Moderada","🔴 Lejos")))) -> 🟠 Moderada | I55: {=IF(OR($B$8=0,B55=""),"",IFERROR(IF($D$4="TODOS",IF($B$4="TODOS",INDEX('BD SECOS'!X:X,MATCH(B55,'BD SECOS'!Q:Q,0)),IF($B$4="SECOS",INDEX('BD SECOS'!X:X,MATCH(B55,'BD SECOS'!Q:Q,0)),IF($B$4="PPA",INDEX('BD PPA'!AD:AD,MATCH(B55,'BD PPA'!U:U,0)),INDEX('BD FRESCOS'!AD:AD,MATCH(B55,'BD FRESCOS'!U:U,0))))),IF($B$4="TODOS",IFERROR(INDEX('BD SECOS'!X:X,MATCH(1,('BD SECOS'!Q:Q=B55)*('BD SECOS'!AE:AE=$D$4),0)),IFERROR(INDEX('BD PPA'!AD:AD,MATCH(1,('BD PPA'!U:U=B55)*('BD PPA'!AK:AK=$D$4),0)),INDEX('BD FRESCOS'!AD:AD,MATCH(1,('BD FRESCOS'!U:U=B55)*('BD FRESCOS'!AK:AK=$D$4),0)))),IF($B$4="SECOS",INDEX('BD SECOS'!X:X,MATCH(1,('BD SECOS'!Q:Q=B55)*('BD SECOS'!AE:AE=$D$4),0)),IF($B$4="PPA",INDEX('BD PPA'!AD:AD,MATCH(1,('BD PPA'!U:U=B55)*('BD PPA'!AK:AK=$D$4),0)),INDEX('BD FRESCOS'!AD:AD,MATCH(1,('BD FRESCOS'!U:U=B55)*('BD FRESCOS'!AK:AK=$D$4),0)))))),""))} -> RUTA 7 | J55: =IF(OR($B$8=0,B55=""),"",IF(AND(E55>20,G55>5),"⚠️ Muy lejos del CD y paraderos",IF(E55>20,"⚠️ Muy lejos del CD",IF(G55>5,"⚠️ Lejos de paraderos","📍 Normal")))) -> ⚠️ Muy lejos del CD
A56: =IF(OR($B$8=0,C56="",C56=0),"",18) -> 18 | B56: =IF($B$8=0,"",IFERROR(IF(INDEX(Distritos!$I$7:$I$66,MATCH(SMALL(Distritos!$J$7:$J$66,18),Distritos!$J$7:$J$66,0))=0,"",INDEX(Distritos!$H$7:$H$66,MATCH(SMALL(Distritos!$J$7:$J$66,18),Distritos!$J$7:$J$66,0))),"")) -> Independencia | C56: =IF($B$8=0,"",IFERROR(IF(INDEX(Distritos!$I$7:$I$66,MATCH(SMALL(Distritos!$J$7:$J$66,18),Distritos!$J$7:$J$66,0))=0,"",INDEX(Distritos!$I$7:$I$66,MATCH(SMALL(Distritos!$J$7:$J$66,18),Distritos!$J$7:$J$66,0))),"")) -> 2 | D56: =IF(OR($B$8=0,C56="",C56=0),"",C56/$B$8) -> 0.013071895 | E56: =IF(OR($B$8=0,B56=""),"",IFERROR(ROUND(IF($D$4="TODOS",IF($B$4="TODOS",(SUMIF('BD SECOS'!Q:Q,B56,'BD SECOS'!U:U)+SUMIF('BD PPA'!U:U,B56,'BD PPA'!AA:AA)+SUMIF('BD FRESCOS'!U:U,B56,'BD FRESCOS'!AA:AA))/(COUNTIF('BD SECOS'!Q:Q,B56)+COUNTIF('BD PPA'!U:U,B56)+COUNTIF('BD FRESCOS'!U:U,B56)),IF($B$4="SECOS",AVERAGEIF('BD SECOS'!Q:Q,B56,'BD SECOS'!U:U),IF($B$4="PPA",AVERAGEIF('BD PPA'!U:U,B56,'BD PPA'!AA:AA),AVERAGEIF('BD FRESCOS'!U:U,B56,'BD FRESCOS'!AA:AA)))),IF($B$4="TODOS",(SUMIFS('BD SECOS'!U:U,'BD SECOS'!Q:Q,B56,'BD SECOS'!AE:AE,$D$4)+SUMIFS('BD PPA'!AA:AA,'BD PPA'!U:U,B56,'BD PPA'!AK:AK,$D$4)+SUMIFS('BD FRESCOS'!AA:AA,'BD FRESCOS'!U:U,B56,'BD FRESCOS'!AK:AK,$D$4))/(COUNTIFS('BD SECOS'!Q:Q,B56,'BD SECOS'!AE:AE,$D$4)+COUNTIFS('BD PPA'!U:U,B56,'BD PPA'!AK:AK,$D$4)+COUNTIFS('BD FRESCOS'!U:U,B56,'BD FRESCOS'!AK:AK,$D$4)),IF($B$4="SECOS",AVERAGEIFS('BD SECOS'!U:U,'BD SECOS'!Q:Q,B56,'BD SECOS'!AE:AE,$D$4),IF($B$4="PPA",AVERAGEIFS('BD PPA'!AA:AA,'BD PPA'!U:U,B56,'BD PPA'!AK:AK,$D$4),AVERAGEIFS('BD FRESCOS'!AA:AA,'BD FRESCOS'!U:U,B56,'BD FRESCOS'!AK:AK,$D$4))))),2),"")) -> 16.73 | F56: =IF(OR($B$8=0,E56=""),"",IF(E56<=5,"🟢 Muy Cerca",IF(E56<=10,"🟡 Cerca",IF(E56<=20,"🟠 Moderada","🔴 Lejos")))) -> 🟠 Moderada | G56: =IF(OR($B$8=0,B56=""),"",IFERROR(ROUND(IF($D$4="TODOS",IF($B$4="TODOS",(SUMIF('BD SECOS'!Q:Q,B56,'BD SECOS'!Y:Y)+SUMIF('BD PPA'!U:U,B56,'BD PPA'!AE:AE)+SUMIF('BD FRESCOS'!U:U,B56,'BD FRESCOS'!AE:AE))/(COUNTIF('BD SECOS'!Q:Q,B56)+COUNTIF('BD PPA'!U:U,B56)+COUNTIF('BD FRESCOS'!U:U,B56)),IF($B$4="SECOS",AVERAGEIF('BD SECOS'!Q:Q,B56,'BD SECOS'!Y:Y),IF($B$4="PPA",AVERAGEIF('BD PPA'!U:U,B56,'BD PPA'!AE:AE),AVERAGEIF('BD FRESCOS'!U:U,B56,'BD FRESCOS'!AE:AE)))),IF($B$4="TODOS",(SUMIFS('BD SECOS'!Y:Y,'BD SECOS'!Q:Q,B56,'BD SECOS'!AE:AE,$D$4)+SUMIFS('BD PPA'!AE:AE,'BD PPA'!U:U,B56,'BD PPA'!AK:AK,$D$4)+SUMIFS('BD FRESCOS'!AE:AE,'BD FRESCOS'!U:U,B56,'BD FRESCOS'!AK:AK,$D$4))/(COUNTIFS('BD SECOS'!Q:Q,B56,'BD SECOS'!AE:AE,$D$4)+COUNTIFS('BD PPA'!U:U,B56,'BD PPA'!AK:AK,$D$4)+COUNTIFS('BD FRESCOS'!U:U,B56,'BD FRESCOS'!AK:AK,$D$4)),IF($B$4="SECOS",AVERAGEIFS('BD SECOS'!Y:Y,'BD SECOS'!Q:Q,B56,'BD SECOS'!AE:AE,$D$4),IF($B$4="PPA",AVERAGEIFS('BD PPA'!AE:AE,'BD PPA'!U:U,B56,'BD PPA'!AK:AK,$D$4),AVERAGEIFS('BD FRESCOS'!AE:AE,'BD FRESCOS'!U:U,B56,'BD FRESCOS'!AK:AK,$D$4))))),2),"")) -> 1.38 | H56: =IF(OR($B$8=0,G56=""),"",IF(G56<=1,"🟢 Muy Cerca",IF(G56<=3,"🟡 Cerca",IF(G56<=5,"🟠 Moderada","🔴 Lejos")))) -> 🟡 Cerca | I56: {=IF(OR($B$8=0,B56=""),"",IFERROR(IF($D$4="TODOS",IF($B$4="TODOS",INDEX('BD SECOS'!X:X,MATCH(B56,'BD SECOS'!Q:Q,0)),IF($B$4="SECOS",INDEX('BD SECOS'!X:X,MATCH(B56,'BD SECOS'!Q:Q,0)),IF($B$4="PPA",INDEX('BD PPA'!AD:AD,MATCH(B56,'BD PPA'!U:U,0)),INDEX('BD FRESCOS'!AD:AD,MATCH(B56,'BD FRESCOS'!U:U,0))))),IF($B$4="TODOS",IFERROR(INDEX('BD SECOS'!X:X,MATCH(1,('BD SECOS'!Q:Q=B56)*('BD SECOS'!AE:AE=$D$4),0)),IFERROR(INDEX('BD PPA'!AD:AD,MATCH(1,('BD PPA'!U:U=B56)*('BD PPA'!AK:AK=$D$4),0)),INDEX('BD FRESCOS'!AD:AD,MATCH(1,('BD FRESCOS'!U:U=B56)*('BD FRESCOS'!AK:AK=$D$4),0)))),IF($B$4="SECOS",INDEX('BD SECOS'!X:X,MATCH(1,('BD SECOS'!Q:Q=B56)*('BD SECOS'!AE:AE=$D$4),0)),IF($B$4="PPA",INDEX('BD PPA'!AD:AD,MATCH(1,('BD PPA'!U:U=B56)*('BD PPA'!AK:AK=$D$4),0)),INDEX('BD FRESCOS'!AD:AD,MATCH(1,('BD FRESCOS'!U:U=B56)*('BD FRESCOS'!AK:AK=$D$4),0)))))),""))} -> RUTA 8 | J56: =IF(OR($B$8=0,B56=""),"",IF(AND(E56>20,G56>5),"⚠️ Muy lejos del CD y paraderos",IF(E56>20,"⚠️ Muy lejos del CD",IF(G56>5,"⚠️ Lejos de paraderos","📍 Normal")))) -> 📍 Normal
A57: =IF(OR($B$8=0,C57="",C57=0),"",19) -> 19 | B57: =IF($B$8=0,"",IFERROR(IF(INDEX(Distritos!$I$7:$I$66,MATCH(SMALL(Distritos!$J$7:$J$66,19),Distritos!$J$7:$J$66,0))=0,"",INDEX(Distritos!$H$7:$H$66,MATCH(SMALL(Distritos!$J$7:$J$66,19),Distritos!$J$7:$J$66,0))),"")) -> La Victoria | C57: =IF($B$8=0,"",IFERROR(IF(INDEX(Distritos!$I$7:$I$66,MATCH(SMALL(Distritos!$J$7:$J$66,19),Distritos!$J$7:$J$66,0))=0,"",INDEX(Distritos!$I$7:$I$66,MATCH(SMALL(Distritos!$J$7:$J$66,19),Distritos!$J$7:$J$66,0))),"")) -> 2 | D57: =IF(OR($B$8=0,C57="",C57=0),"",C57/$B$8) -> 0.013071895 | E57: =IF(OR($B$8=0,B57=""),"",IFERROR(ROUND(IF($D$4="TODOS",IF($B$4="TODOS",(SUMIF('BD SECOS'!Q:Q,B57,'BD SECOS'!U:U)+SUMIF('BD PPA'!U:U,B57,'BD PPA'!AA:AA)+SUMIF('BD FRESCOS'!U:U,B57,'BD FRESCOS'!AA:AA))/(COUNTIF('BD SECOS'!Q:Q,B57)+COUNTIF('BD PPA'!U:U,B57)+COUNTIF('BD FRESCOS'!U:U,B57)),IF($B$4="SECOS",AVERAGEIF('BD SECOS'!Q:Q,B57,'BD SECOS'!U:U),IF($B$4="PPA",AVERAGEIF('BD PPA'!U:U,B57,'BD PPA'!AA:AA),AVERAGEIF('BD FRESCOS'!U:U,B57,'BD FRESCOS'!AA:AA)))),IF($B$4="TODOS",(SUMIFS('BD SECOS'!U:U,'BD SECOS'!Q:Q,B57,'BD SECOS'!AE:AE,$D$4)+SUMIFS('BD PPA'!AA:AA,'BD PPA'!U:U,B57,'BD PPA'!AK:AK,$D$4)+SUMIFS('BD FRESCOS'!AA:AA,'BD FRESCOS'!U:U,B57,'BD FRESCOS'!AK:AK,$D$4))/(COUNTIFS('BD SECOS'!Q:Q,B57,'BD SECOS'!AE:AE,$D$4)+COUNTIFS('BD PPA'!U:U,B57,'BD PPA'!AK:AK,$D$4)+COUNTIFS('BD FRESCOS'!U:U,B57,'BD FRESCOS'!AK:AK,$D$4)),IF($B$4="SECOS",AVERAGEIFS('BD SECOS'!U:U,'BD SECOS'!Q:Q,B57,'BD SECOS'!AE:AE,$D$4),IF($B$4="PPA",AVERAGEIFS('BD PPA'!AA:AA,'BD PPA'!U:U,B57,'BD PPA'!AK:AK,$D$4),AVERAGEIFS('BD FRESCOS'!AA:AA,'BD FRESCOS'!U:U,B57,'BD FRESCOS'!AK:AK,$D$4))))),2),"")) -> 15.52 | F57: =IF(OR($B$8=0,E57=""),"",IF(E57<=5,"🟢 Muy Cerca",IF(E57<=10,"🟡 Cerca",IF(E57<=20,"🟠 Moderada","🔴 Lejos")))) -> 🟠 Moderada | G57: =IF(OR($B$8=0,B57=""),"",IFERROR(ROUND(IF($D$4="TODOS",IF($B$4="TODOS",(SUMIF('BD SECOS'!Q:Q,B57,'BD SECOS'!Y:Y)+SUMIF('BD PPA'!U:U,B57,'BD PPA'!AE:AE)+SUMIF('BD FRESCOS'!U:U,B57,'BD FRESCOS'!AE:AE))/(COUNTIF('BD SECOS'!Q:Q,B57)+COUNTIF('BD PPA'!U:U,B57)+COUNTIF('BD FRESCOS'!U:U,B57)),IF($B$4="SECOS",AVERAGEIF('BD SECOS'!Q:Q,B57,'BD SECOS'!Y:Y),IF($B$4="PPA",AVERAGEIF('BD PPA'!U:U,B57,'BD PPA'!AE:AE),AVERAGEIF('BD FRESCOS'!U:U,B57,'BD FRESCOS'!AE:AE)))),IF($B$4="TODOS",(SUMIFS('BD SECOS'!Y:Y,'BD SECOS'!Q:Q,B57,'BD SECOS'!AE:AE,$D$4)+SUMIFS('BD PPA'!AE:AE,'BD PPA'!U:U,B57,'BD PPA'!AK:AK,$D$4)+SUMIFS('BD FRESCOS'!AE:AE,'BD FRESCOS'!U:U,B57,'BD FRESCOS'!AK:AK,$D$4))/(COUNTIFS('BD SECOS'!Q:Q,B57,'BD SECOS'!AE:AE,$D$4)+COUNTIFS('BD PPA'!U:U,B57,'BD PPA'!AK:AK,$D$4)+COUNTIFS('BD FRESCOS'!U:U,B57,'BD FRESCOS'!AK:AK,$D$4)),IF($B$4="SECOS",AVERAGEIFS('BD SECOS'!Y:Y,'BD SECOS'!Q:Q,B57,'BD SECOS'!AE:AE,$D$4),IF($B$4="PPA",AVERAGEIFS('BD PPA'!AE:AE,'BD PPA'!U:U,B57,'BD PPA'!AK:AK,$D$4),AVERAGEIFS('BD FRESCOS'!AE:AE,'BD FRESCOS'!U:U,B57,'BD FRESCOS'!AK:AK,$D$4))))),2),"")) -> 1.24 | H57: =IF(OR($B$8=0,G57=""),"",IF(G57<=1,"🟢 Muy Cerca",IF(G57<=3,"🟡 Cerca",IF(G57<=5,"🟠 Moderada","🔴 Lejos")))) -> 🟡 Cerca | I57: {=IF(OR($B$8=0,B57=""),"",IFERROR(IF($D$4="TODOS",IF($B$4="TODOS",INDEX('BD SECOS'!X:X,MATCH(B57,'BD SECOS'!Q:Q,0)),IF($B$4="SECOS",INDEX('BD SECOS'!X:X,MATCH(B57,'BD SECOS'!Q:Q,0)),IF($B$4="PPA",INDEX('BD PPA'!AD:AD,MATCH(B57,'BD PPA'!U:U,0)),INDEX('BD FRESCOS'!AD:AD,MATCH(B57,'BD FRESCOS'!U:U,0))))),IF($B$4="TODOS",IFERROR(INDEX('BD SECOS'!X:X,MATCH(1,('BD SECOS'!Q:Q=B57)*('BD SECOS'!AE:AE=$D$4),0)),IFERROR(INDEX('BD PPA'!AD:AD,MATCH(1,('BD PPA'!U:U=B57)*('BD PPA'!AK:AK=$D$4),0)),INDEX('BD FRESCOS'!AD:AD,MATCH(1,('BD FRESCOS'!U:U=B57)*('BD FRESCOS'!AK:AK=$D$4),0)))),IF($B$4="SECOS",INDEX('BD SECOS'!X:X,MATCH(1,('BD SECOS'!Q:Q=B57)*('BD SECOS'!AE:AE=$D$4),0)),IF($B$4="PPA",INDEX('BD PPA'!AD:AD,MATCH(1,('BD PPA'!U:U=B57)*('BD PPA'!AK:AK=$D$4),0)),INDEX('BD FRESCOS'!AD:AD,MATCH(1,('BD FRESCOS'!U:U=B57)*('BD FRESCOS'!AK:AK=$D$4),0)))))),""))} -> RUTA 4A | J57: =IF(OR($B$8=0,B57=""),"",IF(AND(E57>20,G57>5),"⚠️ Muy lejos del CD y paraderos",IF(E57>20,"⚠️ Muy lejos del CD",IF(G57>5,"⚠️ Lejos de paraderos","📍 Normal")))) -> 📍 Normal
A58: =IF(OR($B$8=0,C58="",C58=0),"",20) -> 20 | B58: =IF($B$8=0,"",IFERROR(IF(INDEX(Distritos!$I$7:$I$66,MATCH(SMALL(Distritos!$J$7:$J$66,20),Distritos!$J$7:$J$66,0))=0,"",INDEX(Distritos!$H$7:$H$66,MATCH(SMALL(Distritos!$J$7:$J$66,20),Distritos!$J$7:$J$66,0))),"")) -> Miraflores | C58: =IF($B$8=0,"",IFERROR(IF(INDEX(Distritos!$I$7:$I$66,MATCH(SMALL(Distritos!$J$7:$J$66,20),Distritos!$J$7:$J$66,0))=0,"",INDEX(Distritos!$I$7:$I$66,MATCH(SMALL(Distritos!$J$7:$J$66,20),Distritos!$J$7:$J$66,0))),"")) -> 2 | D58: =IF(OR($B$8=0,C58="",C58=0),"",C58/$B$8) -> 0.013071895 | E58: =IF(OR($B$8=0,B58=""),"",IFERROR(ROUND(IF($D$4="TODOS",IF($B$4="TODOS",(SUMIF('BD SECOS'!Q:Q,B58,'BD SECOS'!U:U)+SUMIF('BD PPA'!U:U,B58,'BD PPA'!AA:AA)+SUMIF('BD FRESCOS'!U:U,B58,'BD FRESCOS'!AA:AA))/(COUNTIF('BD SECOS'!Q:Q,B58)+COUNTIF('BD PPA'!U:U,B58)+COUNTIF('BD FRESCOS'!U:U,B58)),IF($B$4="SECOS",AVERAGEIF('BD SECOS'!Q:Q,B58,'BD SECOS'!U:U),IF($B$4="PPA",AVERAGEIF('BD PPA'!U:U,B58,'BD PPA'!AA:AA),AVERAGEIF('BD FRESCOS'!U:U,B58,'BD FRESCOS'!AA:AA)))),IF($B$4="TODOS",(SUMIFS('BD SECOS'!U:U,'BD SECOS'!Q:Q,B58,'BD SECOS'!AE:AE,$D$4)+SUMIFS('BD PPA'!AA:AA,'BD PPA'!U:U,B58,'BD PPA'!AK:AK,$D$4)+SUMIFS('BD FRESCOS'!AA:AA,'BD FRESCOS'!U:U,B58,'BD FRESCOS'!AK:AK,$D$4))/(COUNTIFS('BD SECOS'!Q:Q,B58,'BD SECOS'!AE:AE,$D$4)+COUNTIFS('BD PPA'!U:U,B58,'BD PPA'!AK:AK,$D$4)+COUNTIFS('BD FRESCOS'!U:U,B58,'BD FRESCOS'!AK:AK,$D$4)),IF($B$4="SECOS",AVERAGEIFS('BD SECOS'!U:U,'BD SECOS'!Q:Q,B58,'BD SECOS'!AE:AE,$D$4),IF($B$4="PPA",AVERAGEIFS('BD PPA'!AA:AA,'BD PPA'!U:U,B58,'BD PPA'!AK:AK,$D$4),AVERAGEIFS('BD FRESCOS'!AA:AA,'BD FRESCOS'!U:U,B58,'BD FRESCOS'!AK:AK,$D$4))))),2),"")) -> 19.25 | F58: =IF(OR($B$8=0,E58=""),"",IF(E58<=5,"🟢 Muy Cerca",IF(E58<=10,"🟡 Cerca",IF(E58<=20,"🟠 Moderada","🔴 Lejos")))) -> 🟠 Moderada | G58: =IF(OR($B$8=0,B58=""),"",IFERROR(ROUND(IF($D$4="TODOS",IF($B$4="TODOS",(SUMIF('BD SECOS'!Q:Q,B58,'BD SECOS'!Y:Y)+SUMIF('BD PPA'!U:U,B58,'BD PPA'!AE:AE)+SUMIF('BD FRESCOS'!U:U,B58,'BD FRESCOS'!AE:AE))/(COUNTIF('BD SECOS'!Q:Q,B58)+COUNTIF('BD PPA'!U:U,B58)+COUNTIF('BD FRESCOS'!U:U,B58)),IF($B$4="SECOS",AVERAGEIF('BD SECOS'!Q:Q,B58,'BD SECOS'!Y:Y),IF($B$4="PPA",AVERAGEIF('BD PPA'!U:U,B58,'BD PPA'!AE:AE),AVERAGEIF('BD FRESCOS'!U:U,B58,'BD FRESCOS'!AE:AE)))),IF($B$4="TODOS",(SUMIFS('BD SECOS'!Y:Y,'BD SECOS'!Q:Q,B58,'BD SECOS'!AE:AE,$D$4)+SUMIFS('BD PPA'!AE:AE,'BD PPA'!U:U,B58,'BD PPA'!AK:AK,$D$4)+SUMIFS('BD FRESCOS'!AE:AE,'BD FRESCOS'!U:U,B58,'BD FRESCOS'!AK:AK,$D$4))/(COUNTIFS('BD SECOS'!Q:Q,B58,'BD SECOS'!AE:AE,$D$4)+COUNTIFS('BD PPA'!U:U,B58,'BD PPA'!AK:AK,$D$4)+COUNTIFS('BD FRESCOS'!U:U,B58,'BD FRESCOS'!AK:AK,$D$4)),IF($B$4="SECOS",AVERAGEIFS('BD SECOS'!Y:Y,'BD SECOS'!Q:Q,B58,'BD SECOS'!AE:AE,$D$4),IF($B$4="PPA",AVERAGEIFS('BD PPA'!AE:AE,'BD PPA'!U:U,B58,'BD PPA'!AK:AK,$D$4),AVERAGEIFS('BD FRESCOS'!AE:AE,'BD FRESCOS'!U:U,B58,'BD FRESCOS'!AK:AK,$D$4))))),2),"")) -> 3.63 | H58: =IF(OR($B$8=0,G58=""),"",IF(G58<=1,"🟢 Muy Cerca",IF(G58<=3,"🟡 Cerca",IF(G58<=5,"🟠 Moderada","🔴 Lejos")))) -> 🟠 Moderada | I58: {=IF(OR($B$8=0,B58=""),"",IFERROR(IF($D$4="TODOS",IF($B$4="TODOS",INDEX('BD SECOS'!X:X,MATCH(B58,'BD SECOS'!Q:Q,0)),IF($B$4="SECOS",INDEX('BD SECOS'!X:X,MATCH(B58,'BD SECOS'!Q:Q,0)),IF($B$4="PPA",INDEX('BD PPA'!AD:AD,MATCH(B58,'BD PPA'!U:U,0)),INDEX('BD FRESCOS'!AD:AD,MATCH(B58,'BD FRESCOS'!U:U,0))))),IF($B$4="TODOS",IFERROR(INDEX('BD SECOS'!X:X,MATCH(1,('BD SECOS'!Q:Q=B58)*('BD SECOS'!AE:AE=$D$4),0)),IFERROR(INDEX('BD PPA'!AD:AD,MATCH(1,('BD PPA'!U:U=B58)*('BD PPA'!AK:AK=$D$4),0)),INDEX('BD FRESCOS'!AD:AD,MATCH(1,('BD FRESCOS'!U:U=B58)*('BD FRESCOS'!AK:AK=$D$4),0)))),IF($B$4="SECOS",INDEX('BD SECOS'!X:X,MATCH(1,('BD SECOS'!Q:Q=B58)*('BD SECOS'!AE:AE=$D$4),0)),IF($B$4="PPA",INDEX('BD PPA'!AD:AD,MATCH(1,('BD PPA'!U:U=B58)*('BD PPA'!AK:AK=$D$4),0)),INDEX('BD FRESCOS'!AD:AD,MATCH(1,('BD FRESCOS'!U:U=B58)*('BD FRESCOS'!AK:AK=$D$4),0)))))),""))} -> RUTA 4A | J58: =IF(OR($B$8=0,B58=""),"",IF(AND(E58>20,G58>5),"⚠️ Muy lejos del CD y paraderos",IF(E58>20,"⚠️ Muy lejos del CD",IF(G58>5,"⚠️ Lejos de paraderos","📍 Normal")))) -> 📍 Normal
A59: =IF(OR($B$8=0,C59="",C59=0),"",21) -> 21 | B59: =IF($B$8=0,"",IFERROR(IF(INDEX(Distritos!$I$7:$I$66,MATCH(SMALL(Distritos!$J$7:$J$66,21),Distritos!$J$7:$J$66,0))=0,"",INDEX(Distritos!$H$7:$H$66,MATCH(SMALL(Distritos!$J$7:$J$66,21),Distritos!$J$7:$J$66,0))),"")) -> Rimac | C59: =IF($B$8=0,"",IFERROR(IF(INDEX(Distritos!$I$7:$I$66,MATCH(SMALL(Distritos!$J$7:$J$66,21),Distritos!$J$7:$J$66,0))=0,"",INDEX(Distritos!$I$7:$I$66,MATCH(SMALL(Distritos!$J$7:$J$66,21),Distritos!$J$7:$J$66,0))),"")) -> 2 | D59: =IF(OR($B$8=0,C59="",C59=0),"",C59/$B$8) -> 0.013071895 | E59: =IF(OR($B$8=0,B59=""),"",IFERROR(ROUND(IF($D$4="TODOS",IF($B$4="TODOS",(SUMIF('BD SECOS'!Q:Q,B59,'BD SECOS'!U:U)+SUMIF('BD PPA'!U:U,B59,'BD PPA'!AA:AA)+SUMIF('BD FRESCOS'!U:U,B59,'BD FRESCOS'!AA:AA))/(COUNTIF('BD SECOS'!Q:Q,B59)+COUNTIF('BD PPA'!U:U,B59)+COUNTIF('BD FRESCOS'!U:U,B59)),IF($B$4="SECOS",AVERAGEIF('BD SECOS'!Q:Q,B59,'BD SECOS'!U:U),IF($B$4="PPA",AVERAGEIF('BD PPA'!U:U,B59,'BD PPA'!AA:AA),AVERAGEIF('BD FRESCOS'!U:U,B59,'BD FRESCOS'!AA:AA)))),IF($B$4="TODOS",(SUMIFS('BD SECOS'!U:U,'BD SECOS'!Q:Q,B59,'BD SECOS'!AE:AE,$D$4)+SUMIFS('BD PPA'!AA:AA,'BD PPA'!U:U,B59,'BD PPA'!AK:AK,$D$4)+SUMIFS('BD FRESCOS'!AA:AA,'BD FRESCOS'!U:U,B59,'BD FRESCOS'!AK:AK,$D$4))/(COUNTIFS('BD SECOS'!Q:Q,B59,'BD SECOS'!AE:AE,$D$4)+COUNTIFS('BD PPA'!U:U,B59,'BD PPA'!AK:AK,$D$4)+COUNTIFS('BD FRESCOS'!U:U,B59,'BD FRESCOS'!AK:AK,$D$4)),IF($B$4="SECOS",AVERAGEIFS('BD SECOS'!U:U,'BD SECOS'!Q:Q,B59,'BD SECOS'!AE:AE,$D$4),IF($B$4="PPA",AVERAGEIFS('BD PPA'!AA:AA,'BD PPA'!U:U,B59,'BD PPA'!AK:AK,$D$4),AVERAGEIFS('BD FRESCOS'!AA:AA,'BD FRESCOS'!U:U,B59,'BD FRESCOS'!AK:AK,$D$4))))),2),"")) -> 14.36 | F59: =IF(OR($B$8=0,E59=""),"",IF(E59<=5,"🟢 Muy Cerca",IF(E59<=10,"🟡 Cerca",IF(E59<=20,"🟠 Moderada","🔴 Lejos")))) -> 🟠 Moderada | G59: =IF(OR($B$8=0,B59=""),"",IFERROR(ROUND(IF($D$4="TODOS",IF($B$4="TODOS",(SUMIF('BD SECOS'!Q:Q,B59,'BD SECOS'!Y:Y)+SUMIF('BD PPA'!U:U,B59,'BD PPA'!AE:AE)+SUMIF('BD FRESCOS'!U:U,B59,'BD FRESCOS'!AE:AE))/(COUNTIF('BD SECOS'!Q:Q,B59)+COUNTIF('BD PPA'!U:U,B59)+COUNTIF('BD FRESCOS'!U:U,B59)),IF($B$4="SECOS",AVERAGEIF('BD SECOS'!Q:Q,B59,'BD SECOS'!Y:Y),IF($B$4="PPA",AVERAGEIF('BD PPA'!U:U,B59,'BD PPA'!AE:AE),AVERAGEIF('BD FRESCOS'!U:U,B59,'BD FRESCOS'!AE:AE)))),IF($B$4="TODOS",(SUMIFS('BD SECOS'!Y:Y,'BD SECOS'!Q:Q,B59,'BD SECOS'!AE:AE,$D$4)+SUMIFS('BD PPA'!AE:AE,'BD PPA'!U:U,B59,'BD PPA'!AK:AK,$D$4)+SUMIFS('BD FRESCOS'!AE:AE,'BD FRESCOS'!U:U,B59,'BD FRESCOS'!AK:AK,$D$4))/(COUNTIFS('BD SECOS'!Q:Q,B59,'BD SECOS'!AE:AE,$D$4)+COUNTIFS('BD PPA'!U:U,B59,'BD PPA'!AK:AK,$D$4)+COUNTIFS('BD FRESCOS'!U:U,B59,'BD FRESCOS'!AK:AK,$D$4)),IF($B$4="SECOS",AVERAGEIFS('BD SECOS'!Y:Y,'BD SECOS'!Q:Q,B59,'BD SECOS'!AE:AE,$D$4),IF($B$4="PPA",AVERAGEIFS('BD PPA'!AE:AE,'BD PPA'!U:U,B59,'BD PPA'!AK:AK,$D$4),AVERAGEIFS('BD FRESCOS'!AE:AE,'BD FRESCOS'!U:U,B59,'BD FRESCOS'!AK:AK,$D$4))))),2),"")) -> 0.98 | H59: =IF(OR($B$8=0,G59=""),"",IF(G59<=1,"🟢 Muy Cerca",IF(G59<=3,"🟡 Cerca",IF(G59<=5,"🟠 Moderada","🔴 Lejos")))) -> 🟢 Muy Cerca | I59: {=IF(OR($B$8=0,B59=""),"",IFERROR(IF($D$4="TODOS",IF($B$4="TODOS",INDEX('BD SECOS'!X:X,MATCH(B59,'BD SECOS'!Q:Q,0)),IF($B$4="SECOS",INDEX('BD SECOS'!X:X,MATCH(B59,'BD SECOS'!Q:Q,0)),IF($B$4="PPA",INDEX('BD PPA'!AD:AD,MATCH(B59,'BD PPA'!U:U,0)),INDEX('BD FRESCOS'!AD:AD,MATCH(B59,'BD FRESCOS'!U:U,0))))),IF($B$4="TODOS",IFERROR(INDEX('BD SECOS'!X:X,MATCH(1,('BD SECOS'!Q:Q=B59)*('BD SECOS'!AE:AE=$D$4),0)),IFERROR(INDEX('BD PPA'!AD:AD,MATCH(1,('BD PPA'!U:U=B59)*('BD PPA'!AK:AK=$D$4),0)),INDEX('BD FRESCOS'!AD:AD,MATCH(1,('BD FRESCOS'!U:U=B59)*('BD FRESCOS'!AK:AK=$D$4),0)))),IF($B$4="SECOS",INDEX('BD SECOS'!X:X,MATCH(1,('BD SECOS'!Q:Q=B59)*('BD SECOS'!AE:AE=$D$4),0)),IF($B$4="PPA",INDEX('BD PPA'!AD:AD,MATCH(1,('BD PPA'!U:U=B59)*('BD PPA'!AK:AK=$D$4),0)),INDEX('BD FRESCOS'!AD:AD,MATCH(1,('BD FRESCOS'!U:U=B59)*('BD FRESCOS'!AK:AK=$D$4),0)))))),""))} -> RUTA 8 | J59: =IF(OR($B$8=0,B59=""),"",IF(AND(E59>20,G59>5),"⚠️ Muy lejos del CD y paraderos",IF(E59>20,"⚠️ Muy lejos del CD",IF(G59>5,"⚠️ Lejos de paraderos","📍 Normal")))) -> 📍 Normal
A60: =IF(OR($B$8=0,C60="",C60=0),"",22) -> 22 | B60: =IF($B$8=0,"",IFERROR(IF(INDEX(Distritos!$I$7:$I$66,MATCH(SMALL(Distritos!$J$7:$J$66,22),Distritos!$J$7:$J$66,0))=0,"",INDEX(Distritos!$H$7:$H$66,MATCH(SMALL(Distritos!$J$7:$J$66,22),Distritos!$J$7:$J$66,0))),"")) -> San Miguel | C60: =IF($B$8=0,"",IFERROR(IF(INDEX(Distritos!$I$7:$I$66,MATCH(SMALL(Distritos!$J$7:$J$66,22),Distritos!$J$7:$J$66,0))=0,"",INDEX(Distritos!$I$7:$I$66,MATCH(SMALL(Distritos!$J$7:$J$66,22),Distritos!$J$7:$J$66,0))),"")) -> 2 | D60: =IF(OR($B$8=0,C60="",C60=0),"",C60/$B$8) -> 0.013071895 | E60: =IF(OR($B$8=0,B60=""),"",IFERROR(ROUND(IF($D$4="TODOS",IF($B$4="TODOS",(SUMIF('BD SECOS'!Q:Q,B60,'BD SECOS'!U:U)+SUMIF('BD PPA'!U:U,B60,'BD PPA'!AA:AA)+SUMIF('BD FRESCOS'!U:U,B60,'BD FRESCOS'!AA:AA))/(COUNTIF('BD SECOS'!Q:Q,B60)+COUNTIF('BD PPA'!U:U,B60)+COUNTIF('BD FRESCOS'!U:U,B60)),IF($B$4="SECOS",AVERAGEIF('BD SECOS'!Q:Q,B60,'BD SECOS'!U:U),IF($B$4="PPA",AVERAGEIF('BD PPA'!U:U,B60,'BD PPA'!AA:AA),AVERAGEIF('BD FRESCOS'!U:U,B60,'BD FRESCOS'!AA:AA)))),IF($B$4="TODOS",(SUMIFS('BD SECOS'!U:U,'BD SECOS'!Q:Q,B60,'BD SECOS'!AE:AE,$D$4)+SUMIFS('BD PPA'!AA:AA,'BD PPA'!U:U,B60,'BD PPA'!AK:AK,$D$4)+SUMIFS('BD FRESCOS'!AA:AA,'BD FRESCOS'!U:U,B60,'BD FRESCOS'!AK:AK,$D$4))/(COUNTIFS('BD SECOS'!Q:Q,B60,'BD SECOS'!AE:AE,$D$4)+COUNTIFS('BD PPA'!U:U,B60,'BD PPA'!AK:AK,$D$4)+COUNTIFS('BD FRESCOS'!U:U,B60,'BD FRESCOS'!AK:AK,$D$4)),IF($B$4="SECOS",AVERAGEIFS('BD SECOS'!U:U,'BD SECOS'!Q:Q,B60,'BD SECOS'!AE:AE,$D$4),IF($B$4="PPA",AVERAGEIFS('BD PPA'!AA:AA,'BD PPA'!U:U,B60,'BD PPA'!AK:AK,$D$4),AVERAGEIFS('BD FRESCOS'!AA:AA,'BD FRESCOS'!U:U,B60,'BD FRESCOS'!AK:AK,$D$4))))),2),"")) -> 23.16 | F60: =IF(OR($B$8=0,E60=""),"",IF(E60<=5,"🟢 Muy Cerca",IF(E60<=10,"🟡 Cerca",IF(E60<=20,"🟠 Moderada","🔴 Lejos")))) -> 🔴 Lejos | G60: =IF(OR($B$8=0,B60=""),"",IFERROR(ROUND(IF($D$4="TODOS",IF($B$4="TODOS",(SUMIF('BD SECOS'!Q:Q,B60,'BD SECOS'!Y:Y)+SUMIF('BD PPA'!U:U,B60,'BD PPA'!AE:AE)+SUMIF('BD FRESCOS'!U:U,B60,'BD FRESCOS'!AE:AE))/(COUNTIF('BD SECOS'!Q:Q,B60)+COUNTIF('BD PPA'!U:U,B60)+COUNTIF('BD FRESCOS'!U:U,B60)),IF($B$4="SECOS",AVERAGEIF('BD SECOS'!Q:Q,B60,'BD SECOS'!Y:Y),IF($B$4="PPA",AVERAGEIF('BD PPA'!U:U,B60,'BD PPA'!AE:AE),AVERAGEIF('BD FRESCOS'!U:U,B60,'BD FRESCOS'!AE:AE)))),IF($B$4="TODOS",(SUMIFS('BD SECOS'!Y:Y,'BD SECOS'!Q:Q,B60,'BD SECOS'!AE:AE,$D$4)+SUMIFS('BD PPA'!AE:AE,'BD PPA'!U:U,B60,'BD PPA'!AK:AK,$D$4)+SUMIFS('BD FRESCOS'!AE:AE,'BD FRESCOS'!U:U,B60,'BD FRESCOS'!AK:AK,$D$4))/(COUNTIFS('BD SECOS'!Q:Q,B60,'BD SECOS'!AE:AE,$D$4)+COUNTIFS('BD PPA'!U:U,B60,'BD PPA'!AK:AK,$D$4)+COUNTIFS('BD FRESCOS'!U:U,B60,'BD FRESCOS'!AK:AK,$D$4)),IF($B$4="SECOS",AVERAGEIFS('BD SECOS'!Y:Y,'BD SECOS'!Q:Q,B60,'BD SECOS'!AE:AE,$D$4),IF($B$4="PPA",AVERAGEIFS('BD PPA'!AE:AE,'BD PPA'!U:U,B60,'BD PPA'!AK:AK,$D$4),AVERAGEIFS('BD FRESCOS'!AE:AE,'BD FRESCOS'!U:U,B60,'BD FRESCOS'!AK:AK,$D$4))))),2),"")) -> 1.77 | H60: =IF(OR($B$8=0,G60=""),"",IF(G60<=1,"🟢 Muy Cerca",IF(G60<=3,"🟡 Cerca",IF(G60<=5,"🟠 Moderada","🔴 Lejos")))) -> 🟡 Cerca | I60: {=IF(OR($B$8=0,B60=""),"",IFERROR(IF($D$4="TODOS",IF($B$4="TODOS",INDEX('BD SECOS'!X:X,MATCH(B60,'BD SECOS'!Q:Q,0)),IF($B$4="SECOS",INDEX('BD SECOS'!X:X,MATCH(B60,'BD SECOS'!Q:Q,0)),IF($B$4="PPA",INDEX('BD PPA'!AD:AD,MATCH(B60,'BD PPA'!U:U,0)),INDEX('BD FRESCOS'!AD:AD,MATCH(B60,'BD FRESCOS'!U:U,0))))),IF($B$4="TODOS",IFERROR(INDEX('BD SECOS'!X:X,MATCH(1,('BD SECOS'!Q:Q=B60)*('BD SECOS'!AE:AE=$D$4),0)),IFERROR(INDEX('BD PPA'!AD:AD,MATCH(1,('BD PPA'!U:U=B60)*('BD PPA'!AK:AK=$D$4),0)),INDEX('BD FRESCOS'!AD:AD,MATCH(1,('BD FRESCOS'!U:U=B60)*('BD FRESCOS'!AK:AK=$D$4),0)))),IF($B$4="SECOS",INDEX('BD SECOS'!X:X,MATCH(1,('BD SECOS'!Q:Q=B60)*('BD SECOS'!AE:AE=$D$4),0)),IF($B$4="PPA",INDEX('BD PPA'!AD:AD,MATCH(1,('BD PPA'!U:U=B60)*('BD PPA'!AK:AK=$D$4),0)),INDEX('BD FRESCOS'!AD:AD,MATCH(1,('BD FRESCOS'!U:U=B60)*('BD FRESCOS'!AK:AK=$D$4),0)))))),""))} -> RUTA 9 | J60: =IF(OR($B$8=0,B60=""),"",IF(AND(E60>20,G60>5),"⚠️ Muy lejos del CD y paraderos",IF(E60>20,"⚠️ Muy lejos del CD",IF(G60>5,"⚠️ Lejos de paraderos","📍 Normal")))) -> ⚠️ Muy lejos del CD
A61: =IF(OR($B$8=0,C61="",C61=0),"",23) -> 23 | B61: =IF($B$8=0,"",IFERROR(IF(INDEX(Distritos!$I$7:$I$66,MATCH(SMALL(Distritos!$J$7:$J$66,23),Distritos!$J$7:$J$66,0))=0,"",INDEX(Distritos!$H$7:$H$66,MATCH(SMALL(Distritos!$J$7:$J$66,23),Distritos!$J$7:$J$66,0))),"")) -> Surquillo | C61: =IF($B$8=0,"",IFERROR(IF(INDEX(Distritos!$I$7:$I$66,MATCH(SMALL(Distritos!$J$7:$J$66,23),Distritos!$J$7:$J$66,0))=0,"",INDEX(Distritos!$I$7:$I$66,MATCH(SMALL(Distritos!$J$7:$J$66,23),Distritos!$J$7:$J$66,0))),"")) -> 2 | D61: =IF(OR($B$8=0,C61="",C61=0),"",C61/$B$8) -> 0.013071895 | E61: =IF(OR($B$8=0,B61=""),"",IFERROR(ROUND(IF($D$4="TODOS",IF($B$4="TODOS",(SUMIF('BD SECOS'!Q:Q,B61,'BD SECOS'!U:U)+SUMIF('BD PPA'!U:U,B61,'BD PPA'!AA:AA)+SUMIF('BD FRESCOS'!U:U,B61,'BD FRESCOS'!AA:AA))/(COUNTIF('BD SECOS'!Q:Q,B61)+COUNTIF('BD PPA'!U:U,B61)+COUNTIF('BD FRESCOS'!U:U,B61)),IF($B$4="SECOS",AVERAGEIF('BD SECOS'!Q:Q,B61,'BD SECOS'!U:U),IF($B$4="PPA",AVERAGEIF('BD PPA'!U:U,B61,'BD PPA'!AA:AA),AVERAGEIF('BD FRESCOS'!U:U,B61,'BD FRESCOS'!AA:AA)))),IF($B$4="TODOS",(SUMIFS('BD SECOS'!U:U,'BD SECOS'!Q:Q,B61,'BD SECOS'!AE:AE,$D$4)+SUMIFS('BD PPA'!AA:AA,'BD PPA'!U:U,B61,'BD PPA'!AK:AK,$D$4)+SUMIFS('BD FRESCOS'!AA:AA,'BD FRESCOS'!U:U,B61,'BD FRESCOS'!AK:AK,$D$4))/(COUNTIFS('BD SECOS'!Q:Q,B61,'BD SECOS'!AE:AE,$D$4)+COUNTIFS('BD PPA'!U:U,B61,'BD PPA'!AK:AK,$D$4)+COUNTIFS('BD FRESCOS'!U:U,B61,'BD FRESCOS'!AK:AK,$D$4)),IF($B$4="SECOS",AVERAGEIFS('BD SECOS'!U:U,'BD SECOS'!Q:Q,B61,'BD SECOS'!AE:AE,$D$4),IF($B$4="PPA",AVERAGEIFS('BD PPA'!AA:AA,'BD PPA'!U:U,B61,'BD PPA'!AK:AK,$D$4),AVERAGEIFS('BD FRESCOS'!AA:AA,'BD FRESCOS'!U:U,B61,'BD FRESCOS'!AK:AK,$D$4))))),2),"")) -> 17.72 | F61: =IF(OR($B$8=0,E61=""),"",IF(E61<=5,"🟢 Muy Cerca",IF(E61<=10,"🟡 Cerca",IF(E61<=20,"🟠 Moderada","🔴 Lejos")))) -> 🟠 Moderada | G61: =IF(OR($B$8=0,B61=""),"",IFERROR(ROUND(IF($D$4="TODOS",IF($B$4="TODOS",(SUMIF('BD SECOS'!Q:Q,B61,'BD SECOS'!Y:Y)+SUMIF('BD PPA'!U:U,B61,'BD PPA'!AE:AE)+SUMIF('BD FRESCOS'!U:U,B61,'BD FRESCOS'!AE:AE))/(COUNTIF('BD SECOS'!Q:Q,B61)+COUNTIF('BD PPA'!U:U,B61)+COUNTIF('BD FRESCOS'!U:U,B61)),IF($B$4="SECOS",AVERAGEIF('BD SECOS'!Q:Q,B61,'BD SECOS'!Y:Y),IF($B$4="PPA",AVERAGEIF('BD PPA'!U:U,B61,'BD PPA'!AE:AE),AVERAGEIF('BD FRESCOS'!U:U,B61,'BD FRESCOS'!AE:AE)))),IF($B$4="TODOS",(SUMIFS('BD SECOS'!Y:Y,'BD SECOS'!Q:Q,B61,'BD SECOS'!AE:AE,$D$4)+SUMIFS('BD PPA'!AE:AE,'BD PPA'!U:U,B61,'BD PPA'!AK:AK,$D$4)+SUMIFS('BD FRESCOS'!AE:AE,'BD FRESCOS'!U:U,B61,'BD FRESCOS'!AK:AK,$D$4))/(COUNTIFS('BD SECOS'!Q:Q,B61,'BD SECOS'!AE:AE,$D$4)+COUNTIFS('BD PPA'!U:U,B61,'BD PPA'!AK:AK,$D$4)+COUNTIFS('BD FRESCOS'!U:U,B61,'BD FRESCOS'!AK:AK,$D$4)),IF($B$4="SECOS",AVERAGEIFS('BD SECOS'!Y:Y,'BD SECOS'!Q:Q,B61,'BD SECOS'!AE:AE,$D$4),IF($B$4="PPA",AVERAGEIFS('BD PPA'!AE:AE,'BD PPA'!U:U,B61,'BD PPA'!AK:AK,$D$4),AVERAGEIFS('BD FRESCOS'!AE:AE,'BD FRESCOS'!U:U,B61,'BD FRESCOS'!AK:AK,$D$4))))),2),"")) -> 2.63 | H61: =IF(OR($B$8=0,G61=""),"",IF(G61<=1,"🟢 Muy Cerca",IF(G61<=3,"🟡 Cerca",IF(G61<=5,"🟠 Moderada","🔴 Lejos")))) -> 🟡 Cerca | I61: {=IF(OR($B$8=0,B61=""),"",IFERROR(IF($D$4="TODOS",IF($B$4="TODOS",INDEX('BD SECOS'!X:X,MATCH(B61,'BD SECOS'!Q:Q,0)),IF($B$4="SECOS",INDEX('BD SECOS'!X:X,MATCH(B61,'BD SECOS'!Q:Q,0)),IF($B$4="PPA",INDEX('BD PPA'!AD:AD,MATCH(B61,'BD PPA'!U:U,0)),INDEX('BD FRESCOS'!AD:AD,MATCH(B61,'BD FRESCOS'!U:U,0))))),IF($B$4="TODOS",IFERROR(INDEX('BD SECOS'!X:X,MATCH(1,('BD SECOS'!Q:Q=B61)*('BD SECOS'!AE:AE=$D$4),0)),IFERROR(INDEX('BD PPA'!AD:AD,MATCH(1,('BD PPA'!U:U=B61)*('BD PPA'!AK:AK=$D$4),0)),INDEX('BD FRESCOS'!AD:AD,MATCH(1,('BD FRESCOS'!U:U=B61)*('BD FRESCOS'!AK:AK=$D$4),0)))),IF($B$4="SECOS",INDEX('BD SECOS'!X:X,MATCH(1,('BD SECOS'!Q:Q=B61)*('BD SECOS'!AE:AE=$D$4),0)),IF($B$4="PPA",INDEX('BD PPA'!AD:AD,MATCH(1,('BD PPA'!U:U=B61)*('BD PPA'!AK:AK=$D$4),0)),INDEX('BD FRESCOS'!AD:AD,MATCH(1,('BD FRESCOS'!U:U=B61)*('BD FRESCOS'!AK:AK=$D$4),0)))))),""))} -> RUTA 7 | J61: =IF(OR($B$8=0,B61=""),"",IF(AND(E61>20,G61>5),"⚠️ Muy lejos del CD y paraderos",IF(E61>20,"⚠️ Muy lejos del CD",IF(G61>5,"⚠️ Lejos de paraderos","📍 Normal")))) -> 📍 Normal
A62: =IF(OR($B$8=0,C62="",C62=0),"",24) -> 24 | B62: =IF($B$8=0,"",IFERROR(IF(INDEX(Distritos!$I$7:$I$66,MATCH(SMALL(Distritos!$J$7:$J$66,24),Distritos!$J$7:$J$66,0))=0,"",INDEX(Distritos!$H$7:$H$66,MATCH(SMALL(Distritos!$J$7:$J$66,24),Distritos!$J$7:$J$66,0))),"")) -> Villa El Salvador | C62: =IF($B$8=0,"",IFERROR(IF(INDEX(Distritos!$I$7:$I$66,MATCH(SMALL(Distritos!$J$7:$J$66,24),Distritos!$J$7:$J$66,0))=0,"",INDEX(Distritos!$I$7:$I$66,MATCH(SMALL(Distritos!$J$7:$J$66,24),Distritos!$J$7:$J$66,0))),"")) -> 2 | D62: =IF(OR($B$8=0,C62="",C62=0),"",C62/$B$8) -> 0.013071895 | E62: =IF(OR($B$8=0,B62=""),"",IFERROR(ROUND(IF($D$4="TODOS",IF($B$4="TODOS",(SUMIF('BD SECOS'!Q:Q,B62,'BD SECOS'!U:U)+SUMIF('BD PPA'!U:U,B62,'BD PPA'!AA:AA)+SUMIF('BD FRESCOS'!U:U,B62,'BD FRESCOS'!AA:AA))/(COUNTIF('BD SECOS'!Q:Q,B62)+COUNTIF('BD PPA'!U:U,B62)+COUNTIF('BD FRESCOS'!U:U,B62)),IF($B$4="SECOS",AVERAGEIF('BD SECOS'!Q:Q,B62,'BD SECOS'!U:U),IF($B$4="PPA",AVERAGEIF('BD PPA'!U:U,B62,'BD PPA'!AA:AA),AVERAGEIF('BD FRESCOS'!U:U,B62,'BD FRESCOS'!AA:AA)))),IF($B$4="TODOS",(SUMIFS('BD SECOS'!U:U,'BD SECOS'!Q:Q,B62,'BD SECOS'!AE:AE,$D$4)+SUMIFS('BD PPA'!AA:AA,'BD PPA'!U:U,B62,'BD PPA'!AK:AK,$D$4)+SUMIFS('BD FRESCOS'!AA:AA,'BD FRESCOS'!U:U,B62,'BD FRESCOS'!AK:AK,$D$4))/(COUNTIFS('BD SECOS'!Q:Q,B62,'BD SECOS'!AE:AE,$D$4)+COUNTIFS('BD PPA'!U:U,B62,'BD PPA'!AK:AK,$D$4)+COUNTIFS('BD FRESCOS'!U:U,B62,'BD FRESCOS'!AK:AK,$D$4)),IF($B$4="SECOS",AVERAGEIFS('BD SECOS'!U:U,'BD SECOS'!Q:Q,B62,'BD SECOS'!AE:AE,$D$4),IF($B$4="PPA",AVERAGEIFS('BD PPA'!AA:AA,'BD PPA'!U:U,B62,'BD PPA'!AK:AK,$D$4),AVERAGEIFS('BD FRESCOS'!AA:AA,'BD FRESCOS'!U:U,B62,'BD FRESCOS'!AK:AK,$D$4))))),2),"")) -> 23.77 | F62: =IF(OR($B$8=0,E62=""),"",IF(E62<=5,"🟢 Muy Cerca",IF(E62<=10,"🟡 Cerca",IF(E62<=20,"🟠 Moderada","🔴 Lejos")))) -> 🔴 Lejos | G62: =IF(OR($B$8=0,B62=""),"",IFERROR(ROUND(IF($D$4="TODOS",IF($B$4="TODOS",(SUMIF('BD SECOS'!Q:Q,B62,'BD SECOS'!Y:Y)+SUMIF('BD PPA'!U:U,B62,'BD PPA'!AE:AE)+SUMIF('BD FRESCOS'!U:U,B62,'BD FRESCOS'!AE:AE))/(COUNTIF('BD SECOS'!Q:Q,B62)+COUNTIF('BD PPA'!U:U,B62)+COUNTIF('BD FRESCOS'!U:U,B62)),IF($B$4="SECOS",AVERAGEIF('BD SECOS'!Q:Q,B62,'BD SECOS'!Y:Y),IF($B$4="PPA",AVERAGEIF('BD PPA'!U:U,B62,'BD PPA'!AE:AE),AVERAGEIF('BD FRESCOS'!U:U,B62,'BD FRESCOS'!AE:AE)))),IF($B$4="TODOS",(SUMIFS('BD SECOS'!Y:Y,'BD SECOS'!Q:Q,B62,'BD SECOS'!AE:AE,$D$4)+SUMIFS('BD PPA'!AE:AE,'BD PPA'!U:U,B62,'BD PPA'!AK:AK,$D$4)+SUMIFS('BD FRESCOS'!AE:AE,'BD FRESCOS'!U:U,B62,'BD FRESCOS'!AK:AK,$D$4))/(COUNTIFS('BD SECOS'!Q:Q,B62,'BD SECOS'!AE:AE,$D$4)+COUNTIFS('BD PPA'!U:U,B62,'BD PPA'!AK:AK,$D$4)+COUNTIFS('BD FRESCOS'!U:U,B62,'BD FRESCOS'!AK:AK,$D$4)),IF($B$4="SECOS",AVERAGEIFS('BD SECOS'!Y:Y,'BD SECOS'!Q:Q,B62,'BD SECOS'!AE:AE,$D$4),IF($B$4="PPA",AVERAGEIFS('BD PPA'!AE:AE,'BD PPA'!U:U,B62,'BD PPA'!AK:AK,$D$4),AVERAGEIFS('BD FRESCOS'!AE:AE,'BD FRESCOS'!U:U,B62,'BD FRESCOS'!AK:AK,$D$4))))),2),"")) -> 1.86 | H62: =IF(OR($B$8=0,G62=""),"",IF(G62<=1,"🟢 Muy Cerca",IF(G62<=3,"🟡 Cerca",IF(G62<=5,"🟠 Moderada","🔴 Lejos")))) -> 🟡 Cerca | I62: {=IF(OR($B$8=0,B62=""),"",IFERROR(IF($D$4="TODOS",IF($B$4="TODOS",INDEX('BD SECOS'!X:X,MATCH(B62,'BD SECOS'!Q:Q,0)),IF($B$4="SECOS",INDEX('BD SECOS'!X:X,MATCH(B62,'BD SECOS'!Q:Q,0)),IF($B$4="PPA",INDEX('BD PPA'!AD:AD,MATCH(B62,'BD PPA'!U:U,0)),INDEX('BD FRESCOS'!AD:AD,MATCH(B62,'BD FRESCOS'!U:U,0))))),IF($B$4="TODOS",IFERROR(INDEX('BD SECOS'!X:X,MATCH(1,('BD SECOS'!Q:Q=B62)*('BD SECOS'!AE:AE=$D$4),0)),IFERROR(INDEX('BD PPA'!AD:AD,MATCH(1,('BD PPA'!U:U=B62)*('BD PPA'!AK:AK=$D$4),0)),INDEX('BD FRESCOS'!AD:AD,MATCH(1,('BD FRESCOS'!U:U=B62)*('BD FRESCOS'!AK:AK=$D$4),0)))),IF($B$4="SECOS",INDEX('BD SECOS'!X:X,MATCH(1,('BD SECOS'!Q:Q=B62)*('BD SECOS'!AE:AE=$D$4),0)),IF($B$4="PPA",INDEX('BD PPA'!AD:AD,MATCH(1,('BD PPA'!U:U=B62)*('BD PPA'!AK:AK=$D$4),0)),INDEX('BD FRESCOS'!AD:AD,MATCH(1,('BD FRESCOS'!U:U=B62)*('BD FRESCOS'!AK:AK=$D$4),0)))))),""))} -> RUTA 7 | J62: =IF(OR($B$8=0,B62=""),"",IF(AND(E62>20,G62>5),"⚠️ Muy lejos del CD y paraderos",IF(E62>20,"⚠️ Muy lejos del CD",IF(G62>5,"⚠️ Lejos de paraderos","📍 Normal")))) -> ⚠️ Muy lejos del CD
A63: =IF(OR($B$8=0,C63="",C63=0),"",25) -> 25 | B63: =IF($B$8=0,"",IFERROR(IF(INDEX(Distritos!$I$7:$I$66,MATCH(SMALL(Distritos!$J$7:$J$66,25),Distritos!$J$7:$J$66,0))=0,"",INDEX(Distritos!$H$7:$H$66,MATCH(SMALL(Distritos!$J$7:$J$66,25),Distritos!$J$7:$J$66,0))),"")) -> Comas | C63: =IF($B$8=0,"",IFERROR(IF(INDEX(Distritos!$I$7:$I$66,MATCH(SMALL(Distritos!$J$7:$J$66,25),Distritos!$J$7:$J$66,0))=0,"",INDEX(Distritos!$I$7:$I$66,MATCH(SMALL(Distritos!$J$7:$J$66,25),Distritos!$J$7:$J$66,0))),"")) -> 1 | D63: =IF(OR($B$8=0,C63="",C63=0),"",C63/$B$8) -> 0.0065359477 | E63: =IF(OR($B$8=0,B63=""),"",IFERROR(ROUND(IF($D$4="TODOS",IF($B$4="TODOS",(SUMIF('BD SECOS'!Q:Q,B63,'BD SECOS'!U:U)+SUMIF('BD PPA'!U:U,B63,'BD PPA'!AA:AA)+SUMIF('BD FRESCOS'!U:U,B63,'BD FRESCOS'!AA:AA))/(COUNTIF('BD SECOS'!Q:Q,B63)+COUNTIF('BD PPA'!U:U,B63)+COUNTIF('BD FRESCOS'!U:U,B63)),IF($B$4="SECOS",AVERAGEIF('BD SECOS'!Q:Q,B63,'BD SECOS'!U:U),IF($B$4="PPA",AVERAGEIF('BD PPA'!U:U,B63,'BD PPA'!AA:AA),AVERAGEIF('BD FRESCOS'!U:U,B63,'BD FRESCOS'!AA:AA)))),IF($B$4="TODOS",(SUMIFS('BD SECOS'!U:U,'BD SECOS'!Q:Q,B63,'BD SECOS'!AE:AE,$D$4)+SUMIFS('BD PPA'!AA:AA,'BD PPA'!U:U,B63,'BD PPA'!AK:AK,$D$4)+SUMIFS('BD FRESCOS'!AA:AA,'BD FRESCOS'!U:U,B63,'BD FRESCOS'!AK:AK,$D$4))/(COUNTIFS('BD SECOS'!Q:Q,B63,'BD SECOS'!AE:AE,$D$4)+COUNTIFS('BD PPA'!U:U,B63,'BD PPA'!AK:AK,$D$4)+COUNTIFS('BD FRESCOS'!U:U,B63,'BD FRESCOS'!AK:AK,$D$4)),IF($B$4="SECOS",AVERAGEIFS('BD SECOS'!U:U,'BD SECOS'!Q:Q,B63,'BD SECOS'!AE:AE,$D$4),IF($B$4="PPA",AVERAGEIFS('BD PPA'!AA:AA,'BD PPA'!U:U,B63,'BD PPA'!AK:AK,$D$4),AVERAGEIFS('BD FRESCOS'!AA:AA,'BD FRESCOS'!U:U,B63,'BD FRESCOS'!AK:AK,$D$4))))),2),"")) -> 18.13 | F63: =IF(OR($B$8=0,E63=""),"",IF(E63<=5,"🟢 Muy Cerca",IF(E63<=10,"🟡 Cerca",IF(E63<=20,"🟠 Moderada","🔴 Lejos")))) -> 🟠 Moderada | G63: =IF(OR($B$8=0,B63=""),"",IFERROR(ROUND(IF($D$4="TODOS",IF($B$4="TODOS",(SUMIF('BD SECOS'!Q:Q,B63,'BD SECOS'!Y:Y)+SUMIF('BD PPA'!U:U,B63,'BD PPA'!AE:AE)+SUMIF('BD FRESCOS'!U:U,B63,'BD FRESCOS'!AE:AE))/(COUNTIF('BD SECOS'!Q:Q,B63)+COUNTIF('BD PPA'!U:U,B63)+COUNTIF('BD FRESCOS'!U:U,B63)),IF($B$4="SECOS",AVERAGEIF('BD SECOS'!Q:Q,B63,'BD SECOS'!Y:Y),IF($B$4="PPA",AVERAGEIF('BD PPA'!U:U,B63,'BD PPA'!AE:AE),AVERAGEIF('BD FRESCOS'!U:U,B63,'BD FRESCOS'!AE:AE)))),IF($B$4="TODOS",(SUMIFS('BD SECOS'!Y:Y,'BD SECOS'!Q:Q,B63,'BD SECOS'!AE:AE,$D$4)+SUMIFS('BD PPA'!AE:AE,'BD PPA'!U:U,B63,'BD PPA'!AK:AK,$D$4)+SUMIFS('BD FRESCOS'!AE:AE,'BD FRESCOS'!U:U,B63,'BD FRESCOS'!AK:AK,$D$4))/(COUNTIFS('BD SECOS'!Q:Q,B63,'BD SECOS'!AE:AE,$D$4)+COUNTIFS('BD PPA'!U:U,B63,'BD PPA'!AK:AK,$D$4)+COUNTIFS('BD FRESCOS'!U:U,B63,'BD FRESCOS'!AK:AK,$D$4)),IF($B$4="SECOS",AVERAGEIFS('BD SECOS'!Y:Y,'BD SECOS'!Q:Q,B63,'BD SECOS'!AE:AE,$D$4),IF($B$4="PPA",AVERAGEIFS('BD PPA'!AE:AE,'BD PPA'!U:U,B63,'BD PPA'!AK:AK,$D$4),AVERAGEIFS('BD FRESCOS'!AE:AE,'BD FRESCOS'!U:U,B63,'BD FRESCOS'!AK:AK,$D$4))))),2),"")) -> 4.71 | H63: =IF(OR($B$8=0,G63=""),"",IF(G63<=1,"🟢 Muy Cerca",IF(G63<=3,"🟡 Cerca",IF(G63<=5,"🟠 Moderada","🔴 Lejos")))) -> 🟠 Moderada | I63: {=IF(OR($B$8=0,B63=""),"",IFERROR(IF($D$4="TODOS",IF($B$4="TODOS",INDEX('BD SECOS'!X:X,MATCH(B63,'BD SECOS'!Q:Q,0)),IF($B$4="SECOS",INDEX('BD SECOS'!X:X,MATCH(B63,'BD SECOS'!Q:Q,0)),IF($B$4="PPA",INDEX('BD PPA'!AD:AD,MATCH(B63,'BD PPA'!U:U,0)),INDEX('BD FRESCOS'!AD:AD,MATCH(B63,'BD FRESCOS'!U:U,0))))),IF($B$4="TODOS",IFERROR(INDEX('BD SECOS'!X:X,MATCH(1,('BD SECOS'!Q:Q=B63)*('BD SECOS'!AE:AE=$D$4),0)),IFERROR(INDEX('BD PPA'!AD:AD,MATCH(1,('BD PPA'!U:U=B63)*('BD PPA'!AK:AK=$D$4),0)),INDEX('BD FRESCOS'!AD:AD,MATCH(1,('BD FRESCOS'!U:U=B63)*('BD FRESCOS'!AK:AK=$D$4),0)))),IF($B$4="SECOS",INDEX('BD SECOS'!X:X,MATCH(1,('BD SECOS'!Q:Q=B63)*('BD SECOS'!AE:AE=$D$4),0)),IF($B$4="PPA",INDEX('BD PPA'!AD:AD,MATCH(1,('BD PPA'!U:U=B63)*('BD PPA'!AK:AK=$D$4),0)),INDEX('BD FRESCOS'!AD:AD,MATCH(1,('BD FRESCOS'!U:U=B63)*('BD FRESCOS'!AK:AK=$D$4),0)))))),""))} -> RUTA 4A | J63: =IF(OR($B$8=0,B63=""),"",IF(AND(E63>20,G63>5),"⚠️ Muy lejos del CD y paraderos",IF(E63>20,"⚠️ Muy lejos del CD",IF(G63>5,"⚠️ Lejos de paraderos","📍 Normal")))) -> 📍 Normal
A64: =IF(OR($B$8=0,C64="",C64=0),"",26) -> 26 | B64: =IF($B$8=0,"",IFERROR(IF(INDEX(Distritos!$I$7:$I$66,MATCH(SMALL(Distritos!$J$7:$J$66,26),Distritos!$J$7:$J$66,0))=0,"",INDEX(Distritos!$H$7:$H$66,MATCH(SMALL(Distritos!$J$7:$J$66,26),Distritos!$J$7:$J$66,0))),"")) -> Jesus Maria | C64: =IF($B$8=0,"",IFERROR(IF(INDEX(Distritos!$I$7:$I$66,MATCH(SMALL(Distritos!$J$7:$J$66,26),Distritos!$J$7:$J$66,0))=0,"",INDEX(Distritos!$I$7:$I$66,MATCH(SMALL(Distritos!$J$7:$J$66,26),Distritos!$J$7:$J$66,0))),"")) -> 1 | D64: =IF(OR($B$8=0,C64="",C64=0),"",C64/$B$8) -> 0.0065359477 | E64: =IF(OR($B$8=0,B64=""),"",IFERROR(ROUND(IF($D$4="TODOS",IF($B$4="TODOS",(SUMIF('BD SECOS'!Q:Q,B64,'BD SECOS'!U:U)+SUMIF('BD PPA'!U:U,B64,'BD PPA'!AA:AA)+SUMIF('BD FRESCOS'!U:U,B64,'BD FRESCOS'!AA:AA))/(COUNTIF('BD SECOS'!Q:Q,B64)+COUNTIF('BD PPA'!U:U,B64)+COUNTIF('BD FRESCOS'!U:U,B64)),IF($B$4="SECOS",AVERAGEIF('BD SECOS'!Q:Q,B64,'BD SECOS'!U:U),IF($B$4="PPA",AVERAGEIF('BD PPA'!U:U,B64,'BD PPA'!AA:AA),AVERAGEIF('BD FRESCOS'!U:U,B64,'BD FRESCOS'!AA:AA)))),IF($B$4="TODOS",(SUMIFS('BD SECOS'!U:U,'BD SECOS'!Q:Q,B64,'BD SECOS'!AE:AE,$D$4)+SUMIFS('BD PPA'!AA:AA,'BD PPA'!U:U,B64,'BD PPA'!AK:AK,$D$4)+SUMIFS('BD FRESCOS'!AA:AA,'BD FRESCOS'!U:U,B64,'BD FRESCOS'!AK:AK,$D$4))/(COUNTIFS('BD SECOS'!Q:Q,B64,'BD SECOS'!AE:AE,$D$4)+COUNTIFS('BD PPA'!U:U,B64,'BD PPA'!AK:AK,$D$4)+COUNTIFS('BD FRESCOS'!U:U,B64,'BD FRESCOS'!AK:AK,$D$4)),IF($B$4="SECOS",AVERAGEIFS('BD SECOS'!U:U,'BD SECOS'!Q:Q,B64,'BD SECOS'!AE:AE,$D$4),IF($B$4="PPA",AVERAGEIFS('BD PPA'!AA:AA,'BD PPA'!U:U,B64,'BD PPA'!AK:AK,$D$4),AVERAGEIFS('BD FRESCOS'!AA:AA,'BD FRESCOS'!U:U,B64,'BD FRESCOS'!AK:AK,$D$4))))),2),"")) -> 18.9 | F64: =IF(OR($B$8=0,E64=""),"",IF(E64<=5,"🟢 Muy Cerca",IF(E64<=10,"🟡 Cerca",IF(E64<=20,"🟠 Moderada","🔴 Lejos")))) -> 🟠 Moderada | G64: =IF(OR($B$8=0,B64=""),"",IFERROR(ROUND(IF($D$4="TODOS",IF($B$4="TODOS",(SUMIF('BD SECOS'!Q:Q,B64,'BD SECOS'!Y:Y)+SUMIF('BD PPA'!U:U,B64,'BD PPA'!AE:AE)+SUMIF('BD FRESCOS'!U:U,B64,'BD FRESCOS'!AE:AE))/(COUNTIF('BD SECOS'!Q:Q,B64)+COUNTIF('BD PPA'!U:U,B64)+COUNTIF('BD FRESCOS'!U:U,B64)),IF($B$4="SECOS",AVERAGEIF('BD SECOS'!Q:Q,B64,'BD SECOS'!Y:Y),IF($B$4="PPA",AVERAGEIF('BD PPA'!U:U,B64,'BD PPA'!AE:AE),AVERAGEIF('BD FRESCOS'!U:U,B64,'BD FRESCOS'!AE:AE)))),IF($B$4="TODOS",(SUMIFS('BD SECOS'!Y:Y,'BD SECOS'!Q:Q,B64,'BD SECOS'!AE:AE,$D$4)+SUMIFS('BD PPA'!AE:AE,'BD PPA'!U:U,B64,'BD PPA'!AK:AK,$D$4)+SUMIFS('BD FRESCOS'!AE:AE,'BD FRESCOS'!U:U,B64,'BD FRESCOS'!AK:AK,$D$4))/(COUNTIFS('BD SECOS'!Q:Q,B64,'BD SECOS'!AE:AE,$D$4)+COUNTIFS('BD PPA'!U:U,B64,'BD PPA'!AK:AK,$D$4)+COUNTIFS('BD FRESCOS'!U:U,B64,'BD FRESCOS'!AK:AK,$D$4)),IF($B$4="SECOS",AVERAGEIFS('BD SECOS'!Y:Y,'BD SECOS'!Q:Q,B64,'BD SECOS'!AE:AE,$D$4),IF($B$4="PPA",AVERAGEIFS('BD PPA'!AE:AE,'BD PPA'!U:U,B64,'BD PPA'!AK:AK,$D$4),AVERAGEIFS('BD FRESCOS'!AE:AE,'BD FRESCOS'!U:U,B64,'BD FRESCOS'!AK:AK,$D$4))))),2),"")) -> 3.42 | H64: =IF(OR($B$8=0,G64=""),"",IF(G64<=1,"🟢 Muy Cerca",IF(G64<=3,"🟡 Cerca",IF(G64<=5,"🟠 Moderada","🔴 Lejos")))) -> 🟠 Moderada | I64: {=IF(OR($B$8=0,B64=""),"",IFERROR(IF($D$4="TODOS",IF($B$4="TODOS",INDEX('BD SECOS'!X:X,MATCH(B64,'BD SECOS'!Q:Q,0)),IF($B$4="SECOS",INDEX('BD SECOS'!X:X,MATCH(B64,'BD SECOS'!Q:Q,0)),IF($B$4="PPA",INDEX('BD PPA'!AD:AD,MATCH(B64,'BD PPA'!U:U,0)),INDEX('BD FRESCOS'!AD:AD,MATCH(B64,'BD FRESCOS'!U:U,0))))),IF($B$4="TODOS",IFERROR(INDEX('BD SECOS'!X:X,MATCH(1,('BD SECOS'!Q:Q=B64)*('BD SECOS'!AE:AE=$D$4),0)),IFERROR(INDEX('BD PPA'!AD:AD,MATCH(1,('BD PPA'!U:U=B64)*('BD PPA'!AK:AK=$D$4),0)),INDEX('BD FRESCOS'!AD:AD,MATCH(1,('BD FRESCOS'!U:U=B64)*('BD FRESCOS'!AK:AK=$D$4),0)))),IF($B$4="SECOS",INDEX('BD SECOS'!X:X,MATCH(1,('BD SECOS'!Q:Q=B64)*('BD SECOS'!AE:AE=$D$4),0)),IF($B$4="PPA",INDEX('BD PPA'!AD:AD,MATCH(1,('BD PPA'!U:U=B64)*('BD PPA'!AK:AK=$D$4),0)),INDEX('BD FRESCOS'!AD:AD,MATCH(1,('BD FRESCOS'!U:U=B64)*('BD FRESCOS'!AK:AK=$D$4),0)))))),""))} -> RUTA 9 | J64: =IF(OR($B$8=0,B64=""),"",IF(AND(E64>20,G64>5),"⚠️ Muy lejos del CD y paraderos",IF(E64>20,"⚠️ Muy lejos del CD",IF(G64>5,"⚠️ Lejos de paraderos","📍 Normal")))) -> 📍 Normal
A65: =IF(OR($B$8=0,C65="",C65=0),"",27) -> 27 | B65: =IF($B$8=0,"",IFERROR(IF(INDEX(Distritos!$I$7:$I$66,MATCH(SMALL(Distritos!$J$7:$J$66,27),Distritos!$J$7:$J$66,0))=0,"",INDEX(Distritos!$H$7:$H$66,MATCH(SMALL(Distritos!$J$7:$J$66,27),Distritos!$J$7:$J$66,0))),"")) -> Magdalena Del Mar | C65: =IF($B$8=0,"",IFERROR(IF(INDEX(Distritos!$I$7:$I$66,MATCH(SMALL(Distritos!$J$7:$J$66,27),Distritos!$J$7:$J$66,0))=0,"",INDEX(Distritos!$I$7:$I$66,MATCH(SMALL(Distritos!$J$7:$J$66,27),Distritos!$J$7:$J$66,0))),"")) -> 1 | D65: =IF(OR($B$8=0,C65="",C65=0),"",C65/$B$8) -> 0.0065359477 | E65: =IF(OR($B$8=0,B65=""),"",IFERROR(ROUND(IF($D$4="TODOS",IF($B$4="TODOS",(SUMIF('BD SECOS'!Q:Q,B65,'BD SECOS'!U:U)+SUMIF('BD PPA'!U:U,B65,'BD PPA'!AA:AA)+SUMIF('BD FRESCOS'!U:U,B65,'BD FRESCOS'!AA:AA))/(COUNTIF('BD SECOS'!Q:Q,B65)+COUNTIF('BD PPA'!U:U,B65)+COUNTIF('BD FRESCOS'!U:U,B65)),IF($B$4="SECOS",AVERAGEIF('BD SECOS'!Q:Q,B65,'BD SECOS'!U:U),IF($B$4="PPA",AVERAGEIF('BD PPA'!U:U,B65,'BD PPA'!AA:AA),AVERAGEIF('BD FRESCOS'!U:U,B65,'BD FRESCOS'!AA:AA)))),IF($B$4="TODOS",(SUMIFS('BD SECOS'!U:U,'BD SECOS'!Q:Q,B65,'BD SECOS'!AE:AE,$D$4)+SUMIFS('BD PPA'!AA:AA,'BD PPA'!U:U,B65,'BD PPA'!AK:AK,$D$4)+SUMIFS('BD FRESCOS'!AA:AA,'BD FRESCOS'!U:U,B65,'BD FRESCOS'!AK:AK,$D$4))/(COUNTIFS('BD SECOS'!Q:Q,B65,'BD SECOS'!AE:AE,$D$4)+COUNTIFS('BD PPA'!U:U,B65,'BD PPA'!AK:AK,$D$4)+COUNTIFS('BD FRESCOS'!U:U,B65,'BD FRESCOS'!AK:AK,$D$4)),IF($B$4="SECOS",AVERAGEIFS('BD SECOS'!U:U,'BD SECOS'!Q:Q,B65,'BD SECOS'!AE:AE,$D$4),IF($B$4="PPA",AVERAGEIFS('BD PPA'!AA:AA,'BD PPA'!U:U,B65,'BD PPA'!AK:AK,$D$4),AVERAGEIFS('BD FRESCOS'!AA:AA,'BD FRESCOS'!U:U,B65,'BD FRESCOS'!AK:AK,$D$4))))),2),"")) -> 21.19 | F65: =IF(OR($B$8=0,E65=""),"",IF(E65<=5,"🟢 Muy Cerca",IF(E65<=10,"🟡 Cerca",IF(E65<=20,"🟠 Moderada","🔴 Lejos")))) -> 🔴 Lejos | G65: =IF(OR($B$8=0,B65=""),"",IFERROR(ROUND(IF($D$4="TODOS",IF($B$4="TODOS",(SUMIF('BD SECOS'!Q:Q,B65,'BD SECOS'!Y:Y)+SUMIF('BD PPA'!U:U,B65,'BD PPA'!AE:AE)+SUMIF('BD FRESCOS'!U:U,B65,'BD FRESCOS'!AE:AE))/(COUNTIF('BD SECOS'!Q:Q,B65)+COUNTIF('BD PPA'!U:U,B65)+COUNTIF('BD FRESCOS'!U:U,B65)),IF($B$4="SECOS",AVERAGEIF('BD SECOS'!Q:Q,B65,'BD SECOS'!Y:Y),IF($B$4="PPA",AVERAGEIF('BD PPA'!U:U,B65,'BD PPA'!AE:AE),AVERAGEIF('BD FRESCOS'!U:U,B65,'BD FRESCOS'!AE:AE)))),IF($B$4="TODOS",(SUMIFS('BD SECOS'!Y:Y,'BD SECOS'!Q:Q,B65,'BD SECOS'!AE:AE,$D$4)+SUMIFS('BD PPA'!AE:AE,'BD PPA'!U:U,B65,'BD PPA'!AK:AK,$D$4)+SUMIFS('BD FRESCOS'!AE:AE,'BD FRESCOS'!U:U,B65,'BD FRESCOS'!AK:AK,$D$4))/(COUNTIFS('BD SECOS'!Q:Q,B65,'BD SECOS'!AE:AE,$D$4)+COUNTIFS('BD PPA'!U:U,B65,'BD PPA'!AK:AK,$D$4)+COUNTIFS('BD FRESCOS'!U:U,B65,'BD FRESCOS'!AK:AK,$D$4)),IF($B$4="SECOS",AVERAGEIFS('BD SECOS'!Y:Y,'BD SECOS'!Q:Q,B65,'BD SECOS'!AE:AE,$D$4),IF($B$4="PPA",AVERAGEIFS('BD PPA'!AE:AE,'BD PPA'!U:U,B65,'BD PPA'!AK:AK,$D$4),AVERAGEIFS('BD FRESCOS'!AE:AE,'BD FRESCOS'!U:U,B65,'BD FRESCOS'!AK:AK,$D$4))))),2),"")) -> 1.88 | H65: =IF(OR($B$8=0,G65=""),"",IF(G65<=1,"🟢 Muy Cerca",IF(G65<=3,"🟡 Cerca",IF(G65<=5,"🟠 Moderada","🔴 Lejos")))) -> 🟡 Cerca | I65: {=IF(OR($B$8=0,B65=""),"",IFERROR(IF($D$4="TODOS",IF($B$4="TODOS",INDEX('BD SECOS'!X:X,MATCH(B65,'BD SECOS'!Q:Q,0)),IF($B$4="SECOS",INDEX('BD SECOS'!X:X,MATCH(B65,'BD SECOS'!Q:Q,0)),IF($B$4="PPA",INDEX('BD PPA'!AD:AD,MATCH(B65,'BD PPA'!U:U,0)),INDEX('BD FRESCOS'!AD:AD,MATCH(B65,'BD FRESCOS'!U:U,0))))),IF($B$4="TODOS",IFERROR(INDEX('BD SECOS'!X:X,MATCH(1,('BD SECOS'!Q:Q=B65)*('BD SECOS'!AE:AE=$D$4),0)),IFERROR(INDEX('BD PPA'!AD:AD,MATCH(1,('BD PPA'!U:U=B65)*('BD PPA'!AK:AK=$D$4),0)),INDEX('BD FRESCOS'!AD:AD,MATCH(1,('BD FRESCOS'!U:U=B65)*('BD FRESCOS'!AK:AK=$D$4),0)))),IF($B$4="SECOS",INDEX('BD SECOS'!X:X,MATCH(1,('BD SECOS'!Q:Q=B65)*('BD SECOS'!AE:AE=$D$4),0)),IF($B$4="PPA",INDEX('BD PPA'!AD:AD,MATCH(1,('BD PPA'!U:U=B65)*('BD PPA'!AK:AK=$D$4),0)),INDEX('BD FRESCOS'!AD:AD,MATCH(1,('BD FRESCOS'!U:U=B65)*('BD FRESCOS'!AK:AK=$D$4),0)))))),""))} -> RUTA 9 | J65: =IF(OR($B$8=0,B65=""),"",IF(AND(E65>20,G65>5),"⚠️ Muy lejos del CD y paraderos",IF(E65>20,"⚠️ Muy lejos del CD",IF(G65>5,"⚠️ Lejos de paraderos","📍 Normal")))) -> ⚠️ Muy lejos del CD
A66: =IF(OR($B$8=0,C66="",C66=0),"",28) -> 28 | B66: =IF($B$8=0,"",IFERROR(IF(INDEX(Distritos!$I$7:$I$66,MATCH(SMALL(Distritos!$J$7:$J$66,28),Distritos!$J$7:$J$66,0))=0,"",INDEX(Distritos!$H$7:$H$66,MATCH(SMALL(Distritos!$J$7:$J$66,28),Distritos!$J$7:$J$66,0))),"")) -> San Antonio | C66: =IF($B$8=0,"",IFERROR(IF(INDEX(Distritos!$I$7:$I$66,MATCH(SMALL(Distritos!$J$7:$J$66,28),Distritos!$J$7:$J$66,0))=0,"",INDEX(Distritos!$I$7:$I$66,MATCH(SMALL(Distritos!$J$7:$J$66,28),Distritos!$J$7:$J$66,0))),"")) -> 1 | D66: =IF(OR($B$8=0,C66="",C66=0),"",C66/$B$8) -> 0.0065359477 | E66: =IF(OR($B$8=0,B66=""),"",IFERROR(ROUND(IF($D$4="TODOS",IF($B$4="TODOS",(SUMIF('BD SECOS'!Q:Q,B66,'BD SECOS'!U:U)+SUMIF('BD PPA'!U:U,B66,'BD PPA'!AA:AA)+SUMIF('BD FRESCOS'!U:U,B66,'BD FRESCOS'!AA:AA))/(COUNTIF('BD SECOS'!Q:Q,B66)+COUNTIF('BD PPA'!U:U,B66)+COUNTIF('BD FRESCOS'!U:U,B66)),IF($B$4="SECOS",AVERAGEIF('BD SECOS'!Q:Q,B66,'BD SECOS'!U:U),IF($B$4="PPA",AVERAGEIF('BD PPA'!U:U,B66,'BD PPA'!AA:AA),AVERAGEIF('BD FRESCOS'!U:U,B66,'BD FRESCOS'!AA:AA)))),IF($B$4="TODOS",(SUMIFS('BD SECOS'!U:U,'BD SECOS'!Q:Q,B66,'BD SECOS'!AE:AE,$D$4)+SUMIFS('BD PPA'!AA:AA,'BD PPA'!U:U,B66,'BD PPA'!AK:AK,$D$4)+SUMIFS('BD FRESCOS'!AA:AA,'BD FRESCOS'!U:U,B66,'BD FRESCOS'!AK:AK,$D$4))/(COUNTIFS('BD SECOS'!Q:Q,B66,'BD SECOS'!AE:AE,$D$4)+COUNTIFS('BD PPA'!U:U,B66,'BD PPA'!AK:AK,$D$4)+COUNTIFS('BD FRESCOS'!U:U,B66,'BD FRESCOS'!AK:AK,$D$4)),IF($B$4="SECOS",AVERAGEIFS('BD SECOS'!U:U,'BD SECOS'!Q:Q,B66,'BD SECOS'!AE:AE,$D$4),IF($B$4="PPA",AVERAGEIFS('BD PPA'!AA:AA,'BD PPA'!U:U,B66,'BD PPA'!AK:AK,$D$4),AVERAGEIFS('BD FRESCOS'!AA:AA,'BD FRESCOS'!U:U,B66,'BD FRESCOS'!AK:AK,$D$4))))),2),"")) -> 5.5 | F66: =IF(OR($B$8=0,E66=""),"",IF(E66<=5,"🟢 Muy Cerca",IF(E66<=10,"🟡 Cerca",IF(E66<=20,"🟠 Moderada","🔴 Lejos")))) -> 🟡 Cerca | G66: =IF(OR($B$8=0,B66=""),"",IFERROR(ROUND(IF($D$4="TODOS",IF($B$4="TODOS",(SUMIF('BD SECOS'!Q:Q,B66,'BD SECOS'!Y:Y)+SUMIF('BD PPA'!U:U,B66,'BD PPA'!AE:AE)+SUMIF('BD FRESCOS'!U:U,B66,'BD FRESCOS'!AE:AE))/(COUNTIF('BD SECOS'!Q:Q,B66)+COUNTIF('BD PPA'!U:U,B66)+COUNTIF('BD FRESCOS'!U:U,B66)),IF($B$4="SECOS",AVERAGEIF('BD SECOS'!Q:Q,B66,'BD SECOS'!Y:Y),IF($B$4="PPA",AVERAGEIF('BD PPA'!U:U,B66,'BD PPA'!AE:AE),AVERAGEIF('BD FRESCOS'!U:U,B66,'BD FRESCOS'!AE:AE)))),IF($B$4="TODOS",(SUMIFS('BD SECOS'!Y:Y,'BD SECOS'!Q:Q,B66,'BD SECOS'!AE:AE,$D$4)+SUMIFS('BD PPA'!AE:AE,'BD PPA'!U:U,B66,'BD PPA'!AK:AK,$D$4)+SUMIFS('BD FRESCOS'!AE:AE,'BD FRESCOS'!U:U,B66,'BD FRESCOS'!AK:AK,$D$4))/(COUNTIFS('BD SECOS'!Q:Q,B66,'BD SECOS'!AE:AE,$D$4)+COUNTIFS('BD PPA'!U:U,B66,'BD PPA'!AK:AK,$D$4)+COUNTIFS('BD FRESCOS'!U:U,B66,'BD FRESCOS'!AK:AK,$D$4)),IF($B$4="SECOS",AVERAGEIFS('BD SECOS'!Y:Y,'BD SECOS'!Q:Q,B66,'BD SECOS'!AE:AE,$D$4),IF($B$4="PPA",AVERAGEIFS('BD PPA'!AE:AE,'BD PPA'!U:U,B66,'BD PPA'!AK:AK,$D$4),AVERAGEIFS('BD FRESCOS'!AE:AE,'BD FRESCOS'!U:U,B66,'BD FRESCOS'!AK:AK,$D$4))))),2),"")) -> 4.94 | H66: =IF(OR($B$8=0,G66=""),"",IF(G66<=1,"🟢 Muy Cerca",IF(G66<=3,"🟡 Cerca",IF(G66<=5,"🟠 Moderada","🔴 Lejos")))) -> 🟠 Moderada | I66: {=IF(OR($B$8=0,B66=""),"",IFERROR(IF($D$4="TODOS",IF($B$4="TODOS",INDEX('BD SECOS'!X:X,MATCH(B66,'BD SECOS'!Q:Q,0)),IF($B$4="SECOS",INDEX('BD SECOS'!X:X,MATCH(B66,'BD SECOS'!Q:Q,0)),IF($B$4="PPA",INDEX('BD PPA'!AD:AD,MATCH(B66,'BD PPA'!U:U,0)),INDEX('BD FRESCOS'!AD:AD,MATCH(B66,'BD FRESCOS'!U:U,0))))),IF($B$4="TODOS",IFERROR(INDEX('BD SECOS'!X:X,MATCH(1,('BD SECOS'!Q:Q=B66)*('BD SECOS'!AE:AE=$D$4),0)),IFERROR(INDEX('BD PPA'!AD:AD,MATCH(1,('BD PPA'!U:U=B66)*('BD PPA'!AK:AK=$D$4),0)),INDEX('BD FRESCOS'!AD:AD,MATCH(1,('BD FRESCOS'!U:U=B66)*('BD FRESCOS'!AK:AK=$D$4),0)))),IF($B$4="SECOS",INDEX('BD SECOS'!X:X,MATCH(1,('BD SECOS'!Q:Q=B66)*('BD SECOS'!AE:AE=$D$4),0)),IF($B$4="PPA",INDEX('BD PPA'!AD:AD,MATCH(1,('BD PPA'!U:U=B66)*('BD PPA'!AK:AK=$D$4),0)),INDEX('BD FRESCOS'!AD:AD,MATCH(1,('BD FRESCOS'!U:U=B66)*('BD FRESCOS'!AK:AK=$D$4),0)))))),""))} -> RUTA 2 | J66: =IF(OR($B$8=0,B66=""),"",IF(AND(E66>20,G66>5),"⚠️ Muy lejos del CD y paraderos",IF(E66>20,"⚠️ Muy lejos del CD",IF(G66>5,"⚠️ Lejos de paraderos","📍 Normal")))) -> 📍 Normal
A67: =IF(OR($B$8=0,C67="",C67=0),"",29) -> 29 | B67: =IF($B$8=0,"",IFERROR(IF(INDEX(Distritos!$I$7:$I$66,MATCH(SMALL(Distritos!$J$7:$J$66,29),Distritos!$J$7:$J$66,0))=0,"",INDEX(Distritos!$H$7:$H$66,MATCH(SMALL(Distritos!$J$7:$J$66,29),Distritos!$J$7:$J$66,0))),"")) -> San Borja | C67: =IF($B$8=0,"",IFERROR(IF(INDEX(Distritos!$I$7:$I$66,MATCH(SMALL(Distritos!$J$7:$J$66,29),Distritos!$J$7:$J$66,0))=0,"",INDEX(Distritos!$I$7:$I$66,MATCH(SMALL(Distritos!$J$7:$J$66,29),Distritos!$J$7:$J$66,0))),"")) -> 1 | D67: =IF(OR($B$8=0,C67="",C67=0),"",C67/$B$8) -> 0.0065359477 | E67: =IF(OR($B$8=0,B67=""),"",IFERROR(ROUND(IF($D$4="TODOS",IF($B$4="TODOS",(SUMIF('BD SECOS'!Q:Q,B67,'BD SECOS'!U:U)+SUMIF('BD PPA'!U:U,B67,'BD PPA'!AA:AA)+SUMIF('BD FRESCOS'!U:U,B67,'BD FRESCOS'!AA:AA))/(COUNTIF('BD SECOS'!Q:Q,B67)+COUNTIF('BD PPA'!U:U,B67)+COUNTIF('BD FRESCOS'!U:U,B67)),IF($B$4="SECOS",AVERAGEIF('BD SECOS'!Q:Q,B67,'BD SECOS'!U:U),IF($B$4="PPA",AVERAGEIF('BD PPA'!U:U,B67,'BD PPA'!AA:AA),AVERAGEIF('BD FRESCOS'!U:U,B67,'BD FRESCOS'!AA:AA)))),IF($B$4="TODOS",(SUMIFS('BD SECOS'!U:U,'BD SECOS'!Q:Q,B67,'BD SECOS'!AE:AE,$D$4)+SUMIFS('BD PPA'!AA:AA,'BD PPA'!U:U,B67,'BD PPA'!AK:AK,$D$4)+SUMIFS('BD FRESCOS'!AA:AA,'BD FRESCOS'!U:U,B67,'BD FRESCOS'!AK:AK,$D$4))/(COUNTIFS('BD SECOS'!Q:Q,B67,'BD SECOS'!AE:AE,$D$4)+COUNTIFS('BD PPA'!U:U,B67,'BD PPA'!AK:AK,$D$4)+COUNTIFS('BD FRESCOS'!U:U,B67,'BD FRESCOS'!AK:AK,$D$4)),IF($B$4="SECOS",AVERAGEIFS('BD SECOS'!U:U,'BD SECOS'!Q:Q,B67,'BD SECOS'!AE:AE,$D$4),IF($B$4="PPA",AVERAGEIFS('BD PPA'!AA:AA,'BD PPA'!U:U,B67,'BD PPA'!AK:AK,$D$4),AVERAGEIFS('BD FRESCOS'!AA:AA,'BD FRESCOS'!U:U,B67,'BD FRESCOS'!AK:AK,$D$4))))),2),"")) -> 14.97 | F67: =IF(OR($B$8=0,E67=""),"",IF(E67<=5,"🟢 Muy Cerca",IF(E67<=10,"🟡 Cerca",IF(E67<=20,"🟠 Moderada","🔴 Lejos")))) -> 🟠 Moderada | G67: =IF(OR($B$8=0,B67=""),"",IFERROR(ROUND(IF($D$4="TODOS",IF($B$4="TODOS",(SUMIF('BD SECOS'!Q:Q,B67,'BD SECOS'!Y:Y)+SUMIF('BD PPA'!U:U,B67,'BD PPA'!AE:AE)+SUMIF('BD FRESCOS'!U:U,B67,'BD FRESCOS'!AE:AE))/(COUNTIF('BD SECOS'!Q:Q,B67)+COUNTIF('BD PPA'!U:U,B67)+COUNTIF('BD FRESCOS'!U:U,B67)),IF($B$4="SECOS",AVERAGEIF('BD SECOS'!Q:Q,B67,'BD SECOS'!Y:Y),IF($B$4="PPA",AVERAGEIF('BD PPA'!U:U,B67,'BD PPA'!AE:AE),AVERAGEIF('BD FRESCOS'!U:U,B67,'BD FRESCOS'!AE:AE)))),IF($B$4="TODOS",(SUMIFS('BD SECOS'!Y:Y,'BD SECOS'!Q:Q,B67,'BD SECOS'!AE:AE,$D$4)+SUMIFS('BD PPA'!AE:AE,'BD PPA'!U:U,B67,'BD PPA'!AK:AK,$D$4)+SUMIFS('BD FRESCOS'!AE:AE,'BD FRESCOS'!U:U,B67,'BD FRESCOS'!AK:AK,$D$4))/(COUNTIFS('BD SECOS'!Q:Q,B67,'BD SECOS'!AE:AE,$D$4)+COUNTIFS('BD PPA'!U:U,B67,'BD PPA'!AK:AK,$D$4)+COUNTIFS('BD FRESCOS'!U:U,B67,'BD FRESCOS'!AK:AK,$D$4)),IF($B$4="SECOS",AVERAGEIFS('BD SECOS'!Y:Y,'BD SECOS'!Q:Q,B67,'BD SECOS'!AE:AE,$D$4),IF($B$4="PPA",AVERAGEIFS('BD PPA'!AE:AE,'BD PPA'!U:U,B67,'BD PPA'!AK:AK,$D$4),AVERAGEIFS('BD FRESCOS'!AE:AE,'BD FRESCOS'!U:U,B67,'BD FRESCOS'!AK:AK,$D$4))))),2),"")) -> 0.22 | H67: =IF(OR($B$8=0,G67=""),"",IF(G67<=1,"🟢 Muy Cerca",IF(G67<=3,"🟡 Cerca",IF(G67<=5,"🟠 Moderada","🔴 Lejos")))) -> 🟢 Muy Cerca | I67: {=IF(OR($B$8=0,B67=""),"",IFERROR(IF($D$4="TODOS",IF($B$4="TODOS",INDEX('BD SECOS'!X:X,MATCH(B67,'BD SECOS'!Q:Q,0)),IF($B$4="SECOS",INDEX('BD SECOS'!X:X,MATCH(B67,'BD SECOS'!Q:Q,0)),IF($B$4="PPA",INDEX('BD PPA'!AD:AD,MATCH(B67,'BD PPA'!U:U,0)),INDEX('BD FRESCOS'!AD:AD,MATCH(B67,'BD FRESCOS'!U:U,0))))),IF($B$4="TODOS",IFERROR(INDEX('BD SECOS'!X:X,MATCH(1,('BD SECOS'!Q:Q=B67)*('BD SECOS'!AE:AE=$D$4),0)),IFERROR(INDEX('BD PPA'!AD:AD,MATCH(1,('BD PPA'!U:U=B67)*('BD PPA'!AK:AK=$D$4),0)),INDEX('BD FRESCOS'!AD:AD,MATCH(1,('BD FRESCOS'!U:U=B67)*('BD FRESCOS'!AK:AK=$D$4),0)))),IF($B$4="SECOS",INDEX('BD SECOS'!X:X,MATCH(1,('BD SECOS'!Q:Q=B67)*('BD SECOS'!AE:AE=$D$4),0)),IF($B$4="PPA",INDEX('BD PPA'!AD:AD,MATCH(1,('BD PPA'!U:U=B67)*('BD PPA'!AK:AK=$D$4),0)),INDEX('BD FRESCOS'!AD:AD,MATCH(1,('BD FRESCOS'!U:U=B67)*('BD FRESCOS'!AK:AK=$D$4),0)))))),""))} -> RUTA 7 | J67: =IF(OR($B$8=0,B67=""),"",IF(AND(E67>20,G67>5),"⚠️ Muy lejos del CD y paraderos",IF(E67>20,"⚠️ Muy lejos del CD",IF(G67>5,"⚠️ Lejos de paraderos","📍 Normal")))) -> 📍 Normal
A68: =IF(OR($B$8=0,C68="",C68=0),"",30) -> 30 | B68: =IF($B$8=0,"",IFERROR(IF(INDEX(Distritos!$I$7:$I$66,MATCH(SMALL(Distritos!$J$7:$J$66,30),Distritos!$J$7:$J$66,0))=0,"",INDEX(Distritos!$H$7:$H$66,MATCH(SMALL(Distritos!$J$7:$J$66,30),Distritos!$J$7:$J$66,0))),"")) -> San Luis | C68: =IF($B$8=0,"",IFERROR(IF(INDEX(Distritos!$I$7:$I$66,MATCH(SMALL(Distritos!$J$7:$J$66,30),Distritos!$J$7:$J$66,0))=0,"",INDEX(Distritos!$I$7:$I$66,MATCH(SMALL(Distritos!$J$7:$J$66,30),Distritos!$J$7:$J$66,0))),"")) -> 1 | D68: =IF(OR($B$8=0,C68="",C68=0),"",C68/$B$8) -> 0.0065359477 | E68: =IF(OR($B$8=0,B68=""),"",IFERROR(ROUND(IF($D$4="TODOS",IF($B$4="TODOS",(SUMIF('BD SECOS'!Q:Q,B68,'BD SECOS'!U:U)+SUMIF('BD PPA'!U:U,B68,'BD PPA'!AA:AA)+SUMIF('BD FRESCOS'!U:U,B68,'BD FRESCOS'!AA:AA))/(COUNTIF('BD SECOS'!Q:Q,B68)+COUNTIF('BD PPA'!U:U,B68)+COUNTIF('BD FRESCOS'!U:U,B68)),IF($B$4="SECOS",AVERAGEIF('BD SECOS'!Q:Q,B68,'BD SECOS'!U:U),IF($B$4="PPA",AVERAGEIF('BD PPA'!U:U,B68,'BD PPA'!AA:AA),AVERAGEIF('BD FRESCOS'!U:U,B68,'BD FRESCOS'!AA:AA)))),IF($B$4="TODOS",(SUMIFS('BD SECOS'!U:U,'BD SECOS'!Q:Q,B68,'BD SECOS'!AE:AE,$D$4)+SUMIFS('BD PPA'!AA:AA,'BD PPA'!U:U,B68,'BD PPA'!AK:AK,$D$4)+SUMIFS('BD FRESCOS'!AA:AA,'BD FRESCOS'!U:U,B68,'BD FRESCOS'!AK:AK,$D$4))/(COUNTIFS('BD SECOS'!Q:Q,B68,'BD SECOS'!AE:AE,$D$4)+COUNTIFS('BD PPA'!U:U,B68,'BD PPA'!AK:AK,$D$4)+COUNTIFS('BD FRESCOS'!U:U,B68,'BD FRESCOS'!AK:AK,$D$4)),IF($B$4="SECOS",AVERAGEIFS('BD SECOS'!U:U,'BD SECOS'!Q:Q,B68,'BD SECOS'!AE:AE,$D$4),IF($B$4="PPA",AVERAGEIFS('BD PPA'!AA:AA,'BD PPA'!U:U,B68,'BD PPA'!AK:AK,$D$4),AVERAGEIFS('BD FRESCOS'!AA:AA,'BD FRESCOS'!U:U,B68,'BD FRESCOS'!AK:AK,$D$4))))),2),"")) -> 14.25 | F68: =IF(OR($B$8=0,E68=""),"",IF(E68<=5,"🟢 Muy Cerca",IF(E68<=10,"🟡 Cerca",IF(E68<=20,"🟠 Moderada","🔴 Lejos")))) -> 🟠 Moderada | G68: =IF(OR($B$8=0,B68=""),"",IFERROR(ROUND(IF($D$4="TODOS",IF($B$4="TODOS",(SUMIF('BD SECOS'!Q:Q,B68,'BD SECOS'!Y:Y)+SUMIF('BD PPA'!U:U,B68,'BD PPA'!AE:AE)+SUMIF('BD FRESCOS'!U:U,B68,'BD FRESCOS'!AE:AE))/(COUNTIF('BD SECOS'!Q:Q,B68)+COUNTIF('BD PPA'!U:U,B68)+COUNTIF('BD FRESCOS'!U:U,B68)),IF($B$4="SECOS",AVERAGEIF('BD SECOS'!Q:Q,B68,'BD SECOS'!Y:Y),IF($B$4="PPA",AVERAGEIF('BD PPA'!U:U,B68,'BD PPA'!AE:AE),AVERAGEIF('BD FRESCOS'!U:U,B68,'BD FRESCOS'!AE:AE)))),IF($B$4="TODOS",(SUMIFS('BD SECOS'!Y:Y,'BD SECOS'!Q:Q,B68,'BD SECOS'!AE:AE,$D$4)+SUMIFS('BD PPA'!AE:AE,'BD PPA'!U:U,B68,'BD PPA'!AK:AK,$D$4)+SUMIFS('BD FRESCOS'!AE:AE,'BD FRESCOS'!U:U,B68,'BD FRESCOS'!AK:AK,$D$4))/(COUNTIFS('BD SECOS'!Q:Q,B68,'BD SECOS'!AE:AE,$D$4)+COUNTIFS('BD PPA'!U:U,B68,'BD PPA'!AK:AK,$D$4)+COUNTIFS('BD FRESCOS'!U:U,B68,'BD FRESCOS'!AK:AK,$D$4)),IF($B$4="SECOS",AVERAGEIFS('BD SECOS'!Y:Y,'BD SECOS'!Q:Q,B68,'BD SECOS'!AE:AE,$D$4),IF($B$4="PPA",AVERAGEIFS('BD PPA'!AE:AE,'BD PPA'!U:U,B68,'BD PPA'!AK:AK,$D$4),AVERAGEIFS('BD FRESCOS'!AE:AE,'BD FRESCOS'!U:U,B68,'BD FRESCOS'!AK:AK,$D$4))))),2),"")) -> 2.17 | H68: =IF(OR($B$8=0,G68=""),"",IF(G68<=1,"🟢 Muy Cerca",IF(G68<=3,"🟡 Cerca",IF(G68<=5,"🟠 Moderada","🔴 Lejos")))) -> 🟡 Cerca | I68: {=IF(OR($B$8=0,B68=""),"",IFERROR(IF($D$4="TODOS",IF($B$4="TODOS",INDEX('BD SECOS'!X:X,MATCH(B68,'BD SECOS'!Q:Q,0)),IF($B$4="SECOS",INDEX('BD SECOS'!X:X,MATCH(B68,'BD SECOS'!Q:Q,0)),IF($B$4="PPA",INDEX('BD PPA'!AD:AD,MATCH(B68,'BD PPA'!U:U,0)),INDEX('BD FRESCOS'!AD:AD,MATCH(B68,'BD FRESCOS'!U:U,0))))),IF($B$4="TODOS",IFERROR(INDEX('BD SECOS'!X:X,MATCH(1,('BD SECOS'!Q:Q=B68)*('BD SECOS'!AE:AE=$D$4),0)),IFERROR(INDEX('BD PPA'!AD:AD,MATCH(1,('BD PPA'!U:U=B68)*('BD PPA'!AK:AK=$D$4),0)),INDEX('BD FRESCOS'!AD:AD,MATCH(1,('BD FRESCOS'!U:U=B68)*('BD FRESCOS'!AK:AK=$D$4),0)))),IF($B$4="SECOS",INDEX('BD SECOS'!X:X,MATCH(1,('BD SECOS'!Q:Q=B68)*('BD SECOS'!AE:AE=$D$4),0)),IF($B$4="PPA",INDEX('BD PPA'!AD:AD,MATCH(1,('BD PPA'!U:U=B68)*('BD PPA'!AK:AK=$D$4),0)),INDEX('BD FRESCOS'!AD:AD,MATCH(1,('BD FRESCOS'!U:U=B68)*('BD FRESCOS'!AK:AK=$D$4),0)))))),""))} -> RUTA 4A | J68: =IF(OR($B$8=0,B68=""),"",IF(AND(E68>20,G68>5),"⚠️ Muy lejos del CD y paraderos",IF(E68>20,"⚠️ Muy lejos del CD",IF(G68>5,"⚠️ Lejos de paraderos","📍 Normal")))) -> 📍 Normal
A69: =IF(OR($B$8=0,C69="",C69=0),"",31) -> 31 | B69: =IF($B$8=0,"",IFERROR(IF(INDEX(Distritos!$I$7:$I$66,MATCH(SMALL(Distritos!$J$7:$J$66,31),Distritos!$J$7:$J$66,0))=0,"",INDEX(Distritos!$H$7:$H$66,MATCH(SMALL(Distritos!$J$7:$J$66,31),Distritos!$J$7:$J$66,0))),"")) -> Vegueta | C69: =IF($B$8=0,"",IFERROR(IF(INDEX(Distritos!$I$7:$I$66,MATCH(SMALL(Distritos!$J$7:$J$66,31),Distritos!$J$7:$J$66,0))=0,"",INDEX(Distritos!$I$7:$I$66,MATCH(SMALL(Distritos!$J$7:$J$66,31),Distritos!$J$7:$J$66,0))),"")) -> 1 | D69: =IF(OR($B$8=0,C69="",C69=0),"",C69/$B$8) -> 0.0065359477 | E69: =IF(OR($B$8=0,B69=""),"",IFERROR(ROUND(IF($D$4="TODOS",IF($B$4="TODOS",(SUMIF('BD SECOS'!Q:Q,B69,'BD SECOS'!U:U)+SUMIF('BD PPA'!U:U,B69,'BD PPA'!AA:AA)+SUMIF('BD FRESCOS'!U:U,B69,'BD FRESCOS'!AA:AA))/(COUNTIF('BD SECOS'!Q:Q,B69)+COUNTIF('BD PPA'!U:U,B69)+COUNTIF('BD FRESCOS'!U:U,B69)),IF($B$4="SECOS",AVERAGEIF('BD SECOS'!Q:Q,B69,'BD SECOS'!U:U),IF($B$4="PPA",AVERAGEIF('BD PPA'!U:U,B69,'BD PPA'!AA:AA),AVERAGEIF('BD FRESCOS'!U:U,B69,'BD FRESCOS'!AA:AA)))),IF($B$4="TODOS",(SUMIFS('BD SECOS'!U:U,'BD SECOS'!Q:Q,B69,'BD SECOS'!AE:AE,$D$4)+SUMIFS('BD PPA'!AA:AA,'BD PPA'!U:U,B69,'BD PPA'!AK:AK,$D$4)+SUMIFS('BD FRESCOS'!AA:AA,'BD FRESCOS'!U:U,B69,'BD FRESCOS'!AK:AK,$D$4))/(COUNTIFS('BD SECOS'!Q:Q,B69,'BD SECOS'!AE:AE,$D$4)+COUNTIFS('BD PPA'!U:U,B69,'BD PPA'!AK:AK,$D$4)+COUNTIFS('BD FRESCOS'!U:U,B69,'BD FRESCOS'!AK:AK,$D$4)),IF($B$4="SECOS",AVERAGEIFS('BD SECOS'!U:U,'BD SECOS'!Q:Q,B69,'BD SECOS'!AE:AE,$D$4),IF($B$4="PPA",AVERAGEIFS('BD PPA'!AA:AA,'BD PPA'!U:U,B69,'BD PPA'!AK:AK,$D$4),AVERAGEIFS('BD FRESCOS'!AA:AA,'BD FRESCOS'!U:U,B69,'BD FRESCOS'!AK:AK,$D$4))))),2),"")) -> 0 | F69: =IF(OR($B$8=0,E69=""),"",IF(E69<=5,"🟢 Muy Cerca",IF(E69<=10,"🟡 Cerca",IF(E69<=20,"🟠 Moderada","🔴 Lejos")))) -> 🟢 Muy Cerca | G69: =IF(OR($B$8=0,B69=""),"",IFERROR(ROUND(IF($D$4="TODOS",IF($B$4="TODOS",(SUMIF('BD SECOS'!Q:Q,B69,'BD SECOS'!Y:Y)+SUMIF('BD PPA'!U:U,B69,'BD PPA'!AE:AE)+SUMIF('BD FRESCOS'!U:U,B69,'BD FRESCOS'!AE:AE))/(COUNTIF('BD SECOS'!Q:Q,B69)+COUNTIF('BD PPA'!U:U,B69)+COUNTIF('BD FRESCOS'!U:U,B69)),IF($B$4="SECOS",AVERAGEIF('BD SECOS'!Q:Q,B69,'BD SECOS'!Y:Y),IF($B$4="PPA",AVERAGEIF('BD PPA'!U:U,B69,'BD PPA'!AE:AE),AVERAGEIF('BD FRESCOS'!U:U,B69,'BD FRESCOS'!AE:AE)))),IF($B$4="TODOS",(SUMIFS('BD SECOS'!Y:Y,'BD SECOS'!Q:Q,B69,'BD SECOS'!AE:AE,$D$4)+SUMIFS('BD PPA'!AE:AE,'BD PPA'!U:U,B69,'BD PPA'!AK:AK,$D$4)+SUMIFS('BD FRESCOS'!AE:AE,'BD FRESCOS'!U:U,B69,'BD FRESCOS'!AK:AK,$D$4))/(COUNTIFS('BD SECOS'!Q:Q,B69,'BD SECOS'!AE:AE,$D$4)+COUNTIFS('BD PPA'!U:U,B69,'BD PPA'!AK:AK,$D$4)+COUNTIFS('BD FRESCOS'!U:U,B69,'BD FRESCOS'!AK:AK,$D$4)),IF($B$4="SECOS",AVERAGEIFS('BD SECOS'!Y:Y,'BD SECOS'!Q:Q,B69,'BD SECOS'!AE:AE,$D$4),IF($B$4="PPA",AVERAGEIFS('BD PPA'!AE:AE,'BD PPA'!U:U,B69,'BD PPA'!AK:AK,$D$4),AVERAGEIFS('BD FRESCOS'!AE:AE,'BD FRESCOS'!U:U,B69,'BD FRESCOS'!AK:AK,$D$4))))),2),"")) -> 0.3 | H69: =IF(OR($B$8=0,G69=""),"",IF(G69<=1,"🟢 Muy Cerca",IF(G69<=3,"🟡 Cerca",IF(G69<=5,"🟠 Moderada","🔴 Lejos")))) -> 🟢 Muy Cerca | I69: {=IF(OR($B$8=0,B69=""),"",IFERROR(IF($D$4="TODOS",IF($B$4="TODOS",INDEX('BD SECOS'!X:X,MATCH(B69,'BD SECOS'!Q:Q,0)),IF($B$4="SECOS",INDEX('BD SECOS'!X:X,MATCH(B69,'BD SECOS'!Q:Q,0)),IF($B$4="PPA",INDEX('BD PPA'!AD:AD,MATCH(B69,'BD PPA'!U:U,0)),INDEX('BD FRESCOS'!AD:AD,MATCH(B69,'BD FRESCOS'!U:U,0))))),IF($B$4="TODOS",IFERROR(INDEX('BD SECOS'!X:X,MATCH(1,('BD SECOS'!Q:Q=B69)*('BD SECOS'!AE:AE=$D$4),0)),IFERROR(INDEX('BD PPA'!AD:AD,MATCH(1,('BD PPA'!U:U=B69)*('BD PPA'!AK:AK=$D$4),0)),INDEX('BD FRESCOS'!AD:AD,MATCH(1,('BD FRESCOS'!U:U=B69)*('BD FRESCOS'!AK:AK=$D$4),0)))),IF($B$4="SECOS",INDEX('BD SECOS'!X:X,MATCH(1,('BD SECOS'!Q:Q=B69)*('BD SECOS'!AE:AE=$D$4),0)),IF($B$4="PPA",INDEX('BD PPA'!AD:AD,MATCH(1,('BD PPA'!U:U=B69)*('BD PPA'!AK:AK=$D$4),0)),INDEX('BD FRESCOS'!AD:AD,MATCH(1,('BD FRESCOS'!U:U=B69)*('BD FRESCOS'!AK:AK=$D$4),0)))))),""))} -> RUTA 1 | J69: =IF(OR($B$8=0,B69=""),"",IF(AND(E69>20,G69>5),"⚠️ Muy lejos del CD y paraderos",IF(E69>20,"⚠️ Muy lejos del CD",IF(G69>5,"⚠️ Lejos de paraderos","📍 Normal")))) -> 📍 Normal
A70: =IF(OR($B$8=0,C70="",C70=0),"",32) -> 32 | B70: =IF($B$8=0,"",IFERROR(IF(INDEX(Distritos!$I$7:$I$66,MATCH(SMALL(Distritos!$J$7:$J$66,32),Distritos!$J$7:$J$66,0))=0,"",INDEX(Distritos!$H$7:$H$66,MATCH(SMALL(Distritos!$J$7:$J$66,32),Distritos!$J$7:$J$66,0))),"")) -> Ventanilla | C70: =IF($B$8=0,"",IFERROR(IF(INDEX(Distritos!$I$7:$I$66,MATCH(SMALL(Distritos!$J$7:$J$66,32),Distritos!$J$7:$J$66,0))=0,"",INDEX(Distritos!$I$7:$I$66,MATCH(SMALL(Distritos!$J$7:$J$66,32),Distritos!$J$7:$J$66,0))),"")) -> 1 | D70: =IF(OR($B$8=0,C70="",C70=0),"",C70/$B$8) -> 0.0065359477 | E70: =IF(OR($B$8=0,B70=""),"",IFERROR(ROUND(IF($D$4="TODOS",IF($B$4="TODOS",(SUMIF('BD SECOS'!Q:Q,B70,'BD SECOS'!U:U)+SUMIF('BD PPA'!U:U,B70,'BD PPA'!AA:AA)+SUMIF('BD FRESCOS'!U:U,B70,'BD FRESCOS'!AA:AA))/(COUNTIF('BD SECOS'!Q:Q,B70)+COUNTIF('BD PPA'!U:U,B70)+COUNTIF('BD FRESCOS'!U:U,B70)),IF($B$4="SECOS",AVERAGEIF('BD SECOS'!Q:Q,B70,'BD SECOS'!U:U),IF($B$4="PPA",AVERAGEIF('BD PPA'!U:U,B70,'BD PPA'!AA:AA),AVERAGEIF('BD FRESCOS'!U:U,B70,'BD FRESCOS'!AA:AA)))),IF($B$4="TODOS",(SUMIFS('BD SECOS'!U:U,'BD SECOS'!Q:Q,B70,'BD SECOS'!AE:AE,$D$4)+SUMIFS('BD PPA'!AA:AA,'BD PPA'!U:U,B70,'BD PPA'!AK:AK,$D$4)+SUMIFS('BD FRESCOS'!AA:AA,'BD FRESCOS'!U:U,B70,'BD FRESCOS'!AK:AK,$D$4))/(COUNTIFS('BD SECOS'!Q:Q,B70,'BD SECOS'!AE:AE,$D$4)+COUNTIFS('BD PPA'!U:U,B70,'BD PPA'!AK:AK,$D$4)+COUNTIFS('BD FRESCOS'!U:U,B70,'BD FRESCOS'!AK:AK,$D$4)),IF($B$4="SECOS",AVERAGEIFS('BD SECOS'!U:U,'BD SECOS'!Q:Q,B70,'BD SECOS'!AE:AE,$D$4),IF($B$4="PPA",AVERAGEIFS('BD PPA'!AA:AA,'BD PPA'!U:U,B70,'BD PPA'!AK:AK,$D$4),AVERAGEIFS('BD FRESCOS'!AA:AA,'BD FRESCOS'!U:U,B70,'BD FRESCOS'!AK:AK,$D$4))))),2),"")) -> 29.78 | F70: =IF(OR($B$8=0,E70=""),"",IF(E70<=5,"🟢 Muy Cerca",IF(E70<=10,"🟡 Cerca",IF(E70<=20,"🟠 Moderada","🔴 Lejos")))) -> 🔴 Lejos | G70: =IF(OR($B$8=0,B70=""),"",IFERROR(ROUND(IF($D$4="TODOS",IF($B$4="TODOS",(SUMIF('BD SECOS'!Q:Q,B70,'BD SECOS'!Y:Y)+SUMIF('BD PPA'!U:U,B70,'BD PPA'!AE:AE)+SUMIF('BD FRESCOS'!U:U,B70,'BD FRESCOS'!AE:AE))/(COUNTIF('BD SECOS'!Q:Q,B70)+COUNTIF('BD PPA'!U:U,B70)+COUNTIF('BD FRESCOS'!U:U,B70)),IF($B$4="SECOS",AVERAGEIF('BD SECOS'!Q:Q,B70,'BD SECOS'!Y:Y),IF($B$4="PPA",AVERAGEIF('BD PPA'!U:U,B70,'BD PPA'!AE:AE),AVERAGEIF('BD FRESCOS'!U:U,B70,'BD FRESCOS'!AE:AE)))),IF($B$4="TODOS",(SUMIFS('BD SECOS'!Y:Y,'BD SECOS'!Q:Q,B70,'BD SECOS'!AE:AE,$D$4)+SUMIFS('BD PPA'!AE:AE,'BD PPA'!U:U,B70,'BD PPA'!AK:AK,$D$4)+SUMIFS('BD FRESCOS'!AE:AE,'BD FRESCOS'!U:U,B70,'BD FRESCOS'!AK:AK,$D$4))/(COUNTIFS('BD SECOS'!Q:Q,B70,'BD SECOS'!AE:AE,$D$4)+COUNTIFS('BD PPA'!U:U,B70,'BD PPA'!AK:AK,$D$4)+COUNTIFS('BD FRESCOS'!U:U,B70,'BD FRESCOS'!AK:AK,$D$4)),IF($B$4="SECOS",AVERAGEIFS('BD SECOS'!Y:Y,'BD SECOS'!Q:Q,B70,'BD SECOS'!AE:AE,$D$4),IF($B$4="PPA",AVERAGEIFS('BD PPA'!AE:AE,'BD PPA'!U:U,B70,'BD PPA'!AK:AK,$D$4),AVERAGEIFS('BD FRESCOS'!AE:AE,'BD FRESCOS'!U:U,B70,'BD FRESCOS'!AK:AK,$D$4))))),2),"")) -> 13.58 | H70: =IF(OR($B$8=0,G70=""),"",IF(G70<=1,"🟢 Muy Cerca",IF(G70<=3,"🟡 Cerca",IF(G70<=5,"🟠 Moderada","🔴 Lejos")))) -> 🔴 Lejos | I70: {=IF(OR($B$8=0,B70=""),"",IFERROR(IF($D$4="TODOS",IF($B$4="TODOS",INDEX('BD SECOS'!X:X,MATCH(B70,'BD SECOS'!Q:Q,0)),IF($B$4="SECOS",INDEX('BD SECOS'!X:X,MATCH(B70,'BD SECOS'!Q:Q,0)),IF($B$4="PPA",INDEX('BD PPA'!AD:AD,MATCH(B70,'BD PPA'!U:U,0)),INDEX('BD FRESCOS'!AD:AD,MATCH(B70,'BD FRESCOS'!U:U,0))))),IF($B$4="TODOS",IFERROR(INDEX('BD SECOS'!X:X,MATCH(1,('BD SECOS'!Q:Q=B70)*('BD SECOS'!AE:AE=$D$4),0)),IFERROR(INDEX('BD PPA'!AD:AD,MATCH(1,('BD PPA'!U:U=B70)*('BD PPA'!AK:AK=$D$4),0)),INDEX('BD FRESCOS'!AD:AD,MATCH(1,('BD FRESCOS'!U:U=B70)*('BD FRESCOS'!AK:AK=$D$4),0)))),IF($B$4="SECOS",INDEX('BD SECOS'!X:X,MATCH(1,('BD SECOS'!Q:Q=B70)*('BD SECOS'!AE:AE=$D$4),0)),IF($B$4="PPA",INDEX('BD PPA'!AD:AD,MATCH(1,('BD PPA'!U:U=B70)*('BD PPA'!AK:AK=$D$4),0)),INDEX('BD FRESCOS'!AD:AD,MATCH(1,('BD FRESCOS'!U:U=B70)*('BD FRESCOS'!AK:AK=$D$4),0)))))),""))} -> RUTA 4B | J70: =IF(OR($B$8=0,B70=""),"",IF(AND(E70>20,G70>5),"⚠️ Muy lejos del CD y paraderos",IF(E70>20,"⚠️ Muy lejos del CD",IF(G70>5,"⚠️ Lejos de paraderos","📍 Normal")))) -> ⚠️ Muy lejos del CD y paraderos
A71: =IF(OR($B$8=0,C71="",C71=0),"",33) -> 33 | B71: =IF($B$8=0,"",IFERROR(IF(INDEX(Distritos!$I$7:$I$66,MATCH(SMALL(Distritos!$J$7:$J$66,33),Distritos!$J$7:$J$66,0))=0,"",INDEX(Distritos!$H$7:$H$66,MATCH(SMALL(Distritos!$J$7:$J$66,33),Distritos!$J$7:$J$66,0))),"")) -> Villa Maria Del Triunfo | C71: =IF($B$8=0,"",IFERROR(IF(INDEX(Distritos!$I$7:$I$66,MATCH(SMALL(Distritos!$J$7:$J$66,33),Distritos!$J$7:$J$66,0))=0,"",INDEX(Distritos!$I$7:$I$66,MATCH(SMALL(Distritos!$J$7:$J$66,33),Distritos!$J$7:$J$66,0))),"")) -> 1 | D71: =IF(OR($B$8=0,C71="",C71=0),"",C71/$B$8) -> 0.0065359477 | E71: =IF(OR($B$8=0,B71=""),"",IFERROR(ROUND(IF($D$4="TODOS",IF($B$4="TODOS",(SUMIF('BD SECOS'!Q:Q,B71,'BD SECOS'!U:U)+SUMIF('BD PPA'!U:U,B71,'BD PPA'!AA:AA)+SUMIF('BD FRESCOS'!U:U,B71,'BD FRESCOS'!AA:AA))/(COUNTIF('BD SECOS'!Q:Q,B71)+COUNTIF('BD PPA'!U:U,B71)+COUNTIF('BD FRESCOS'!U:U,B71)),IF($B$4="SECOS",AVERAGEIF('BD SECOS'!Q:Q,B71,'BD SECOS'!U:U),IF($B$4="PPA",AVERAGEIF('BD PPA'!U:U,B71,'BD PPA'!AA:AA),AVERAGEIF('BD FRESCOS'!U:U,B71,'BD FRESCOS'!AA:AA)))),IF($B$4="TODOS",(SUMIFS('BD SECOS'!U:U,'BD SECOS'!Q:Q,B71,'BD SECOS'!AE:AE,$D$4)+SUMIFS('BD PPA'!AA:AA,'BD PPA'!U:U,B71,'BD PPA'!AK:AK,$D$4)+SUMIFS('BD FRESCOS'!AA:AA,'BD FRESCOS'!U:U,B71,'BD FRESCOS'!AK:AK,$D$4))/(COUNTIFS('BD SECOS'!Q:Q,B71,'BD SECOS'!AE:AE,$D$4)+COUNTIFS('BD PPA'!U:U,B71,'BD PPA'!AK:AK,$D$4)+COUNTIFS('BD FRESCOS'!U:U,B71,'BD FRESCOS'!AK:AK,$D$4)),IF($B$4="SECOS",AVERAGEIFS('BD SECOS'!U:U,'BD SECOS'!Q:Q,B71,'BD SECOS'!AE:AE,$D$4),IF($B$4="PPA",AVERAGEIFS('BD PPA'!AA:AA,'BD PPA'!U:U,B71,'BD PPA'!AK:AK,$D$4),AVERAGEIFS('BD FRESCOS'!AA:AA,'BD FRESCOS'!U:U,B71,'BD FRESCOS'!AK:AK,$D$4))))),2),"")) -> 18.38 | F71: =IF(OR($B$8=0,E71=""),"",IF(E71<=5,"🟢 Muy Cerca",IF(E71<=10,"🟡 Cerca",IF(E71<=20,"🟠 Moderada","🔴 Lejos")))) -> 🟠 Moderada | G71: =IF(OR($B$8=0,B71=""),"",IFERROR(ROUND(IF($D$4="TODOS",IF($B$4="TODOS",(SUMIF('BD SECOS'!Q:Q,B71,'BD SECOS'!Y:Y)+SUMIF('BD PPA'!U:U,B71,'BD PPA'!AE:AE)+SUMIF('BD FRESCOS'!U:U,B71,'BD FRESCOS'!AE:AE))/(COUNTIF('BD SECOS'!Q:Q,B71)+COUNTIF('BD PPA'!U:U,B71)+COUNTIF('BD FRESCOS'!U:U,B71)),IF($B$4="SECOS",AVERAGEIF('BD SECOS'!Q:Q,B71,'BD SECOS'!Y:Y),IF($B$4="PPA",AVERAGEIF('BD PPA'!U:U,B71,'BD PPA'!AE:AE),AVERAGEIF('BD FRESCOS'!U:U,B71,'BD FRESCOS'!AE:AE)))),IF($B$4="TODOS",(SUMIFS('BD SECOS'!Y:Y,'BD SECOS'!Q:Q,B71,'BD SECOS'!AE:AE,$D$4)+SUMIFS('BD PPA'!AE:AE,'BD PPA'!U:U,B71,'BD PPA'!AK:AK,$D$4)+SUMIFS('BD FRESCOS'!AE:AE,'BD FRESCOS'!U:U,B71,'BD FRESCOS'!AK:AK,$D$4))/(COUNTIFS('BD SECOS'!Q:Q,B71,'BD SECOS'!AE:AE,$D$4)+COUNTIFS('BD PPA'!U:U,B71,'BD PPA'!AK:AK,$D$4)+COUNTIFS('BD FRESCOS'!U:U,B71,'BD FRESCOS'!AK:AK,$D$4)),IF($B$4="SECOS",AVERAGEIFS('BD SECOS'!Y:Y,'BD SECOS'!Q:Q,B71,'BD SECOS'!AE:AE,$D$4),IF($B$4="PPA",AVERAGEIFS('BD PPA'!AE:AE,'BD PPA'!U:U,B71,'BD PPA'!AK:AK,$D$4),AVERAGEIFS('BD FRESCOS'!AE:AE,'BD FRESCOS'!U:U,B71,'BD FRESCOS'!AK:AK,$D$4))))),2),"")) -> 2.5 | H71: =IF(OR($B$8=0,G71=""),"",IF(G71<=1,"🟢 Muy Cerca",IF(G71<=3,"🟡 Cerca",IF(G71<=5,"🟠 Moderada","🔴 Lejos")))) -> 🟡 Cerca | I71: {=IF(OR($B$8=0,B71=""),"",IFERROR(IF($D$4="TODOS",IF($B$4="TODOS",INDEX('BD SECOS'!X:X,MATCH(B71,'BD SECOS'!Q:Q,0)),IF($B$4="SECOS",INDEX('BD SECOS'!X:X,MATCH(B71,'BD SECOS'!Q:Q,0)),IF($B$4="PPA",INDEX('BD PPA'!AD:AD,MATCH(B71,'BD PPA'!U:U,0)),INDEX('BD FRESCOS'!AD:AD,MATCH(B71,'BD FRESCOS'!U:U,0))))),IF($B$4="TODOS",IFERROR(INDEX('BD SECOS'!X:X,MATCH(1,('BD SECOS'!Q:Q=B71)*('BD SECOS'!AE:AE=$D$4),0)),IFERROR(INDEX('BD PPA'!AD:AD,MATCH(1,('BD PPA'!U:U=B71)*('BD PPA'!AK:AK=$D$4),0)),INDEX('BD FRESCOS'!AD:AD,MATCH(1,('BD FRESCOS'!U:U=B71)*('BD FRESCOS'!AK:AK=$D$4),0)))),IF($B$4="SECOS",INDEX('BD SECOS'!X:X,MATCH(1,('BD SECOS'!Q:Q=B71)*('BD SECOS'!AE:AE=$D$4),0)),IF($B$4="PPA",INDEX('BD PPA'!AD:AD,MATCH(1,('BD PPA'!U:U=B71)*('BD PPA'!AK:AK=$D$4),0)),INDEX('BD FRESCOS'!AD:AD,MATCH(1,('BD FRESCOS'!U:U=B71)*('BD FRESCOS'!AK:AK=$D$4),0)))))),""))} -> RUTA 5B | J71: =IF(OR($B$8=0,B71=""),"",IF(AND(E71>20,G71>5),"⚠️ Muy lejos del CD y paraderos",IF(E71>20,"⚠️ Muy lejos del CD",IF(G71>5,"⚠️ Lejos de paraderos","📍 Normal")))) -> 📍 Normal
A72: =IF(OR($B$8=0,C72="",C72=0),"",34) | B72: =IF($B$8=0,"",IFERROR(IF(INDEX(Distritos!$I$7:$I$66,MATCH(SMALL(Distritos!$J$7:$J$66,34),Distritos!$J$7:$J$66,0))=0,"",INDEX(Distritos!$H$7:$H$66,MATCH(SMALL(Distritos!$J$7:$J$66,34),Distritos!$J$7:$J$66,0))),"")) | C72: =IF($B$8=0,"",IFERROR(IF(INDEX(Distritos!$I$7:$I$66,MATCH(SMALL(Distritos!$J$7:$J$66,34),Distritos!$J$7:$J$66,0))=0,"",INDEX(Distritos!$I$7:$I$66,MATCH(SMALL(Distritos!$J$7:$J$66,34),Distritos!$J$7:$J$66,0))),"")) | D72: =IF(OR($B$8=0,C72="",C72=0),"",C72/$B$8) | E72: =IF(OR($B$8=0,B72=""),"",IFERROR(ROUND(IF($D$4="TODOS",IF($B$4="TODOS",(SUMIF('BD SECOS'!Q:Q,B72,'BD SECOS'!U:U)+SUMIF('BD PPA'!U:U,B72,'BD PPA'!AA:AA)+SUMIF('BD FRESCOS'!U:U,B72,'BD FRESCOS'!AA:AA))/(COUNTIF('BD SECOS'!Q:Q,B72)+COUNTIF('BD PPA'!U:U,B72)+COUNTIF('BD FRESCOS'!U:U,B72)),IF($B$4="SECOS",AVERAGEIF('BD SECOS'!Q:Q,B72,'BD SECOS'!U:U),IF($B$4="PPA",AVERAGEIF('BD PPA'!U:U,B72,'BD PPA'!AA:AA),AVERAGEIF('BD FRESCOS'!U:U,B72,'BD FRESCOS'!AA:AA)))),IF($B$4="TODOS",(SUMIFS('BD SECOS'!U:U,'BD SECOS'!Q:Q,B72,'BD SECOS'!AE:AE,$D$4)+SUMIFS('BD PPA'!AA:AA,'BD PPA'!U:U,B72,'BD PPA'!AK:AK,$D$4)+SUMIFS('BD FRESCOS'!AA:AA,'BD FRESCOS'!U:U,B72,'BD FRESCOS'!AK:AK,$D$4))/(COUNTIFS('BD SECOS'!Q:Q,B72,'BD SECOS'!AE:AE,$D$4)+COUNTIFS('BD PPA'!U:U,B72,'BD PPA'!AK:AK,$D$4)+COUNTIFS('BD FRESCOS'!U:U,B72,'BD FRESCOS'!AK:AK,$D$4)),IF($B$4="SECOS",AVERAGEIFS('BD SECOS'!U:U,'BD SECOS'!Q:Q,B72,'BD SECOS'!AE:AE,$D$4),IF($B$4="PPA",AVERAGEIFS('BD PPA'!AA:AA,'BD PPA'!U:U,B72,'BD PPA'!AK:AK,$D$4),AVERAGEIFS('BD FRESCOS'!AA:AA,'BD FRESCOS'!U:U,B72,'BD FRESCOS'!AK:AK,$D$4))))),2),"")) | F72: =IF(OR($B$8=0,E72=""),"",IF(E72<=5,"🟢 Muy Cerca",IF(E72<=10,"🟡 Cerca",IF(E72<=20,"🟠 Moderada","🔴 Lejos")))) | G72: =IF(OR($B$8=0,B72=""),"",IFERROR(ROUND(IF($D$4="TODOS",IF($B$4="TODOS",(SUMIF('BD SECOS'!Q:Q,B72,'BD SECOS'!Y:Y)+SUMIF('BD PPA'!U:U,B72,'BD PPA'!AE:AE)+SUMIF('BD FRESCOS'!U:U,B72,'BD FRESCOS'!AE:AE))/(COUNTIF('BD SECOS'!Q:Q,B72)+COUNTIF('BD PPA'!U:U,B72)+COUNTIF('BD FRESCOS'!U:U,B72)),IF($B$4="SECOS",AVERAGEIF('BD SECOS'!Q:Q,B72,'BD SECOS'!Y:Y),IF($B$4="PPA",AVERAGEIF('BD PPA'!U:U,B72,'BD PPA'!AE:AE),AVERAGEIF('BD FRESCOS'!U:U,B72,'BD FRESCOS'!AE:AE)))),IF($B$4="TODOS",(SUMIFS('BD SECOS'!Y:Y,'BD SECOS'!Q:Q,B72,'BD SECOS'!AE:AE,$D$4)+SUMIFS('BD PPA'!AE:AE,'BD PPA'!U:U,B72,'BD PPA'!AK:AK,$D$4)+SUMIFS('BD FRESCOS'!AE:AE,'BD FRESCOS'!U:U,B72,'BD FRESCOS'!AK:AK,$D$4))/(COUNTIFS('BD SECOS'!Q:Q,B72,'BD SECOS'!AE:AE,$D$4)+COUNTIFS('BD PPA'!U:U,B72,'BD PPA'!AK:AK,$D$4)+COUNTIFS('BD FRESCOS'!U:U,B72,'BD FRESCOS'!AK:AK,$D$4)),IF($B$4="SECOS",AVERAGEIFS('BD SECOS'!Y:Y,'BD SECOS'!Q:Q,B72,'BD SECOS'!AE:AE,$D$4),IF($B$4="PPA",AVERAGEIFS('BD PPA'!AE:AE,'BD PPA'!U:U,B72,'BD PPA'!AK:AK,$D$4),AVERAGEIFS('BD FRESCOS'!AE:AE,'BD FRESCOS'!U:U,B72,'BD FRESCOS'!AK:AK,$D$4))))),2),"")) | H72: =IF(OR($B$8=0,G72=""),"",IF(G72<=1,"🟢 Muy Cerca",IF(G72<=3,"🟡 Cerca",IF(G72<=5,"🟠 Moderada","🔴 Lejos")))) | I72: {=IF(OR($B$8=0,B72=""),"",IFERROR(IF($D$4="TODOS",IF($B$4="TODOS",INDEX('BD SECOS'!X:X,MATCH(B72,'BD SECOS'!Q:Q,0)),IF($B$4="SECOS",INDEX('BD SECOS'!X:X,MATCH(B72,'BD SECOS'!Q:Q,0)),IF($B$4="PPA",INDEX('BD PPA'!AD:AD,MATCH(B72,'BD PPA'!U:U,0)),INDEX('BD FRESCOS'!AD:AD,MATCH(B72,'BD FRESCOS'!U:U,0))))),IF($B$4="TODOS",IFERROR(INDEX('BD SECOS'!X:X,MATCH(1,('BD SECOS'!Q:Q=B72)*('BD SECOS'!AE:AE=$D$4),0)),IFERROR(INDEX('BD PPA'!AD:AD,MATCH(1,('BD PPA'!U:U=B72)*('BD PPA'!AK:AK=$D$4),0)),INDEX('BD FRESCOS'!AD:AD,MATCH(1,('BD FRESCOS'!U:U=B72)*('BD FRESCOS'!AK:AK=$D$4),0)))),IF($B$4="SECOS",INDEX('BD SECOS'!X:X,MATCH(1,('BD SECOS'!Q:Q=B72)*('BD SECOS'!AE:AE=$D$4),0)),IF($B$4="PPA",INDEX('BD PPA'!AD:AD,MATCH(1,('BD PPA'!U:U=B72)*('BD PPA'!AK:AK=$D$4),0)),INDEX('BD FRESCOS'!AD:AD,MATCH(1,('BD FRESCOS'!U:U=B72)*('BD FRESCOS'!AK:AK=$D$4),0)))))),""))} | J72: =IF(OR($B$8=0,B72=""),"",IF(AND(E72>20,G72>5),"⚠️ Muy lejos del CD y paraderos",IF(E72>20,"⚠️ Muy lejos del CD",IF(G72>5,"⚠️ Lejos de paraderos","📍 Normal"))))
A73: =IF(OR($B$8=0,C73="",C73=0),"",35) | B73: =IF($B$8=0,"",IFERROR(IF(INDEX(Distritos!$I$7:$I$66,MATCH(SMALL(Distritos!$J$7:$J$66,35),Distritos!$J$7:$J$66,0))=0,"",INDEX(Distritos!$H$7:$H$66,MATCH(SMALL(Distritos!$J$7:$J$66,35),Distritos!$J$7:$J$66,0))),"")) | C73: =IF($B$8=0,"",IFERROR(IF(INDEX(Distritos!$I$7:$I$66,MATCH(SMALL(Distritos!$J$7:$J$66,35),Distritos!$J$7:$J$66,0))=0,"",INDEX(Distritos!$I$7:$I$66,MATCH(SMALL(Distritos!$J$7:$J$66,35),Distritos!$J$7:$J$66,0))),"")) | D73: =IF(OR($B$8=0,C73="",C73=0),"",C73/$B$8) | E73: =IF(OR($B$8=0,B73=""),"",IFERROR(ROUND(IF($D$4="TODOS",IF($B$4="TODOS",(SUMIF('BD SECOS'!Q:Q,B73,'BD SECOS'!U:U)+SUMIF('BD PPA'!U:U,B73,'BD PPA'!AA:AA)+SUMIF('BD FRESCOS'!U:U,B73,'BD FRESCOS'!AA:AA))/(COUNTIF('BD SECOS'!Q:Q,B73)+COUNTIF('BD PPA'!U:U,B73)+COUNTIF('BD FRESCOS'!U:U,B73)),IF($B$4="SECOS",AVERAGEIF('BD SECOS'!Q:Q,B73,'BD SECOS'!U:U),IF($B$4="PPA",AVERAGEIF('BD PPA'!U:U,B73,'BD PPA'!AA:AA),AVERAGEIF('BD FRESCOS'!U:U,B73,'BD FRESCOS'!AA:AA)))),IF($B$4="TODOS",(SUMIFS('BD SECOS'!U:U,'BD SECOS'!Q:Q,B73,'BD SECOS'!AE:AE,$D$4)+SUMIFS('BD PPA'!AA:AA,'BD PPA'!U:U,B73,'BD PPA'!AK:AK,$D$4)+SUMIFS('BD FRESCOS'!AA:AA,'BD FRESCOS'!U:U,B73,'BD FRESCOS'!AK:AK,$D$4))/(COUNTIFS('BD SECOS'!Q:Q,B73,'BD SECOS'!AE:AE,$D$4)+COUNTIFS('BD PPA'!U:U,B73,'BD PPA'!AK:AK,$D$4)+COUNTIFS('BD FRESCOS'!U:U,B73,'BD FRESCOS'!AK:AK,$D$4)),IF($B$4="SECOS",AVERAGEIFS('BD SECOS'!U:U,'BD SECOS'!Q:Q,B73,'BD SECOS'!AE:AE,$D$4),IF($B$4="PPA",AVERAGEIFS('BD PPA'!AA:AA,'BD PPA'!U:U,B73,'BD PPA'!AK:AK,$D$4),AVERAGEIFS('BD FRESCOS'!AA:AA,'BD FRESCOS'!U:U,B73,'BD FRESCOS'!AK:AK,$D$4))))),2),"")) | F73: =IF(OR($B$8=0,E73=""),"",IF(E73<=5,"🟢 Muy Cerca",IF(E73<=10,"🟡 Cerca",IF(E73<=20,"🟠 Moderada","🔴 Lejos")))) | G73: =IF(OR($B$8=0,B73=""),"",IFERROR(ROUND(IF($D$4="TODOS",IF($B$4="TODOS",(SUMIF('BD SECOS'!Q:Q,B73,'BD SECOS'!Y:Y)+SUMIF('BD PPA'!U:U,B73,'BD PPA'!AE:AE)+SUMIF('BD FRESCOS'!U:U,B73,'BD FRESCOS'!AE:AE))/(COUNTIF('BD SECOS'!Q:Q,B73)+COUNTIF('BD PPA'!U:U,B73)+COUNTIF('BD FRESCOS'!U:U,B73)),IF($B$4="SECOS",AVERAGEIF('BD SECOS'!Q:Q,B73,'BD SECOS'!Y:Y),IF($B$4="PPA",AVERAGEIF('BD PPA'!U:U,B73,'BD PPA'!AE:AE),AVERAGEIF('BD FRESCOS'!U:U,B73,'BD FRESCOS'!AE:AE)))),IF($B$4="TODOS",(SUMIFS('BD SECOS'!Y:Y,'BD SECOS'!Q:Q,B73,'BD SECOS'!AE:AE,$D$4)+SUMIFS('BD PPA'!AE:AE,'BD PPA'!U:U,B73,'BD PPA'!AK:AK,$D$4)+SUMIFS('BD FRESCOS'!AE:AE,'BD FRESCOS'!U:U,B73,'BD FRESCOS'!AK:AK,$D$4))/(COUNTIFS('BD SECOS'!Q:Q,B73,'BD SECOS'!AE:AE,$D$4)+COUNTIFS('BD PPA'!U:U,B73,'BD PPA'!AK:AK,$D$4)+COUNTIFS('BD FRESCOS'!U:U,B73,'BD FRESCOS'!AK:AK,$D$4)),IF($B$4="SECOS",AVERAGEIFS('BD SECOS'!Y:Y,'BD SECOS'!Q:Q,B73,'BD SECOS'!AE:AE,$D$4),IF($B$4="PPA",AVERAGEIFS('BD PPA'!AE:AE,'BD PPA'!U:U,B73,'BD PPA'!AK:AK,$D$4),AVERAGEIFS('BD FRESCOS'!AE:AE,'BD FRESCOS'!U:U,B73,'BD FRESCOS'!AK:AK,$D$4))))),2),"")) | H73: =IF(OR($B$8=0,G73=""),"",IF(G73<=1,"🟢 Muy Cerca",IF(G73<=3,"🟡 Cerca",IF(G73<=5,"🟠 Moderada","🔴 Lejos")))) | I73: {=IF(OR($B$8=0,B73=""),"",IFERROR(IF($D$4="TODOS",IF($B$4="TODOS",INDEX('BD SECOS'!X:X,MATCH(B73,'BD SECOS'!Q:Q,0)),IF($B$4="SECOS",INDEX('BD SECOS'!X:X,MATCH(B73,'BD SECOS'!Q:Q,0)),IF($B$4="PPA",INDEX('BD PPA'!AD:AD,MATCH(B73,'BD PPA'!U:U,0)),INDEX('BD FRESCOS'!AD:AD,MATCH(B73,'BD FRESCOS'!U:U,0))))),IF($B$4="TODOS",IFERROR(INDEX('BD SECOS'!X:X,MATCH(1,('BD SECOS'!Q:Q=B73)*('BD SECOS'!AE:AE=$D$4),0)),IFERROR(INDEX('BD PPA'!AD:AD,MATCH(1,('BD PPA'!U:U=B73)*('BD PPA'!AK:AK=$D$4),0)),INDEX('BD FRESCOS'!AD:AD,MATCH(1,('BD FRESCOS'!U:U=B73)*('BD FRESCOS'!AK:AK=$D$4),0)))),IF($B$4="SECOS",INDEX('BD SECOS'!X:X,MATCH(1,('BD SECOS'!Q:Q=B73)*('BD SECOS'!AE:AE=$D$4),0)),IF($B$4="PPA",INDEX('BD PPA'!AD:AD,MATCH(1,('BD PPA'!U:U=B73)*('BD PPA'!AK:AK=$D$4),0)),INDEX('BD FRESCOS'!AD:AD,MATCH(1,('BD FRESCOS'!U:U=B73)*('BD FRESCOS'!AK:AK=$D$4),0)))))),""))} | J73: =IF(OR($B$8=0,B73=""),"",IF(AND(E73>20,G73>5),"⚠️ Muy lejos del CD y paraderos",IF(E73>20,"⚠️ Muy lejos del CD",IF(G73>5,"⚠️ Lejos de paraderos","📍 Normal"))))
A74: =IF(OR($B$8=0,C74="",C74=0),"",36) | B74: =IF($B$8=0,"",IFERROR(IF(INDEX(Distritos!$I$7:$I$66,MATCH(SMALL(Distritos!$J$7:$J$66,36),Distritos!$J$7:$J$66,0))=0,"",INDEX(Distritos!$H$7:$H$66,MATCH(SMALL(Distritos!$J$7:$J$66,36),Distritos!$J$7:$J$66,0))),"")) | C74: =IF($B$8=0,"",IFERROR(IF(INDEX(Distritos!$I$7:$I$66,MATCH(SMALL(Distritos!$J$7:$J$66,36),Distritos!$J$7:$J$66,0))=0,"",INDEX(Distritos!$I$7:$I$66,MATCH(SMALL(Distritos!$J$7:$J$66,36),Distritos!$J$7:$J$66,0))),"")) | D74: =IF(OR($B$8=0,C74="",C74=0),"",C74/$B$8) | E74: =IF(OR($B$8=0,B74=""),"",IFERROR(ROUND(IF($D$4="TODOS",IF($B$4="TODOS",(SUMIF('BD SECOS'!Q:Q,B74,'BD SECOS'!U:U)+SUMIF('BD PPA'!U:U,B74,'BD PPA'!AA:AA)+SUMIF('BD FRESCOS'!U:U,B74,'BD FRESCOS'!AA:AA))/(COUNTIF('BD SECOS'!Q:Q,B74)+COUNTIF('BD PPA'!U:U,B74)+COUNTIF('BD FRESCOS'!U:U,B74)),IF($B$4="SECOS",AVERAGEIF('BD SECOS'!Q:Q,B74,'BD SECOS'!U:U),IF($B$4="PPA",AVERAGEIF('BD PPA'!U:U,B74,'BD PPA'!AA:AA),AVERAGEIF('BD FRESCOS'!U:U,B74,'BD FRESCOS'!AA:AA)))),IF($B$4="TODOS",(SUMIFS('BD SECOS'!U:U,'BD SECOS'!Q:Q,B74,'BD SECOS'!AE:AE,$D$4)+SUMIFS('BD PPA'!AA:AA,'BD PPA'!U:U,B74,'BD PPA'!AK:AK,$D$4)+SUMIFS('BD FRESCOS'!AA:AA,'BD FRESCOS'!U:U,B74,'BD FRESCOS'!AK:AK,$D$4))/(COUNTIFS('BD SECOS'!Q:Q,B74,'BD SECOS'!AE:AE,$D$4)+COUNTIFS('BD PPA'!U:U,B74,'BD PPA'!AK:AK,$D$4)+COUNTIFS('BD FRESCOS'!U:U,B74,'BD FRESCOS'!AK:AK,$D$4)),IF($B$4="SECOS",AVERAGEIFS('BD SECOS'!U:U,'BD SECOS'!Q:Q,B74,'BD SECOS'!AE:AE,$D$4),IF($B$4="PPA",AVERAGEIFS('BD PPA'!AA:AA,'BD PPA'!U:U,B74,'BD PPA'!AK:AK,$D$4),AVERAGEIFS('BD FRESCOS'!AA:AA,'BD FRESCOS'!U:U,B74,'BD FRESCOS'!AK:AK,$D$4))))),2),"")) | F74: =IF(OR($B$8=0,E74=""),"",IF(E74<=5,"🟢 Muy Cerca",IF(E74<=10,"🟡 Cerca",IF(E74<=20,"🟠 Moderada","🔴 Lejos")))) | G74: =IF(OR($B$8=0,B74=""),"",IFERROR(ROUND(IF($D$4="TODOS",IF($B$4="TODOS",(SUMIF('BD SECOS'!Q:Q,B74,'BD SECOS'!Y:Y)+SUMIF('BD PPA'!U:U,B74,'BD PPA'!AE:AE)+SUMIF('BD FRESCOS'!U:U,B74,'BD FRESCOS'!AE:AE))/(COUNTIF('BD SECOS'!Q:Q,B74)+COUNTIF('BD PPA'!U:U,B74)+COUNTIF('BD FRESCOS'!U:U,B74)),IF($B$4="SECOS",AVERAGEIF('BD SECOS'!Q:Q,B74,'BD SECOS'!Y:Y),IF($B$4="PPA",AVERAGEIF('BD PPA'!U:U,B74,'BD PPA'!AE:AE),AVERAGEIF('BD FRESCOS'!U:U,B74,'BD FRESCOS'!AE:AE)))),IF($B$4="TODOS",(SUMIFS('BD SECOS'!Y:Y,'BD SECOS'!Q:Q,B74,'BD SECOS'!AE:AE,$D$4)+SUMIFS('BD PPA'!AE:AE,'BD PPA'!U:U,B74,'BD PPA'!AK:AK,$D$4)+SUMIFS('BD FRESCOS'!AE:AE,'BD FRESCOS'!U:U,B74,'BD FRESCOS'!AK:AK,$D$4))/(COUNTIFS('BD SECOS'!Q:Q,B74,'BD SECOS'!AE:AE,$D$4)+COUNTIFS('BD PPA'!U:U,B74,'BD PPA'!AK:AK,$D$4)+COUNTIFS('BD FRESCOS'!U:U,B74,'BD FRESCOS'!AK:AK,$D$4)),IF($B$4="SECOS",AVERAGEIFS('BD SECOS'!Y:Y,'BD SECOS'!Q:Q,B74,'BD SECOS'!AE:AE,$D$4),IF($B$4="PPA",AVERAGEIFS('BD PPA'!AE:AE,'BD PPA'!U:U,B74,'BD PPA'!AK:AK,$D$4),AVERAGEIFS('BD FRESCOS'!AE:AE,'BD FRESCOS'!U:U,B74,'BD FRESCOS'!AK:AK,$D$4))))),2),"")) | H74: =IF(OR($B$8=0,G74=""),"",IF(G74<=1,"🟢 Muy Cerca",IF(G74<=3,"🟡 Cerca",IF(G74<=5,"🟠 Moderada","🔴 Lejos")))) | I74: {=IF(OR($B$8=0,B74=""),"",IFERROR(IF($D$4="TODOS",IF($B$4="TODOS",INDEX('BD SECOS'!X:X,MATCH(B74,'BD SECOS'!Q:Q,0)),IF($B$4="SECOS",INDEX('BD SECOS'!X:X,MATCH(B74,'BD SECOS'!Q:Q,0)),IF($B$4="PPA",INDEX('BD PPA'!AD:AD,MATCH(B74,'BD PPA'!U:U,0)),INDEX('BD FRESCOS'!AD:AD,MATCH(B74,'BD FRESCOS'!U:U,0))))),IF($B$4="TODOS",IFERROR(INDEX('BD SECOS'!X:X,MATCH(1,('BD SECOS'!Q:Q=B74)*('BD SECOS'!AE:AE=$D$4),0)),IFERROR(INDEX('BD PPA'!AD:AD,MATCH(1,('BD PPA'!U:U=B74)*('BD PPA'!AK:AK=$D$4),0)),INDEX('BD FRESCOS'!AD:AD,MATCH(1,('BD FRESCOS'!U:U=B74)*('BD FRESCOS'!AK:AK=$D$4),0)))),IF($B$4="SECOS",INDEX('BD SECOS'!X:X,MATCH(1,('BD SECOS'!Q:Q=B74)*('BD SECOS'!AE:AE=$D$4),0)),IF($B$4="PPA",INDEX('BD PPA'!AD:AD,MATCH(1,('BD PPA'!U:U=B74)*('BD PPA'!AK:AK=$D$4),0)),INDEX('BD FRESCOS'!AD:AD,MATCH(1,('BD FRESCOS'!U:U=B74)*('BD FRESCOS'!AK:AK=$D$4),0)))))),""))} | J74: =IF(OR($B$8=0,B74=""),"",IF(AND(E74>20,G74>5),"⚠️ Muy lejos del CD y paraderos",IF(E74>20,"⚠️ Muy lejos del CD",IF(G74>5,"⚠️ Lejos de paraderos","📍 Normal"))))
A75: =IF(OR($B$8=0,C75="",C75=0),"",37) | B75: =IF($B$8=0,"",IFERROR(IF(INDEX(Distritos!$I$7:$I$66,MATCH(SMALL(Distritos!$J$7:$J$66,37),Distritos!$J$7:$J$66,0))=0,"",INDEX(Distritos!$H$7:$H$66,MATCH(SMALL(Distritos!$J$7:$J$66,37),Distritos!$J$7:$J$66,0))),"")) | C75: =IF($B$8=0,"",IFERROR(IF(INDEX(Distritos!$I$7:$I$66,MATCH(SMALL(Distritos!$J$7:$J$66,37),Distritos!$J$7:$J$66,0))=0,"",INDEX(Distritos!$I$7:$I$66,MATCH(SMALL(Distritos!$J$7:$J$66,37),Distritos!$J$7:$J$66,0))),"")) | D75: =IF(OR($B$8=0,C75="",C75=0),"",C75/$B$8) | E75: =IF(OR($B$8=0,B75=""),"",IFERROR(ROUND(IF($D$4="TODOS",IF($B$4="TODOS",(SUMIF('BD SECOS'!Q:Q,B75,'BD SECOS'!U:U)+SUMIF('BD PPA'!U:U,B75,'BD PPA'!AA:AA)+SUMIF('BD FRESCOS'!U:U,B75,'BD FRESCOS'!AA:AA))/(COUNTIF('BD SECOS'!Q:Q,B75)+COUNTIF('BD PPA'!U:U,B75)+COUNTIF('BD FRESCOS'!U:U,B75)),IF($B$4="SECOS",AVERAGEIF('BD SECOS'!Q:Q,B75,'BD SECOS'!U:U),IF($B$4="PPA",AVERAGEIF('BD PPA'!U:U,B75,'BD PPA'!AA:AA),AVERAGEIF('BD FRESCOS'!U:U,B75,'BD FRESCOS'!AA:AA)))),IF($B$4="TODOS",(SUMIFS('BD SECOS'!U:U,'BD SECOS'!Q:Q,B75,'BD SECOS'!AE:AE,$D$4)+SUMIFS('BD PPA'!AA:AA,'BD PPA'!U:U,B75,'BD PPA'!AK:AK,$D$4)+SUMIFS('BD FRESCOS'!AA:AA,'BD FRESCOS'!U:U,B75,'BD FRESCOS'!AK:AK,$D$4))/(COUNTIFS('BD SECOS'!Q:Q,B75,'BD SECOS'!AE:AE,$D$4)+COUNTIFS('BD PPA'!U:U,B75,'BD PPA'!AK:AK,$D$4)+COUNTIFS('BD FRESCOS'!U:U,B75,'BD FRESCOS'!AK:AK,$D$4)),IF($B$4="SECOS",AVERAGEIFS('BD SECOS'!U:U,'BD SECOS'!Q:Q,B75,'BD SECOS'!AE:AE,$D$4),IF($B$4="PPA",AVERAGEIFS('BD PPA'!AA:AA,'BD PPA'!U:U,B75,'BD PPA'!AK:AK,$D$4),AVERAGEIFS('BD FRESCOS'!AA:AA,'BD FRESCOS'!U:U,B75,'BD FRESCOS'!AK:AK,$D$4))))),2),"")) | F75: =IF(OR($B$8=0,E75=""),"",IF(E75<=5,"🟢 Muy Cerca",IF(E75<=10,"🟡 Cerca",IF(E75<=20,"🟠 Moderada","🔴 Lejos")))) | G75: =IF(OR($B$8=0,B75=""),"",IFERROR(ROUND(IF($D$4="TODOS",IF($B$4="TODOS",(SUMIF('BD SECOS'!Q:Q,B75,'BD SECOS'!Y:Y)+SUMIF('BD PPA'!U:U,B75,'BD PPA'!AE:AE)+SUMIF('BD FRESCOS'!U:U,B75,'BD FRESCOS'!AE:AE))/(COUNTIF('BD SECOS'!Q:Q,B75)+COUNTIF('BD PPA'!U:U,B75)+COUNTIF('BD FRESCOS'!U:U,B75)),IF($B$4="SECOS",AVERAGEIF('BD SECOS'!Q:Q,B75,'BD SECOS'!Y:Y),IF($B$4="PPA",AVERAGEIF('BD PPA'!U:U,B75,'BD PPA'!AE:AE),AVERAGEIF('BD FRESCOS'!U:U,B75,'BD FRESCOS'!AE:AE)))),IF($B$4="TODOS",(SUMIFS('BD SECOS'!Y:Y,'BD SECOS'!Q:Q,B75,'BD SECOS'!AE:AE,$D$4)+SUMIFS('BD PPA'!AE:AE,'BD PPA'!U:U,B75,'BD PPA'!AK:AK,$D$4)+SUMIFS('BD FRESCOS'!AE:AE,'BD FRESCOS'!U:U,B75,'BD FRESCOS'!AK:AK,$D$4))/(COUNTIFS('BD SECOS'!Q:Q,B75,'BD SECOS'!AE:AE,$D$4)+COUNTIFS('BD PPA'!U:U,B75,'BD PPA'!AK:AK,$D$4)+COUNTIFS('BD FRESCOS'!U:U,B75,'BD FRESCOS'!AK:AK,$D$4)),IF($B$4="SECOS",AVERAGEIFS('BD SECOS'!Y:Y,'BD SECOS'!Q:Q,B75,'BD SECOS'!AE:AE,$D$4),IF($B$4="PPA",AVERAGEIFS('BD PPA'!AE:AE,'BD PPA'!U:U,B75,'BD PPA'!AK:AK,$D$4),AVERAGEIFS('BD FRESCOS'!AE:AE,'BD FRESCOS'!U:U,B75,'BD FRESCOS'!AK:AK,$D$4))))),2),"")) | H75: =IF(OR($B$8=0,G75=""),"",IF(G75<=1,"🟢 Muy Cerca",IF(G75<=3,"🟡 Cerca",IF(G75<=5,"🟠 Moderada","🔴 Lejos")))) | I75: {=IF(OR($B$8=0,B75=""),"",IFERROR(IF($D$4="TODOS",IF($B$4="TODOS",INDEX('BD SECOS'!X:X,MATCH(B75,'BD SECOS'!Q:Q,0)),IF($B$4="SECOS",INDEX('BD SECOS'!X:X,MATCH(B75,'BD SECOS'!Q:Q,0)),IF($B$4="PPA",INDEX('BD PPA'!AD:AD,MATCH(B75,'BD PPA'!U:U,0)),INDEX('BD FRESCOS'!AD:AD,MATCH(B75,'BD FRESCOS'!U:U,0))))),IF($B$4="TODOS",IFERROR(INDEX('BD SECOS'!X:X,MATCH(1,('BD SECOS'!Q:Q=B75)*('BD SECOS'!AE:AE=$D$4),0)),IFERROR(INDEX('BD PPA'!AD:AD,MATCH(1,('BD PPA'!U:U=B75)*('BD PPA'!AK:AK=$D$4),0)),INDEX('BD FRESCOS'!AD:AD,MATCH(1,('BD FRESCOS'!U:U=B75)*('BD FRESCOS'!AK:AK=$D$4),0)))),IF($B$4="SECOS",INDEX('BD SECOS'!X:X,MATCH(1,('BD SECOS'!Q:Q=B75)*('BD SECOS'!AE:AE=$D$4),0)),IF($B$4="PPA",INDEX('BD PPA'!AD:AD,MATCH(1,('BD PPA'!U:U=B75)*('BD PPA'!AK:AK=$D$4),0)),INDEX('BD FRESCOS'!AD:AD,MATCH(1,('BD FRESCOS'!U:U=B75)*('BD FRESCOS'!AK:AK=$D$4),0)))))),""))} | J75: =IF(OR($B$8=0,B75=""),"",IF(AND(E75>20,G75>5),"⚠️ Muy lejos del CD y paraderos",IF(E75>20,"⚠️ Muy lejos del CD",IF(G75>5,"⚠️ Lejos de paraderos","📍 Normal"))))
A76: =IF(OR($B$8=0,C76="",C76=0),"",38) | B76: =IF($B$8=0,"",IFERROR(IF(INDEX(Distritos!$I$7:$I$66,MATCH(SMALL(Distritos!$J$7:$J$66,38),Distritos!$J$7:$J$66,0))=0,"",INDEX(Distritos!$H$7:$H$66,MATCH(SMALL(Distritos!$J$7:$J$66,38),Distritos!$J$7:$J$66,0))),"")) | C76: =IF($B$8=0,"",IFERROR(IF(INDEX(Distritos!$I$7:$I$66,MATCH(SMALL(Distritos!$J$7:$J$66,38),Distritos!$J$7:$J$66,0))=0,"",INDEX(Distritos!$I$7:$I$66,MATCH(SMALL(Distritos!$J$7:$J$66,38),Distritos!$J$7:$J$66,0))),"")) | D76: =IF(OR($B$8=0,C76="",C76=0),"",C76/$B$8) | E76: =IF(OR($B$8=0,B76=""),"",IFERROR(ROUND(IF($D$4="TODOS",IF($B$4="TODOS",(SUMIF('BD SECOS'!Q:Q,B76,'BD SECOS'!U:U)+SUMIF('BD PPA'!U:U,B76,'BD PPA'!AA:AA)+SUMIF('BD FRESCOS'!U:U,B76,'BD FRESCOS'!AA:AA))/(COUNTIF('BD SECOS'!Q:Q,B76)+COUNTIF('BD PPA'!U:U,B76)+COUNTIF('BD FRESCOS'!U:U,B76)),IF($B$4="SECOS",AVERAGEIF('BD SECOS'!Q:Q,B76,'BD SECOS'!U:U),IF($B$4="PPA",AVERAGEIF('BD PPA'!U:U,B76,'BD PPA'!AA:AA),AVERAGEIF('BD FRESCOS'!U:U,B76,'BD FRESCOS'!AA:AA)))),IF($B$4="TODOS",(SUMIFS('BD SECOS'!U:U,'BD SECOS'!Q:Q,B76,'BD SECOS'!AE:AE,$D$4)+SUMIFS('BD PPA'!AA:AA,'BD PPA'!U:U,B76,'BD PPA'!AK:AK,$D$4)+SUMIFS('BD FRESCOS'!AA:AA,'BD FRESCOS'!U:U,B76,'BD FRESCOS'!AK:AK,$D$4))/(COUNTIFS('BD SECOS'!Q:Q,B76,'BD SECOS'!AE:AE,$D$4)+COUNTIFS('BD PPA'!U:U,B76,'BD PPA'!AK:AK,$D$4)+COUNTIFS('BD FRESCOS'!U:U,B76,'BD FRESCOS'!AK:AK,$D$4)),IF($B$4="SECOS",AVERAGEIFS('BD SECOS'!U:U,'BD SECOS'!Q:Q,B76,'BD SECOS'!AE:AE,$D$4),IF($B$4="PPA",AVERAGEIFS('BD PPA'!AA:AA,'BD PPA'!U:U,B76,'BD PPA'!AK:AK,$D$4),AVERAGEIFS('BD FRESCOS'!AA:AA,'BD FRESCOS'!U:U,B76,'BD FRESCOS'!AK:AK,$D$4))))),2),"")) | F76: =IF(OR($B$8=0,E76=""),"",IF(E76<=5,"🟢 Muy Cerca",IF(E76<=10,"🟡 Cerca",IF(E76<=20,"🟠 Moderada","🔴 Lejos")))) | G76: =IF(OR($B$8=0,B76=""),"",IFERROR(ROUND(IF($D$4="TODOS",IF($B$4="TODOS",(SUMIF('BD SECOS'!Q:Q,B76,'BD SECOS'!Y:Y)+SUMIF('BD PPA'!U:U,B76,'BD PPA'!AE:AE)+SUMIF('BD FRESCOS'!U:U,B76,'BD FRESCOS'!AE:AE))/(COUNTIF('BD SECOS'!Q:Q,B76)+COUNTIF('BD PPA'!U:U,B76)+COUNTIF('BD FRESCOS'!U:U,B76)),IF($B$4="SECOS",AVERAGEIF('BD SECOS'!Q:Q,B76,'BD SECOS'!Y:Y),IF($B$4="PPA",AVERAGEIF('BD PPA'!U:U,B76,'BD PPA'!AE:AE),AVERAGEIF('BD FRESCOS'!U:U,B76,'BD FRESCOS'!AE:AE)))),IF($B$4="TODOS",(SUMIFS('BD SECOS'!Y:Y,'BD SECOS'!Q:Q,B76,'BD SECOS'!AE:AE,$D$4)+SUMIFS('BD PPA'!AE:AE,'BD PPA'!U:U,B76,'BD PPA'!AK:AK,$D$4)+SUMIFS('BD FRESCOS'!AE:AE,'BD FRESCOS'!U:U,B76,'BD FRESCOS'!AK:AK,$D$4))/(COUNTIFS('BD SECOS'!Q:Q,B76,'BD SECOS'!AE:AE,$D$4)+COUNTIFS('BD PPA'!U:U,B76,'BD PPA'!AK:AK,$D$4)+COUNTIFS('BD FRESCOS'!U:U,B76,'BD FRESCOS'!AK:AK,$D$4)),IF($B$4="SECOS",AVERAGEIFS('BD SECOS'!Y:Y,'BD SECOS'!Q:Q,B76,'BD SECOS'!AE:AE,$D$4),IF($B$4="PPA",AVERAGEIFS('BD PPA'!AE:AE,'BD PPA'!U:U,B76,'BD PPA'!AK:AK,$D$4),AVERAGEIFS('BD FRESCOS'!AE:AE,'BD FRESCOS'!U:U,B76,'BD FRESCOS'!AK:AK,$D$4))))),2),"")) | H76: =IF(OR($B$8=0,G76=""),"",IF(G76<=1,"🟢 Muy Cerca",IF(G76<=3,"🟡 Cerca",IF(G76<=5,"🟠 Moderada","🔴 Lejos")))) | I76: {=IF(OR($B$8=0,B76=""),"",IFERROR(IF($D$4="TODOS",IF($B$4="TODOS",INDEX('BD SECOS'!X:X,MATCH(B76,'BD SECOS'!Q:Q,0)),IF($B$4="SECOS",INDEX('BD SECOS'!X:X,MATCH(B76,'BD SECOS'!Q:Q,0)),IF($B$4="PPA",INDEX('BD PPA'!AD:AD,MATCH(B76,'BD PPA'!U:U,0)),INDEX('BD FRESCOS'!AD:AD,MATCH(B76,'BD FRESCOS'!U:U,0))))),IF($B$4="TODOS",IFERROR(INDEX('BD SECOS'!X:X,MATCH(1,('BD SECOS'!Q:Q=B76)*('BD SECOS'!AE:AE=$D$4),0)),IFERROR(INDEX('BD PPA'!AD:AD,MATCH(1,('BD PPA'!U:U=B76)*('BD PPA'!AK:AK=$D$4),0)),INDEX('BD FRESCOS'!AD:AD,MATCH(1,('BD FRESCOS'!U:U=B76)*('BD FRESCOS'!AK:AK=$D$4),0)))),IF($B$4="SECOS",INDEX('BD SECOS'!X:X,MATCH(1,('BD SECOS'!Q:Q=B76)*('BD SECOS'!AE:AE=$D$4),0)),IF($B$4="PPA",INDEX('BD PPA'!AD:AD,MATCH(1,('BD PPA'!U:U=B76)*('BD PPA'!AK:AK=$D$4),0)),INDEX('BD FRESCOS'!AD:AD,MATCH(1,('BD FRESCOS'!U:U=B76)*('BD FRESCOS'!AK:AK=$D$4),0)))))),""))} | J76: =IF(OR($B$8=0,B76=""),"",IF(AND(E76>20,G76>5),"⚠️ Muy lejos del CD y paraderos",IF(E76>20,"⚠️ Muy lejos del CD",IF(G76>5,"⚠️ Lejos de paraderos","📍 Normal"))))
A77: =IF(OR($B$8=0,C77="",C77=0),"",39) | B77: =IF($B$8=0,"",IFERROR(IF(INDEX(Distritos!$I$7:$I$66,MATCH(SMALL(Distritos!$J$7:$J$66,39),Distritos!$J$7:$J$66,0))=0,"",INDEX(Distritos!$H$7:$H$66,MATCH(SMALL(Distritos!$J$7:$J$66,39),Distritos!$J$7:$J$66,0))),"")) | C77: =IF($B$8=0,"",IFERROR(IF(INDEX(Distritos!$I$7:$I$66,MATCH(SMALL(Distritos!$J$7:$J$66,39),Distritos!$J$7:$J$66,0))=0,"",INDEX(Distritos!$I$7:$I$66,MATCH(SMALL(Distritos!$J$7:$J$66,39),Distritos!$J$7:$J$66,0))),"")) | D77: =IF(OR($B$8=0,C77="",C77=0),"",C77/$B$8) | E77: =IF(OR($B$8=0,B77=""),"",IFERROR(ROUND(IF($D$4="TODOS",IF($B$4="TODOS",(SUMIF('BD SECOS'!Q:Q,B77,'BD SECOS'!U:U)+SUMIF('BD PPA'!U:U,B77,'BD PPA'!AA:AA)+SUMIF('BD FRESCOS'!U:U,B77,'BD FRESCOS'!AA:AA))/(COUNTIF('BD SECOS'!Q:Q,B77)+COUNTIF('BD PPA'!U:U,B77)+COUNTIF('BD FRESCOS'!U:U,B77)),IF($B$4="SECOS",AVERAGEIF('BD SECOS'!Q:Q,B77,'BD SECOS'!U:U),IF($B$4="PPA",AVERAGEIF('BD PPA'!U:U,B77,'BD PPA'!AA:AA),AVERAGEIF('BD FRESCOS'!U:U,B77,'BD FRESCOS'!AA:AA)))),IF($B$4="TODOS",(SUMIFS('BD SECOS'!U:U,'BD SECOS'!Q:Q,B77,'BD SECOS'!AE:AE,$D$4)+SUMIFS('BD PPA'!AA:AA,'BD PPA'!U:U,B77,'BD PPA'!AK:AK,$D$4)+SUMIFS('BD FRESCOS'!AA:AA,'BD FRESCOS'!U:U,B77,'BD FRESCOS'!AK:AK,$D$4))/(COUNTIFS('BD SECOS'!Q:Q,B77,'BD SECOS'!AE:AE,$D$4)+COUNTIFS('BD PPA'!U:U,B77,'BD PPA'!AK:AK,$D$4)+COUNTIFS('BD FRESCOS'!U:U,B77,'BD FRESCOS'!AK:AK,$D$4)),IF($B$4="SECOS",AVERAGEIFS('BD SECOS'!U:U,'BD SECOS'!Q:Q,B77,'BD SECOS'!AE:AE,$D$4),IF($B$4="PPA",AVERAGEIFS('BD PPA'!AA:AA,'BD PPA'!U:U,B77,'BD PPA'!AK:AK,$D$4),AVERAGEIFS('BD FRESCOS'!AA:AA,'BD FRESCOS'!U:U,B77,'BD FRESCOS'!AK:AK,$D$4))))),2),"")) | F77: =IF(OR($B$8=0,E77=""),"",IF(E77<=5,"🟢 Muy Cerca",IF(E77<=10,"🟡 Cerca",IF(E77<=20,"🟠 Moderada","🔴 Lejos")))) | G77: =IF(OR($B$8=0,B77=""),"",IFERROR(ROUND(IF($D$4="TODOS",IF($B$4="TODOS",(SUMIF('BD SECOS'!Q:Q,B77,'BD SECOS'!Y:Y)+SUMIF('BD PPA'!U:U,B77,'BD PPA'!AE:AE)+SUMIF('BD FRESCOS'!U:U,B77,'BD FRESCOS'!AE:AE))/(COUNTIF('BD SECOS'!Q:Q,B77)+COUNTIF('BD PPA'!U:U,B77)+COUNTIF('BD FRESCOS'!U:U,B77)),IF($B$4="SECOS",AVERAGEIF('BD SECOS'!Q:Q,B77,'BD SECOS'!Y:Y),IF($B$4="PPA",AVERAGEIF('BD PPA'!U:U,B77,'BD PPA'!AE:AE),AVERAGEIF('BD FRESCOS'!U:U,B77,'BD FRESCOS'!AE:AE)))),IF($B$4="TODOS",(SUMIFS('BD SECOS'!Y:Y,'BD SECOS'!Q:Q,B77,'BD SECOS'!AE:AE,$D$4)+SUMIFS('BD PPA'!AE:AE,'BD PPA'!U:U,B77,'BD PPA'!AK:AK,$D$4)+SUMIFS('BD FRESCOS'!AE:AE,'BD FRESCOS'!U:U,B77,'BD FRESCOS'!AK:AK,$D$4))/(COUNTIFS('BD SECOS'!Q:Q,B77,'BD SECOS'!AE:AE,$D$4)+COUNTIFS('BD PPA'!U:U,B77,'BD PPA'!AK:AK,$D$4)+COUNTIFS('BD FRESCOS'!U:U,B77,'BD FRESCOS'!AK:AK,$D$4)),IF($B$4="SECOS",AVERAGEIFS('BD SECOS'!Y:Y,'BD SECOS'!Q:Q,B77,'BD SECOS'!AE:AE,$D$4),IF($B$4="PPA",AVERAGEIFS('BD PPA'!AE:AE,'BD PPA'!U:U,B77,'BD PPA'!AK:AK,$D$4),AVERAGEIFS('BD FRESCOS'!AE:AE,'BD FRESCOS'!U:U,B77,'BD FRESCOS'!AK:AK,$D$4))))),2),"")) | H77: =IF(OR($B$8=0,G77=""),"",IF(G77<=1,"🟢 Muy Cerca",IF(G77<=3,"🟡 Cerca",IF(G77<=5,"🟠 Moderada","🔴 Lejos")))) | I77: {=IF(OR($B$8=0,B77=""),"",IFERROR(IF($D$4="TODOS",IF($B$4="TODOS",INDEX('BD SECOS'!X:X,MATCH(B77,'BD SECOS'!Q:Q,0)),IF($B$4="SECOS",INDEX('BD SECOS'!X:X,MATCH(B77,'BD SECOS'!Q:Q,0)),IF($B$4="PPA",INDEX('BD PPA'!AD:AD,MATCH(B77,'BD PPA'!U:U,0)),INDEX('BD FRESCOS'!AD:AD,MATCH(B77,'BD FRESCOS'!U:U,0))))),IF($B$4="TODOS",IFERROR(INDEX('BD SECOS'!X:X,MATCH(1,('BD SECOS'!Q:Q=B77)*('BD SECOS'!AE:AE=$D$4),0)),IFERROR(INDEX('BD PPA'!AD:AD,MATCH(1,('BD PPA'!U:U=B77)*('BD PPA'!AK:AK=$D$4),0)),INDEX('BD FRESCOS'!AD:AD,MATCH(1,('BD FRESCOS'!U:U=B77)*('BD FRESCOS'!AK:AK=$D$4),0)))),IF($B$4="SECOS",INDEX('BD SECOS'!X:X,MATCH(1,('BD SECOS'!Q:Q=B77)*('BD SECOS'!AE:AE=$D$4),0)),IF($B$4="PPA",INDEX('BD PPA'!AD:AD,MATCH(1,('BD PPA'!U:U=B77)*('BD PPA'!AK:AK=$D$4),0)),INDEX('BD FRESCOS'!AD:AD,MATCH(1,('BD FRESCOS'!U:U=B77)*('BD FRESCOS'!AK:AK=$D$4),0)))))),""))} | J77: =IF(OR($B$8=0,B77=""),"",IF(AND(E77>20,G77>5),"⚠️ Muy lejos del CD y paraderos",IF(E77>20,"⚠️ Muy lejos del CD",IF(G77>5,"⚠️ Lejos de paraderos","📍 Normal"))))
A78: =IF(OR($B$8=0,C78="",C78=0),"",40) | B78: =IF($B$8=0,"",IFERROR(IF(INDEX(Distritos!$I$7:$I$66,MATCH(SMALL(Distritos!$J$7:$J$66,40),Distritos!$J$7:$J$66,0))=0,"",INDEX(Distritos!$H$7:$H$66,MATCH(SMALL(Distritos!$J$7:$J$66,40),Distritos!$J$7:$J$66,0))),"")) | C78: =IF($B$8=0,"",IFERROR(IF(INDEX(Distritos!$I$7:$I$66,MATCH(SMALL(Distritos!$J$7:$J$66,40),Distritos!$J$7:$J$66,0))=0,"",INDEX(Distritos!$I$7:$I$66,MATCH(SMALL(Distritos!$J$7:$J$66,40),Distritos!$J$7:$J$66,0))),"")) | D78: =IF(OR($B$8=0,C78="",C78=0),"",C78/$B$8) | E78: =IF(OR($B$8=0,B78=""),"",IFERROR(ROUND(IF($D$4="TODOS",IF($B$4="TODOS",(SUMIF('BD SECOS'!Q:Q,B78,'BD SECOS'!U:U)+SUMIF('BD PPA'!U:U,B78,'BD PPA'!AA:AA)+SUMIF('BD FRESCOS'!U:U,B78,'BD FRESCOS'!AA:AA))/(COUNTIF('BD SECOS'!Q:Q,B78)+COUNTIF('BD PPA'!U:U,B78)+COUNTIF('BD FRESCOS'!U:U,B78)),IF($B$4="SECOS",AVERAGEIF('BD SECOS'!Q:Q,B78,'BD SECOS'!U:U),IF($B$4="PPA",AVERAGEIF('BD PPA'!U:U,B78,'BD PPA'!AA:AA),AVERAGEIF('BD FRESCOS'!U:U,B78,'BD FRESCOS'!AA:AA)))),IF($B$4="TODOS",(SUMIFS('BD SECOS'!U:U,'BD SECOS'!Q:Q,B78,'BD SECOS'!AE:AE,$D$4)+SUMIFS('BD PPA'!AA:AA,'BD PPA'!U:U,B78,'BD PPA'!AK:AK,$D$4)+SUMIFS('BD FRESCOS'!AA:AA,'BD FRESCOS'!U:U,B78,'BD FRESCOS'!AK:AK,$D$4))/(COUNTIFS('BD SECOS'!Q:Q,B78,'BD SECOS'!AE:AE,$D$4)+COUNTIFS('BD PPA'!U:U,B78,'BD PPA'!AK:AK,$D$4)+COUNTIFS('BD FRESCOS'!U:U,B78,'BD FRESCOS'!AK:AK,$D$4)),IF($B$4="SECOS",AVERAGEIFS('BD SECOS'!U:U,'BD SECOS'!Q:Q,B78,'BD SECOS'!AE:AE,$D$4),IF($B$4="PPA",AVERAGEIFS('BD PPA'!AA:AA,'BD PPA'!U:U,B78,'BD PPA'!AK:AK,$D$4),AVERAGEIFS('BD FRESCOS'!AA:AA,'BD FRESCOS'!U:U,B78,'BD FRESCOS'!AK:AK,$D$4))))),2),"")) | F78: =IF(OR($B$8=0,E78=""),"",IF(E78<=5,"🟢 Muy Cerca",IF(E78<=10,"🟡 Cerca",IF(E78<=20,"🟠 Moderada","🔴 Lejos")))) | G78: =IF(OR($B$8=0,B78=""),"",IFERROR(ROUND(IF($D$4="TODOS",IF($B$4="TODOS",(SUMIF('BD SECOS'!Q:Q,B78,'BD SECOS'!Y:Y)+SUMIF('BD PPA'!U:U,B78,'BD PPA'!AE:AE)+SUMIF('BD FRESCOS'!U:U,B78,'BD FRESCOS'!AE:AE))/(COUNTIF('BD SECOS'!Q:Q,B78)+COUNTIF('BD PPA'!U:U,B78)+COUNTIF('BD FRESCOS'!U:U,B78)),IF($B$4="SECOS",AVERAGEIF('BD SECOS'!Q:Q,B78,'BD SECOS'!Y:Y),IF($B$4="PPA",AVERAGEIF('BD PPA'!U:U,B78,'BD PPA'!AE:AE),AVERAGEIF('BD FRESCOS'!U:U,B78,'BD FRESCOS'!AE:AE)))),IF($B$4="TODOS",(SUMIFS('BD SECOS'!Y:Y,'BD SECOS'!Q:Q,B78,'BD SECOS'!AE:AE,$D$4)+SUMIFS('BD PPA'!AE:AE,'BD PPA'!U:U,B78,'BD PPA'!AK:AK,$D$4)+SUMIFS('BD FRESCOS'!AE:AE,'BD FRESCOS'!U:U,B78,'BD FRESCOS'!AK:AK,$D$4))/(COUNTIFS('BD SECOS'!Q:Q,B78,'BD SECOS'!AE:AE,$D$4)+COUNTIFS('BD PPA'!U:U,B78,'BD PPA'!AK:AK,$D$4)+COUNTIFS('BD FRESCOS'!U:U,B78,'BD FRESCOS'!AK:AK,$D$4)),IF($B$4="SECOS",AVERAGEIFS('BD SECOS'!Y:Y,'BD SECOS'!Q:Q,B78,'BD SECOS'!AE:AE,$D$4),IF($B$4="PPA",AVERAGEIFS('BD PPA'!AE:AE,'BD PPA'!U:U,B78,'BD PPA'!AK:AK,$D$4),AVERAGEIFS('BD FRESCOS'!AE:AE,'BD FRESCOS'!U:U,B78,'BD FRESCOS'!AK:AK,$D$4))))),2),"")) | H78: =IF(OR($B$8=0,G78=""),"",IF(G78<=1,"🟢 Muy Cerca",IF(G78<=3,"🟡 Cerca",IF(G78<=5,"🟠 Moderada","🔴 Lejos")))) | I78: {=IF(OR($B$8=0,B78=""),"",IFERROR(IF($D$4="TODOS",IF($B$4="TODOS",INDEX('BD SECOS'!X:X,MATCH(B78,'BD SECOS'!Q:Q,0)),IF($B$4="SECOS",INDEX('BD SECOS'!X:X,MATCH(B78,'BD SECOS'!Q:Q,0)),IF($B$4="PPA",INDEX('BD PPA'!AD:AD,MATCH(B78,'BD PPA'!U:U,0)),INDEX('BD FRESCOS'!AD:AD,MATCH(B78,'BD FRESCOS'!U:U,0))))),IF($B$4="TODOS",IFERROR(INDEX('BD SECOS'!X:X,MATCH(1,('BD SECOS'!Q:Q=B78)*('BD SECOS'!AE:AE=$D$4),0)),IFERROR(INDEX('BD PPA'!AD:AD,MATCH(1,('BD PPA'!U:U=B78)*('BD PPA'!AK:AK=$D$4),0)),INDEX('BD FRESCOS'!AD:AD,MATCH(1,('BD FRESCOS'!U:U=B78)*('BD FRESCOS'!AK:AK=$D$4),0)))),IF($B$4="SECOS",INDEX('BD SECOS'!X:X,MATCH(1,('BD SECOS'!Q:Q=B78)*('BD SECOS'!AE:AE=$D$4),0)),IF($B$4="PPA",INDEX('BD PPA'!AD:AD,MATCH(1,('BD PPA'!U:U=B78)*('BD PPA'!AK:AK=$D$4),0)),INDEX('BD FRESCOS'!AD:AD,MATCH(1,('BD FRESCOS'!U:U=B78)*('BD FRESCOS'!AK:AK=$D$4),0)))))),""))} | J78: =IF(OR($B$8=0,B78=""),"",IF(AND(E78>20,G78>5),"⚠️ Muy lejos del CD y paraderos",IF(E78>20,"⚠️ Muy lejos del CD",IF(G78>5,"⚠️ Lejos de paraderos","📍 Normal"))))
A79: =IF(OR($B$8=0,C79="",C79=0),"",41) | B79: =IF($B$8=0,"",IFERROR(IF(INDEX(Distritos!$I$7:$I$66,MATCH(SMALL(Distritos!$J$7:$J$66,41),Distritos!$J$7:$J$66,0))=0,"",INDEX(Distritos!$H$7:$H$66,MATCH(SMALL(Distritos!$J$7:$J$66,41),Distritos!$J$7:$J$66,0))),"")) | C79: =IF($B$8=0,"",IFERROR(IF(INDEX(Distritos!$I$7:$I$66,MATCH(SMALL(Distritos!$J$7:$J$66,41),Distritos!$J$7:$J$66,0))=0,"",INDEX(Distritos!$I$7:$I$66,MATCH(SMALL(Distritos!$J$7:$J$66,41),Distritos!$J$7:$J$66,0))),"")) | D79: =IF(OR($B$8=0,C79="",C79=0),"",C79/$B$8) | E79: =IF(OR($B$8=0,B79=""),"",IFERROR(ROUND(IF($D$4="TODOS",IF($B$4="TODOS",(SUMIF('BD SECOS'!Q:Q,B79,'BD SECOS'!U:U)+SUMIF('BD PPA'!U:U,B79,'BD PPA'!AA:AA)+SUMIF('BD FRESCOS'!U:U,B79,'BD FRESCOS'!AA:AA))/(COUNTIF('BD SECOS'!Q:Q,B79)+COUNTIF('BD PPA'!U:U,B79)+COUNTIF('BD FRESCOS'!U:U,B79)),IF($B$4="SECOS",AVERAGEIF('BD SECOS'!Q:Q,B79,'BD SECOS'!U:U),IF($B$4="PPA",AVERAGEIF('BD PPA'!U:U,B79,'BD PPA'!AA:AA),AVERAGEIF('BD FRESCOS'!U:U,B79,'BD FRESCOS'!AA:AA)))),IF($B$4="TODOS",(SUMIFS('BD SECOS'!U:U,'BD SECOS'!Q:Q,B79,'BD SECOS'!AE:AE,$D$4)+SUMIFS('BD PPA'!AA:AA,'BD PPA'!U:U,B79,'BD PPA'!AK:AK,$D$4)+SUMIFS('BD FRESCOS'!AA:AA,'BD FRESCOS'!U:U,B79,'BD FRESCOS'!AK:AK,$D$4))/(COUNTIFS('BD SECOS'!Q:Q,B79,'BD SECOS'!AE:AE,$D$4)+COUNTIFS('BD PPA'!U:U,B79,'BD PPA'!AK:AK,$D$4)+COUNTIFS('BD FRESCOS'!U:U,B79,'BD FRESCOS'!AK:AK,$D$4)),IF($B$4="SECOS",AVERAGEIFS('BD SECOS'!U:U,'BD SECOS'!Q:Q,B79,'BD SECOS'!AE:AE,$D$4),IF($B$4="PPA",AVERAGEIFS('BD PPA'!AA:AA,'BD PPA'!U:U,B79,'BD PPA'!AK:AK,$D$4),AVERAGEIFS('BD FRESCOS'!AA:AA,'BD FRESCOS'!U:U,B79,'BD FRESCOS'!AK:AK,$D$4))))),2),"")) | F79: =IF(OR($B$8=0,E79=""),"",IF(E79<=5,"🟢 Muy Cerca",IF(E79<=10,"🟡 Cerca",IF(E79<=20,"🟠 Moderada","🔴 Lejos")))) | G79: =IF(OR($B$8=0,B79=""),"",IFERROR(ROUND(IF($D$4="TODOS",IF($B$4="TODOS",(SUMIF('BD SECOS'!Q:Q,B79,'BD SECOS'!Y:Y)+SUMIF('BD PPA'!U:U,B79,'BD PPA'!AE:AE)+SUMIF('BD FRESCOS'!U:U,B79,'BD FRESCOS'!AE:AE))/(COUNTIF('BD SECOS'!Q:Q,B79)+COUNTIF('BD PPA'!U:U,B79)+COUNTIF('BD FRESCOS'!U:U,B79)),IF($B$4="SECOS",AVERAGEIF('BD SECOS'!Q:Q,B79,'BD SECOS'!Y:Y),IF($B$4="PPA",AVERAGEIF('BD PPA'!U:U,B79,'BD PPA'!AE:AE),AVERAGEIF('BD FRESCOS'!U:U,B79,'BD FRESCOS'!AE:AE)))),IF($B$4="TODOS",(SUMIFS('BD SECOS'!Y:Y,'BD SECOS'!Q:Q,B79,'BD SECOS'!AE:AE,$D$4)+SUMIFS('BD PPA'!AE:AE,'BD PPA'!U:U,B79,'BD PPA'!AK:AK,$D$4)+SUMIFS('BD FRESCOS'!AE:AE,'BD FRESCOS'!U:U,B79,'BD FRESCOS'!AK:AK,$D$4))/(COUNTIFS('BD SECOS'!Q:Q,B79,'BD SECOS'!AE:AE,$D$4)+COUNTIFS('BD PPA'!U:U,B79,'BD PPA'!AK:AK,$D$4)+COUNTIFS('BD FRESCOS'!U:U,B79,'BD FRESCOS'!AK:AK,$D$4)),IF($B$4="SECOS",AVERAGEIFS('BD SECOS'!Y:Y,'BD SECOS'!Q:Q,B79,'BD SECOS'!AE:AE,$D$4),IF($B$4="PPA",AVERAGEIFS('BD PPA'!AE:AE,'BD PPA'!U:U,B79,'BD PPA'!AK:AK,$D$4),AVERAGEIFS('BD FRESCOS'!AE:AE,'BD FRESCOS'!U:U,B79,'BD FRESCOS'!AK:AK,$D$4))))),2),"")) | H79: =IF(OR($B$8=0,G79=""),"",IF(G79<=1,"🟢 Muy Cerca",IF(G79<=3,"🟡 Cerca",IF(G79<=5,"🟠 Moderada","🔴 Lejos")))) | I79: {=IF(OR($B$8=0,B79=""),"",IFERROR(IF($D$4="TODOS",IF($B$4="TODOS",INDEX('BD SECOS'!X:X,MATCH(B79,'BD SECOS'!Q:Q,0)),IF($B$4="SECOS",INDEX('BD SECOS'!X:X,MATCH(B79,'BD SECOS'!Q:Q,0)),IF($B$4="PPA",INDEX('BD PPA'!AD:AD,MATCH(B79,'BD PPA'!U:U,0)),INDEX('BD FRESCOS'!AD:AD,MATCH(B79,'BD FRESCOS'!U:U,0))))),IF($B$4="TODOS",IFERROR(INDEX('BD SECOS'!X:X,MATCH(1,('BD SECOS'!Q:Q=B79)*('BD SECOS'!AE:AE=$D$4),0)),IFERROR(INDEX('BD PPA'!AD:AD,MATCH(1,('BD PPA'!U:U=B79)*('BD PPA'!AK:AK=$D$4),0)),INDEX('BD FRESCOS'!AD:AD,MATCH(1,('BD FRESCOS'!U:U=B79)*('BD FRESCOS'!AK:AK=$D$4),0)))),IF($B$4="SECOS",INDEX('BD SECOS'!X:X,MATCH(1,('BD SECOS'!Q:Q=B79)*('BD SECOS'!AE:AE=$D$4),0)),IF($B$4="PPA",INDEX('BD PPA'!AD:AD,MATCH(1,('BD PPA'!U:U=B79)*('BD PPA'!AK:AK=$D$4),0)),INDEX('BD FRESCOS'!AD:AD,MATCH(1,('BD FRESCOS'!U:U=B79)*('BD FRESCOS'!AK:AK=$D$4),0)))))),""))} | J79: =IF(OR($B$8=0,B79=""),"",IF(AND(E79>20,G79>5),"⚠️ Muy lejos del CD y paraderos",IF(E79>20,"⚠️ Muy lejos del CD",IF(G79>5,"⚠️ Lejos de paraderos","📍 Normal"))))
A80: =IF(OR($B$8=0,C80="",C80=0),"",42) | B80: =IF($B$8=0,"",IFERROR(IF(INDEX(Distritos!$I$7:$I$66,MATCH(SMALL(Distritos!$J$7:$J$66,42),Distritos!$J$7:$J$66,0))=0,"",INDEX(Distritos!$H$7:$H$66,MATCH(SMALL(Distritos!$J$7:$J$66,42),Distritos!$J$7:$J$66,0))),"")) | C80: =IF($B$8=0,"",IFERROR(IF(INDEX(Distritos!$I$7:$I$66,MATCH(SMALL(Distritos!$J$7:$J$66,42),Distritos!$J$7:$J$66,0))=0,"",INDEX(Distritos!$I$7:$I$66,MATCH(SMALL(Distritos!$J$7:$J$66,42),Distritos!$J$7:$J$66,0))),"")) | D80: =IF(OR($B$8=0,C80="",C80=0),"",C80/$B$8) | E80: =IF(OR($B$8=0,B80=""),"",IFERROR(ROUND(IF($D$4="TODOS",IF($B$4="TODOS",(SUMIF('BD SECOS'!Q:Q,B80,'BD SECOS'!U:U)+SUMIF('BD PPA'!U:U,B80,'BD PPA'!AA:AA)+SUMIF('BD FRESCOS'!U:U,B80,'BD FRESCOS'!AA:AA))/(COUNTIF('BD SECOS'!Q:Q,B80)+COUNTIF('BD PPA'!U:U,B80)+COUNTIF('BD FRESCOS'!U:U,B80)),IF($B$4="SECOS",AVERAGEIF('BD SECOS'!Q:Q,B80,'BD SECOS'!U:U),IF($B$4="PPA",AVERAGEIF('BD PPA'!U:U,B80,'BD PPA'!AA:AA),AVERAGEIF('BD FRESCOS'!U:U,B80,'BD FRESCOS'!AA:AA)))),IF($B$4="TODOS",(SUMIFS('BD SECOS'!U:U,'BD SECOS'!Q:Q,B80,'BD SECOS'!AE:AE,$D$4)+SUMIFS('BD PPA'!AA:AA,'BD PPA'!U:U,B80,'BD PPA'!AK:AK,$D$4)+SUMIFS('BD FRESCOS'!AA:AA,'BD FRESCOS'!U:U,B80,'BD FRESCOS'!AK:AK,$D$4))/(COUNTIFS('BD SECOS'!Q:Q,B80,'BD SECOS'!AE:AE,$D$4)+COUNTIFS('BD PPA'!U:U,B80,'BD PPA'!AK:AK,$D$4)+COUNTIFS('BD FRESCOS'!U:U,B80,'BD FRESCOS'!AK:AK,$D$4)),IF($B$4="SECOS",AVERAGEIFS('BD SECOS'!U:U,'BD SECOS'!Q:Q,B80,'BD SECOS'!AE:AE,$D$4),IF($B$4="PPA",AVERAGEIFS('BD PPA'!AA:AA,'BD PPA'!U:U,B80,'BD PPA'!AK:AK,$D$4),AVERAGEIFS('BD FRESCOS'!AA:AA,'BD FRESCOS'!U:U,B80,'BD FRESCOS'!AK:AK,$D$4))))),2),"")) | F80: =IF(OR($B$8=0,E80=""),"",IF(E80<=5,"🟢 Muy Cerca",IF(E80<=10,"🟡 Cerca",IF(E80<=20,"🟠 Moderada","🔴 Lejos")))) | G80: =IF(OR($B$8=0,B80=""),"",IFERROR(ROUND(IF($D$4="TODOS",IF($B$4="TODOS",(SUMIF('BD SECOS'!Q:Q,B80,'BD SECOS'!Y:Y)+SUMIF('BD PPA'!U:U,B80,'BD PPA'!AE:AE)+SUMIF('BD FRESCOS'!U:U,B80,'BD FRESCOS'!AE:AE))/(COUNTIF('BD SECOS'!Q:Q,B80)+COUNTIF('BD PPA'!U:U,B80)+COUNTIF('BD FRESCOS'!U:U,B80)),IF($B$4="SECOS",AVERAGEIF('BD SECOS'!Q:Q,B80,'BD SECOS'!Y:Y),IF($B$4="PPA",AVERAGEIF('BD PPA'!U:U,B80,'BD PPA'!AE:AE),AVERAGEIF('BD FRESCOS'!U:U,B80,'BD FRESCOS'!AE:AE)))),IF($B$4="TODOS",(SUMIFS('BD SECOS'!Y:Y,'BD SECOS'!Q:Q,B80,'BD SECOS'!AE:AE,$D$4)+SUMIFS('BD PPA'!AE:AE,'BD PPA'!U:U,B80,'BD PPA'!AK:AK,$D$4)+SUMIFS('BD FRESCOS'!AE:AE,'BD FRESCOS'!U:U,B80,'BD FRESCOS'!AK:AK,$D$4))/(COUNTIFS('BD SECOS'!Q:Q,B80,'BD SECOS'!AE:AE,$D$4)+COUNTIFS('BD PPA'!U:U,B80,'BD PPA'!AK:AK,$D$4)+COUNTIFS('BD FRESCOS'!U:U,B80,'BD FRESCOS'!AK:AK,$D$4)),IF($B$4="SECOS",AVERAGEIFS('BD SECOS'!Y:Y,'BD SECOS'!Q:Q,B80,'BD SECOS'!AE:AE,$D$4),IF($B$4="PPA",AVERAGEIFS('BD PPA'!AE:AE,'BD PPA'!U:U,B80,'BD PPA'!AK:AK,$D$4),AVERAGEIFS('BD FRESCOS'!AE:AE,'BD FRESCOS'!U:U,B80,'BD FRESCOS'!AK:AK,$D$4))))),2),"")) | H80: =IF(OR($B$8=0,G80=""),"",IF(G80<=1,"🟢 Muy Cerca",IF(G80<=3,"🟡 Cerca",IF(G80<=5,"🟠 Moderada","🔴 Lejos")))) | I80: {=IF(OR($B$8=0,B80=""),"",IFERROR(IF($D$4="TODOS",IF($B$4="TODOS",INDEX('BD SECOS'!X:X,MATCH(B80,'BD SECOS'!Q:Q,0)),IF($B$4="SECOS",INDEX('BD SECOS'!X:X,MATCH(B80,'BD SECOS'!Q:Q,0)),IF($B$4="PPA",INDEX('BD PPA'!AD:AD,MATCH(B80,'BD PPA'!U:U,0)),INDEX('BD FRESCOS'!AD:AD,MATCH(B80,'BD FRESCOS'!U:U,0))))),IF($B$4="TODOS",IFERROR(INDEX('BD SECOS'!X:X,MATCH(1,('BD SECOS'!Q:Q=B80)*('BD SECOS'!AE:AE=$D$4),0)),IFERROR(INDEX('BD PPA'!AD:AD,MATCH(1,('BD PPA'!U:U=B80)*('BD PPA'!AK:AK=$D$4),0)),INDEX('BD FRESCOS'!AD:AD,MATCH(1,('BD FRESCOS'!U:U=B80)*('BD FRESCOS'!AK:AK=$D$4),0)))),IF($B$4="SECOS",INDEX('BD SECOS'!X:X,MATCH(1,('BD SECOS'!Q:Q=B80)*('BD SECOS'!AE:AE=$D$4),0)),IF($B$4="PPA",INDEX('BD PPA'!AD:AD,MATCH(1,('BD PPA'!U:U=B80)*('BD PPA'!AK:AK=$D$4),0)),INDEX('BD FRESCOS'!AD:AD,MATCH(1,('BD FRESCOS'!U:U=B80)*('BD FRESCOS'!AK:AK=$D$4),0)))))),""))} | J80: =IF(OR($B$8=0,B80=""),"",IF(AND(E80>20,G80>5),"⚠️ Muy lejos del CD y paraderos",IF(E80>20,"⚠️ Muy lejos del CD",IF(G80>5,"⚠️ Lejos de paraderos","📍 Normal"))))
A81: =IF(OR($B$8=0,C81="",C81=0),"",43) | B81: =IF($B$8=0,"",IFERROR(IF(INDEX(Distritos!$I$7:$I$66,MATCH(SMALL(Distritos!$J$7:$J$66,43),Distritos!$J$7:$J$66,0))=0,"",INDEX(Distritos!$H$7:$H$66,MATCH(SMALL(Distritos!$J$7:$J$66,43),Distritos!$J$7:$J$66,0))),"")) | C81: =IF($B$8=0,"",IFERROR(IF(INDEX(Distritos!$I$7:$I$66,MATCH(SMALL(Distritos!$J$7:$J$66,43),Distritos!$J$7:$J$66,0))=0,"",INDEX(Distritos!$I$7:$I$66,MATCH(SMALL(Distritos!$J$7:$J$66,43),Distritos!$J$7:$J$66,0))),"")) | D81: =IF(OR($B$8=0,C81="",C81=0),"",C81/$B$8) | E81: =IF(OR($B$8=0,B81=""),"",IFERROR(ROUND(IF($D$4="TODOS",IF($B$4="TODOS",(SUMIF('BD SECOS'!Q:Q,B81,'BD SECOS'!U:U)+SUMIF('BD PPA'!U:U,B81,'BD PPA'!AA:AA)+SUMIF('BD FRESCOS'!U:U,B81,'BD FRESCOS'!AA:AA))/(COUNTIF('BD SECOS'!Q:Q,B81)+COUNTIF('BD PPA'!U:U,B81)+COUNTIF('BD FRESCOS'!U:U,B81)),IF($B$4="SECOS",AVERAGEIF('BD SECOS'!Q:Q,B81,'BD SECOS'!U:U),IF($B$4="PPA",AVERAGEIF('BD PPA'!U:U,B81,'BD PPA'!AA:AA),AVERAGEIF('BD FRESCOS'!U:U,B81,'BD FRESCOS'!AA:AA)))),IF($B$4="TODOS",(SUMIFS('BD SECOS'!U:U,'BD SECOS'!Q:Q,B81,'BD SECOS'!AE:AE,$D$4)+SUMIFS('BD PPA'!AA:AA,'BD PPA'!U:U,B81,'BD PPA'!AK:AK,$D$4)+SUMIFS('BD FRESCOS'!AA:AA,'BD FRESCOS'!U:U,B81,'BD FRESCOS'!AK:AK,$D$4))/(COUNTIFS('BD SECOS'!Q:Q,B81,'BD SECOS'!AE:AE,$D$4)+COUNTIFS('BD PPA'!U:U,B81,'BD PPA'!AK:AK,$D$4)+COUNTIFS('BD FRESCOS'!U:U,B81,'BD FRESCOS'!AK:AK,$D$4)),IF($B$4="SECOS",AVERAGEIFS('BD SECOS'!U:U,'BD SECOS'!Q:Q,B81,'BD SECOS'!AE:AE,$D$4),IF($B$4="PPA",AVERAGEIFS('BD PPA'!AA:AA,'BD PPA'!U:U,B81,'BD PPA'!AK:AK,$D$4),AVERAGEIFS('BD FRESCOS'!AA:AA,'BD FRESCOS'!U:U,B81,'BD FRESCOS'!AK:AK,$D$4))))),2),"")) | F81: =IF(OR($B$8=0,E81=""),"",IF(E81<=5,"🟢 Muy Cerca",IF(E81<=10,"🟡 Cerca",IF(E81<=20,"🟠 Moderada","🔴 Lejos")))) | G81: =IF(OR($B$8=0,B81=""),"",IFERROR(ROUND(IF($D$4="TODOS",IF($B$4="TODOS",(SUMIF('BD SECOS'!Q:Q,B81,'BD SECOS'!Y:Y)+SUMIF('BD PPA'!U:U,B81,'BD PPA'!AE:AE)+SUMIF('BD FRESCOS'!U:U,B81,'BD FRESCOS'!AE:AE))/(COUNTIF('BD SECOS'!Q:Q,B81)+COUNTIF('BD PPA'!U:U,B81)+COUNTIF('BD FRESCOS'!U:U,B81)),IF($B$4="SECOS",AVERAGEIF('BD SECOS'!Q:Q,B81,'BD SECOS'!Y:Y),IF($B$4="PPA",AVERAGEIF('BD PPA'!U:U,B81,'BD PPA'!AE:AE),AVERAGEIF('BD FRESCOS'!U:U,B81,'BD FRESCOS'!AE:AE)))),IF($B$4="TODOS",(SUMIFS('BD SECOS'!Y:Y,'BD SECOS'!Q:Q,B81,'BD SECOS'!AE:AE,$D$4)+SUMIFS('BD PPA'!AE:AE,'BD PPA'!U:U,B81,'BD PPA'!AK:AK,$D$4)+SUMIFS('BD FRESCOS'!AE:AE,'BD FRESCOS'!U:U,B81,'BD FRESCOS'!AK:AK,$D$4))/(COUNTIFS('BD SECOS'!Q:Q,B81,'BD SECOS'!AE:AE,$D$4)+COUNTIFS('BD PPA'!U:U,B81,'BD PPA'!AK:AK,$D$4)+COUNTIFS('BD FRESCOS'!U:U,B81,'BD FRESCOS'!AK:AK,$D$4)),IF($B$4="SECOS",AVERAGEIFS('BD SECOS'!Y:Y,'BD SECOS'!Q:Q,B81,'BD SECOS'!AE:AE,$D$4),IF($B$4="PPA",AVERAGEIFS('BD PPA'!AE:AE,'BD PPA'!U:U,B81,'BD PPA'!AK:AK,$D$4),AVERAGEIFS('BD FRESCOS'!AE:AE,'BD FRESCOS'!U:U,B81,'BD FRESCOS'!AK:AK,$D$4))))),2),"")) | H81: =IF(OR($B$8=0,G81=""),"",IF(G81<=1,"🟢 Muy Cerca",IF(G81<=3,"🟡 Cerca",IF(G81<=5,"🟠 Moderada","🔴 Lejos")))) | I81: {=IF(OR($B$8=0,B81=""),"",IFERROR(IF($D$4="TODOS",IF($B$4="TODOS",INDEX('BD SECOS'!X:X,MATCH(B81,'BD SECOS'!Q:Q,0)),IF($B$4="SECOS",INDEX('BD SECOS'!X:X,MATCH(B81,'BD SECOS'!Q:Q,0)),IF($B$4="PPA",INDEX('BD PPA'!AD:AD,MATCH(B81,'BD PPA'!U:U,0)),INDEX('BD FRESCOS'!AD:AD,MATCH(B81,'BD FRESCOS'!U:U,0))))),IF($B$4="TODOS",IFERROR(INDEX('BD SECOS'!X:X,MATCH(1,('BD SECOS'!Q:Q=B81)*('BD SECOS'!AE:AE=$D$4),0)),IFERROR(INDEX('BD PPA'!AD:AD,MATCH(1,('BD PPA'!U:U=B81)*('BD PPA'!AK:AK=$D$4),0)),INDEX('BD FRESCOS'!AD:AD,MATCH(1,('BD FRESCOS'!U:U=B81)*('BD FRESCOS'!AK:AK=$D$4),0)))),IF($B$4="SECOS",INDEX('BD SECOS'!X:X,MATCH(1,('BD SECOS'!Q:Q=B81)*('BD SECOS'!AE:AE=$D$4),0)),IF($B$4="PPA",INDEX('BD PPA'!AD:AD,MATCH(1,('BD PPA'!U:U=B81)*('BD PPA'!AK:AK=$D$4),0)),INDEX('BD FRESCOS'!AD:AD,MATCH(1,('BD FRESCOS'!U:U=B81)*('BD FRESCOS'!AK:AK=$D$4),0)))))),""))} | J81: =IF(OR($B$8=0,B81=""),"",IF(AND(E81>20,G81>5),"⚠️ Muy lejos del CD y paraderos",IF(E81>20,"⚠️ Muy lejos del CD",IF(G81>5,"⚠️ Lejos de paraderos","📍 Normal"))))
